Workbook
Name gaiyou: 設定用!$D$6:$D$15
Name lank: 設定用!$H$6:$H$14
Name mendan: 設定用!$F$6:$F$13
Name shiten: 設定用!$B$6:$B$8

Sheet シート118

Sheet シート119

Sheet シート120

Sheet シート171

Sheet シート174

Sheet シート134

Sheet シート122

Sheet シート115

Sheet シート113

Sheet シート103

Sheet 拠点別年間集計
A1: -- | F1: 1月 | G1: 2月 | H1: 3月 | I1: 4月 | J1: 5月 | K1: 6月 | L1: 7月 | M1: 8月 | N1: 9月 | O1: 10月 | P1: 11月 | Q1: 12月
C2: アポ率集計 | F2: 1月 | G2: 2月 | H2: 3月 | I2: 4月 | J2: 5月 | K2: 6月 | L2: 7月 | M2: 8月 | N2: 9月 | O2: 10月 | P2: 11月 | Q2: 12月 | R2: 年間
B3: D4 | C3: 総計 | D3: 受信件数 | F3: =INDIRECT(F$1&"!"&$B3) -> 55 | G3: =INDIRECT(G$1&"!"&$B3) -> 52 | H3: =INDIRECT(H$1&"!"&$B3) -> 68 | I3: =INDIRECT(I$1&"!"&$B3) -> 73 | J3: =INDIRECT(J$1&"!"&$B3) -> 0 | K3: =INDIRECT(K$1&"!"&$B3) -> 0 | L3: =INDIRECT(L$1&"!"&$B3) -> 0 | M3: =INDIRECT(M$1&"!"&$B3) -> 0 | ... Q3: =INDIRECT(Q$1&"!"&$B3) -> 0 | R3: =SUM(F3:Q3) -> 248
B4: D5 | D4: 面談予約件数 | F4: =INDIRECT(F$1&"!"&$B4) -> 35 | G4: =INDIRECT(G$1&"!"&$B4) -> 25 | H4: =INDIRECT(H$1&"!"&$B4) -> 44 | I4: =INDIRECT(I$1&"!"&$B4) -> 39 | J4: =INDIRECT(J$1&"!"&$B4) -> 0 | K4: =INDIRECT(K$1&"!"&$B4) -> 0 | L4: =INDIRECT(L$1&"!"&$B4) -> 0 | M4: =INDIRECT(M$1&"!"&$B4) -> 0 | ... Q4: =INDIRECT(Q$1&"!"&$B4) -> 0 | R4: =SUM(F4:Q4) -> 143
B5: D6 | D5: 面談獲得率 | F5: =INDIRECT(F$1&"!"&$B5) -> 0.63636364 | G5: =INDIRECT(G$1&"!"&$B5) -> 0.48076923 | H5: =INDIRECT(H$1&"!"&$B5) -> 0.64705882 | I5: =INDIRECT(I$1&"!"&$B5) -> 0.53424658 | J5: =INDIRECT(J$1&"!"&$B5) | K5: =INDIRECT(K$1&"!"&$B5) | L5: =INDIRECT(L$1&"!"&$B5) | M5: =INDIRECT(M$1&"!"&$B5) | ... Q5: =INDIRECT(Q$1&"!"&$B5) | R5: =R4/R3 -> 0.5766129
B7: E4 | C7: =設定用!B6 -> 横浜本店 | D7: 受信件数 | F7: =INDIRECT(F$1&"!"&$B7) -> 55 | G7: =INDIRECT(G$1&"!"&$B7) -> 51 | H7: =INDIRECT(H$1&"!"&$B7) -> 67 | I7: =INDIRECT(I$1&"!"&$B7) -> 73 | J7: =INDIRECT(J$1&"!"&$B7) -> 0 | K7: =INDIRECT(K$1&"!"&$B7) -> 0 | L7: =INDIRECT(L$1&"!"&$B7) -> 0 | M7: =INDIRECT(M$1&"!"&$B7) -> 0 | ... Q7: =INDIRECT(Q$1&"!"&$B7) -> 0 | R7: =SUM(F7:Q7) -> 246
B8: E5 | D8: 面談予約件数 | F8: =INDIRECT(F$1&"!"&$B8) -> 35 | G8: =INDIRECT(G$1&"!"&$B8) -> 24 | H8: =INDIRECT(H$1&"!"&$B8) -> 43 | I8: =INDIRECT(I$1&"!"&$B8) -> 39 | J8: =INDIRECT(J$1&"!"&$B8) -> 0 | K8: =INDIRECT(K$1&"!"&$B8) -> 0 | L8: =INDIRECT(L$1&"!"&$B8) -> 0 | M8: =INDIRECT(M$1&"!"&$B8) -> 0 | ... Q8: =INDIRECT(Q$1&"!"&$B8) -> 0 | R8: =SUM(F8:Q8) -> 141
B9: E6 | D9: 面談獲得率 | F9: =INDIRECT(F$1&"!"&$B9) -> 0.63636364 | G9: =INDIRECT(G$1&"!"&$B9) -> 0.47058824 | H9: =INDIRECT(H$1&"!"&$B9) -> 0.64179104 | I9: =INDIRECT(I$1&"!"&$B9) -> 0.53424658 | J9: =INDIRECT(J$1&"!"&$B9) | K9: =INDIRECT(K$1&"!"&$B9) | L9: =INDIRECT(L$1&"!"&$B9) | M9: =INDIRECT(M$1&"!"&$B9) | ... Q9: =INDIRECT(Q$1&"!"&$B9) | R9: =R8/R7 -> 0.57317073
B11: F4 | C11: =設定用!B7 -> 藤沢支店 | D11: 受信件数 | F11: =INDIRECT(F$1&"!"&$B11) -> 0 | G11: =INDIRECT(G$1&"!"&$B11) -> 1 | H11: =INDIRECT(H$1&"!"&$B11) -> 1 | I11: =INDIRECT(I$1&"!"&$B11) -> 0 | J11: =INDIRECT(J$1&"!"&$B11) -> 0 | K11: =INDIRECT(K$1&"!"&$B11) -> 0 | L11: =INDIRECT(L$1&"!"&$B11) -> 0 | M11: =INDIRECT(M$1&"!"&$B11) -> 0 | ... Q11: =INDIRECT(Q$1&"!"&$B11) -> 0 | R11: =SUM(F11:Q11) -> 2 | S11: =AVERAGE(E11:N11) -> 0.22222222
B12: F5 | D12: 面談予約件数 | F12: =INDIRECT(F$1&"!"&$B12) -> 0 | G12: =INDIRECT(G$1&"!"&$B12) -> 1 | H12: =INDIRECT(H$1&"!"&$B12) -> 1 | I12: =INDIRECT(I$1&"!"&$B12) -> 0 | J12: =INDIRECT(J$1&"!"&$B12) -> 0 | K12: =INDIRECT(K$1&"!"&$B12) -> 0 | L12: =INDIRECT(L$1&"!"&$B12) -> 0 | M12: =INDIRECT(M$1&"!"&$B12) -> 0 | ... Q12: =INDIRECT(Q$1&"!"&$B12) -> 0 | R12: =SUM(F12:Q12) -> 2
B13: F6 | D13: 面談獲得率 | F13: =INDIRECT(F$1&"!"&$B13) | G13: =INDIRECT(G$1&"!"&$B13) -> 1 | H13: =INDIRECT(H$1&"!"&$B13) -> 1 | I13: =INDIRECT(I$1&"!"&$B13) | J13: =INDIRECT(J$1&"!"&$B13) | K13: =INDIRECT(K$1&"!"&$B13) | L13: =INDIRECT(L$1&"!"&$B13) | M13: =INDIRECT(M$1&"!"&$B13) | ... Q13: =INDIRECT(Q$1&"!"&$B13) | R13: =R12/R11 -> 1
B15: G4 | C15: =設定用!B8 -> 渋谷支店 | D15: 受信件数 | F15: =INDIRECT(F$1&"!"&$B15) -> 0 | G15: =INDIRECT(G$1&"!"&$B15) -> 0 | H15: =INDIRECT(H$1&"!"&$B15) -> 0 | I15: =INDIRECT(I$1&"!"&$B15) -> 0 | J15: =INDIRECT(J$1&"!"&$B15) -> 0 | K15: =INDIRECT(K$1&"!"&$B15) -> 0 | L15: =INDIRECT(L$1&"!"&$B15) -> 0 | M15: =INDIRECT(M$1&"!"&$B15) -> 0 | ... Q15: =INDIRECT(Q$1&"!"&$B15) -> 0 | R15: =SUM(F15:Q15) -> 0
B16: G5 | D16: 面談予約件数 | F16: =INDIRECT(F$1&"!"&$B16) -> 0 | G16: =INDIRECT(G$1&"!"&$B16) -> 0 | H16: =INDIRECT(H$1&"!"&$B16) -> 0 | I16: =INDIRECT(I$1&"!"&$B16) -> 0 | J16: =INDIRECT(J$1&"!"&$B16) -> 0 | K16: =INDIRECT(K$1&"!"&$B16) -> 0 | L16: =INDIRECT(L$1&"!"&$B16) -> 0 | M16: =INDIRECT(M$1&"!"&$B16) -> 0 | ... Q16: =INDIRECT(Q$1&"!"&$B16) -> 0 | R16: =SUM(F16:Q16) -> 0
B17: G6 | D17: 面談獲得率 | F17: =INDIRECT(F$1&"!"&$B17) | G17: =INDIRECT(G$1&"!"&$B17) | H17: =INDIRECT(H$1&"!"&$B17) | I17: =INDIRECT(I$1&"!"&$B17) | J17: =INDIRECT(J$1&"!"&$B17) | K17: =INDIRECT(K$1&"!"&$B17) | L17: =INDIRECT(L$1&"!"&$B17) | M17: =INDIRECT(M$1&"!"&$B17) | ... Q17: =INDIRECT(Q$1&"!"&$B17) | R17: =R16/R15 -> #DIV/0!
C20: 受注率 集計 | F20: 1月 | G20: 2月 | H20: 3月 | I20: 4月 | J20: 5月 | K20: 6月 | L20: 7月 | M20: 8月 | N20: 9月 | O20: 10月 | P20: 11月 | Q20: 12月 | R20: 年間
B21: D211 | C21: 総計 | D21: 面談対応件数 | F21: =INDIRECT(F$1&"!"&$B21) -> 0 | G21: =INDIRECT(G$1&"!"&$B21) -> 7 | H21: =INDIRECT(H$1&"!"&$B21) -> 0 | I21: =INDIRECT(I$1&"!"&$B21) -> 0 | J21: =INDIRECT(J$1&"!"&$B21) -> 0 | K21: =INDIRECT(K$1&"!"&$B21) -> 0 | L21: =INDIRECT(L$1&"!"&$B21) -> 0 | M21: =INDIRECT(M$1&"!"&$B21) -> 0 | ... Q21: =INDIRECT(Q$1&"!"&$B21) -> 0 | R21: =SUM(F21:Q21) -> 7
B22: D212 | D22: 即受注 件数 | F22: =INDIRECT(F$1&"!"&$B22) -> 0 | G22: =INDIRECT(G$1&"!"&$B22) -> 0 | H22: =INDIRECT(H$1&"!"&$B22) -> 0 | I22: =INDIRECT(I$1&"!"&$B22) -> 0 | J22: =INDIRECT(J$1&"!"&$B22) | K22: =INDIRECT(K$1&"!"&$B22) -> 0 | L22: =INDIRECT(L$1&"!"&$B22) | M22: =INDIRECT(M$1&"!"&$B22) -> 0 | ... O22: =INDIRECT(O$1&"!"&$B22) -> 0 | R22: =SUM(F22:Q22) -> 0
B23: D213 | D23: 戻り受注 件数 | F23: =INDIRECT(F$1&"!"&$B23) -> 代表 | G23: =INDIRECT(G$1&"!"&$B23) -> 0.26923077 | H23: =INDIRECT(H$1&"!"&$B23) -> 代表 | I23: =INDIRECT(I$1&"!"&$B23) -> 代表 | J23: =INDIRECT(J$1&"!"&$B23) -> 0 | K23: =INDIRECT(K$1&"!"&$B23) | L23: =INDIRECT(L$1&"!"&$B23) -> 0 | M23: =INDIRECT(M$1&"!"&$B23) | ... Q23: =INDIRECT(Q$1&"!"&$B23) | R23: =SUM(F23:Q23) -> 0.26923077
B24: D214 | D24: 受注率 | F24: =INDIRECT(F$1&"!"&$B24) -> 0 | G24: =INDIRECT(G$1&"!"&$B24) -> 0 | H24: =INDIRECT(H$1&"!"&$B24) -> 0 | I24: =INDIRECT(I$1&"!"&$B24) -> 0 | J24: =INDIRECT(J$1&"!"&$B24) -> 0 | K24: =INDIRECT(K$1&"!"&$B24) -> 0 | L24: =INDIRECT(L$1&"!"&$B24) -> 0 | M24: =INDIRECT(M$1&"!"&$B24) -> 0 | ... Q24: =INDIRECT(Q$1&"!"&$B24) -> 0 | R24: =SUM(R22:R23)/R21 -> 0.038461538
B26: E211 | C26: =設定用!F6 -> 横浜本店 | D26: 面談対応件数 | F26: =INDIRECT(F$1&"!"&$B26) -> 0 | G26: =INDIRECT(G$1&"!"&$B26) -> 4 | H26: =INDIRECT(H$1&"!"&$B26) -> 0 | I26: =INDIRECT(I$1&"!"&$B26) -> 0 | J26: =INDIRECT(J$1&"!"&$B26) -> 0 | K26: =INDIRECT(K$1&"!"&$B26) -> 0 | L26: =INDIRECT(L$1&"!"&$B26) -> 0 | M26: =INDIRECT(M$1&"!"&$B26) -> 0 | ... Q26: =INDIRECT(Q$1&"!"&$B26) -> 0 | R26: =SUM(F26:Q26) -> 4
B27: E212 | D27: 即受注 件数 | F27: =INDIRECT(F$1&"!"&$B27) -> 0 | G27: =INDIRECT(G$1&"!"&$B27) -> 0 | H27: =INDIRECT(H$1&"!"&$B27) -> 0 | I27: =INDIRECT(I$1&"!"&$B27) -> 0 | J27: =INDIRECT(J$1&"!"&$B27) | K27: =INDIRECT(K$1&"!"&$B27) -> 0 | L27: =INDIRECT(L$1&"!"&$B27) | M27: =INDIRECT(M$1&"!"&$B27) -> 0 | ... Q27: =INDIRECT(Q$1&"!"&$B27) -> 0 | R27: =SUM(F27:Q27) -> 0
B28: E213 | D28: 戻り受注 件数 | F28: =INDIRECT(F$1&"!"&$B28) -> 黒田み | G28: =INDIRECT(G$1&"!"&$B28) -> 0.25 | H28: =INDIRECT(H$1&"!"&$B28) -> 黒田み | I28: =INDIRECT(I$1&"!"&$B28) -> 黒田み | J28: =INDIRECT(J$1&"!"&$B28) -> 0 | K28: =INDIRECT(K$1&"!"&$B28) | L28: =INDIRECT(L$1&"!"&$B28) -> 0 | M28: =INDIRECT(M$1&"!"&$B28) | ... Q28: =INDIRECT(Q$1&"!"&$B28) | R28: =SUM(F28:Q28) -> 0.25
B29: E214 | D29: 受注率 | F29: =INDIRECT(F$1&"!"&$B29) -> 0 | G29: =INDIRECT(G$1&"!"&$B29) -> 0 | H29: =INDIRECT(H$1&"!"&$B29) -> 0 | I29: =INDIRECT(I$1&"!"&$B29) -> 0 | J29: =INDIRECT(J$1&"!"&$B29) -> 0 | K29: =INDIRECT(K$1&"!"&$B29) -> 0 | L29: =INDIRECT(L$1&"!"&$B29) -> 0 | M29: =INDIRECT(M$1&"!"&$B29) -> 0 | ... Q29: =INDIRECT(Q$1&"!"&$B29) -> 0 | R29: =SUM(R27:R28)/R26 -> 0.0625
B31: F211 | C31: =設定用!F7 -> 藤沢支店 | D31: 面談対応件数 | F31: =INDIRECT(F$1&"!"&$B31) -> 0 | G31: =INDIRECT(G$1&"!"&$B31) -> 2 | H31: =INDIRECT(H$1&"!"&$B31) -> 0 | I31: =INDIRECT(I$1&"!"&$B31) -> 0 | J31: =INDIRECT(J$1&"!"&$B31) -> 0 | K31: =INDIRECT(K$1&"!"&$B31) -> 0 | L31: =INDIRECT(L$1&"!"&$B31) -> 0 | M31: =INDIRECT(M$1&"!"&$B31) -> 0 | ... Q31: =INDIRECT(Q$1&"!"&$B31) -> 0 | R31: =SUM(F31:Q31) -> 2
B32: F212 | D32: 即受注 件数 | F32: =INDIRECT(F$1&"!"&$B32) -> 0 | G32: =INDIRECT(G$1&"!"&$B32) -> 0 | H32: =INDIRECT(H$1&"!"&$B32) -> 0 | I32: =INDIRECT(I$1&"!"&$B32) -> 0 | J32: =INDIRECT(J$1&"!"&$B32) | K32: =INDIRECT(K$1&"!"&$B32) -> 0 | L32: =INDIRECT(L$1&"!"&$B32) | M32: =INDIRECT(M$1&"!"&$B32) -> 0 | ... Q32: =INDIRECT(Q$1&"!"&$B32) -> 0 | R32: =SUM(F32:Q32) -> 0
B33: F213 | D33: 戻り受注 件数 | F33: =INDIRECT(F$1&"!"&$B33) -> 山田 | G33: =INDIRECT(G$1&"!"&$B33) -> 0.4 | H33: =INDIRECT(H$1&"!"&$B33) -> 山田 | I33: =INDIRECT(I$1&"!"&$B33) -> 山田 | J33: =INDIRECT(J$1&"!"&$B33) -> 0 | K33: =INDIRECT(K$1&"!"&$B33) | L33: =INDIRECT(L$1&"!"&$B33) -> 0 | M33: =INDIRECT(M$1&"!"&$B33) | ... Q33: =INDIRECT(Q$1&"!"&$B33) | R33: =SUM(F33:Q33) -> 0.4
B34: F214 | D34: 受注率 | F34: =INDIRECT(F$1&"!"&$B34) -> 3 | G34: =INDIRECT(G$1&"!"&$B34) -> 0 | H34: =INDIRECT(H$1&"!"&$B34) -> 1 | I34: =INDIRECT(I$1&"!"&$B34) -> 4 | J34: =INDIRECT(J$1&"!"&$B34) -> 0 | K34: =INDIRECT(K$1&"!"&$B34) -> 0 | L34: =INDIRECT(L$1&"!"&$B34) -> 0 | M34: =INDIRECT(M$1&"!"&$B34) -> 0 | ... Q34: =INDIRECT(Q$1&"!"&$B34) -> 0 | R34: =SUM(R32:R33)/R31 -> 0.2
B36: G211 | C36: =設定用!F8 -> 渋谷支店 | D36: 面談対応件数 | F36: =INDIRECT(F$1&"!"&$B36) -> 0 | G36: =INDIRECT(G$1&"!"&$B36) -> 0 | H36: =INDIRECT(H$1&"!"&$B36) -> 0 | I36: =INDIRECT(I$1&"!"&$B36) -> 0 | J36: =INDIRECT(J$1&"!"&$B36) -> 0 | K36: =INDIRECT(K$1&"!"&$B36) -> 0 | L36: =INDIRECT(L$1&"!"&$B36) -> 0 | M36: =INDIRECT(M$1&"!"&$B36) -> 0 | ... Q36: =INDIRECT(Q$1&"!"&$B36) -> 0 | R36: =SUM(F36:Q36) -> 0
B37: G212 | D37: 即受注 件数 | F37: =INDIRECT(F$1&"!"&$B37) -> 0 | G37: =INDIRECT(G$1&"!"&$B37) -> 0 | H37: =INDIRECT(H$1&"!"&$B37) -> 0 | I37: =INDIRECT(I$1&"!"&$B37) -> 0 | J37: =INDIRECT(J$1&"!"&$B37) | K37: =INDIRECT(K$1&"!"&$B37) -> 0 | L37: =INDIRECT(L$1&"!"&$B37) | M37: =INDIRECT(M$1&"!"&$B37) -> 0 | ... Q37: =INDIRECT(Q$1&"!"&$B37) -> 0 | R37: =SUM(F37:Q37) -> 0
B38: G213 | D38: 戻り受注 件数 | F38: =INDIRECT(F$1&"!"&$B38) -> 奥章 | G38: =INDIRECT(G$1&"!"&$B38) -> 0 | H38: =INDIRECT(H$1&"!"&$B38) -> 奥章 | I38: =INDIRECT(I$1&"!"&$B38) -> 奥章 | J38: =INDIRECT(J$1&"!"&$B38) -> 0 | K38: =INDIRECT(K$1&"!"&$B38) | L38: =INDIRECT(L$1&"!"&$B38) -> 0 | M38: =INDIRECT(M$1&"!"&$B38) | ... Q38: =INDIRECT(Q$1&"!"&$B38) | R38: =SUM(F38:Q38) -> 0
B39: G214 | D39: 受注率 | F39: =INDIRECT(F$1&"!"&$B39) -> 0 | G39: =INDIRECT(G$1&"!"&$B39) -> 0 | H39: =INDIRECT(H$1&"!"&$B39) -> 0 | I39: =INDIRECT(I$1&"!"&$B39) -> 0 | J39: =INDIRECT(J$1&"!"&$B39) -> 0 | K39: =INDIRECT(K$1&"!"&$B39) -> 0 | L39: =INDIRECT(L$1&"!"&$B39) -> 0 | M39: =INDIRECT(M$1&"!"&$B39) -> 0 | ... Q39: =INDIRECT(Q$1&"!"&$B39) -> 0 | R39: =SUM(R37:R38)/R36 -> #DIV/0!
B41: H211 | C41: =設定用!F9 -> お客様先 | D41: 面談対応件数 | F41: =INDIRECT(F$1&"!"&$B41) -> 0 | G41: =INDIRECT(G$1&"!"&$B41) -> 0 | H41: =INDIRECT(H$1&"!"&$B41) -> 0 | I41: =INDIRECT(I$1&"!"&$B41) -> 0 | J41: =INDIRECT(J$1&"!"&$B41) -> 0 | K41: =INDIRECT(K$1&"!"&$B41) -> 0 | L41: =INDIRECT(L$1&"!"&$B41) -> 0 | M41: =INDIRECT(M$1&"!"&$B41) -> 0 | ... Q41: =INDIRECT(Q$1&"!"&$B41) -> 0 | R41: =SUM(F41:Q41) -> 0
B42: H212 | D42: 即受注 件数 | F42: =INDIRECT(F$1&"!"&$B42) -> 0 | G42: =INDIRECT(G$1&"!"&$B42) -> 0 | H42: =INDIRECT(H$1&"!"&$B42) -> 0 | I42: =INDIRECT(I$1&"!"&$B42) -> 0 | J42: =INDIRECT(J$1&"!"&$B42) | K42: =INDIRECT(K$1&"!"&$B42) -> 0 | L42: =INDIRECT(L$1&"!"&$B42) | M42: =INDIRECT(M$1&"!"&$B42) -> 0 | ... Q42: =INDIRECT(Q$1&"!"&$B42) -> 0 | R42: =SUM(F42:Q42) -> 0
B43: H213 | D43: 戻り受注 件数 | F43: =INDIRECT(F$1&"!"&$B43) -> 山﨑 | G43: =INDIRECT(G$1&"!"&$B43) | H43: =INDIRECT(H$1&"!"&$B43) -> 山﨑 | I43: =INDIRECT(I$1&"!"&$B43) -> 山﨑 | J43: =INDIRECT(J$1&"!"&$B43) -> 0 | K43: =INDIRECT(K$1&"!"&$B43) | L43: =INDIRECT(L$1&"!"&$B43) -> 0 | M43: =INDIRECT(M$1&"!"&$B43) | ... Q43: =INDIRECT(Q$1&"!"&$B43) | R43: =SUM(F43:Q43) -> 0
B44: H214 | D44: 受注率 | F44: =INDIRECT(F$1&"!"&$B44) -> 0 | G44: =INDIRECT(G$1&"!"&$B44) -> 0 | H44: =INDIRECT(H$1&"!"&$B44) -> 0 | I44: =INDIRECT(I$1&"!"&$B44) -> 0 | J44: =INDIRECT(J$1&"!"&$B44) -> 0 | K44: =INDIRECT(K$1&"!"&$B44) -> 0 | L44: =INDIRECT(L$1&"!"&$B44) -> 0 | M44: =INDIRECT(M$1&"!"&$B44) -> 0 | ... Q44: =INDIRECT(Q$1&"!"&$B44) -> 0 | R44: =SUM(R42:R43)/R41 -> #DIV/0!
B46: I211 | C46: =設定用!F10 -> パートナー先 | D46: 面談対応件数 | F46: =INDIRECT(F$1&"!"&$B46) -> 0 | G46: =INDIRECT(G$1&"!"&$B46) -> 0 | H46: =INDIRECT(H$1&"!"&$B46) -> 0 | I46: =INDIRECT(I$1&"!"&$B46) -> 0 | J46: =INDIRECT(J$1&"!"&$B46) -> 0 | K46: =INDIRECT(K$1&"!"&$B46) -> 0 | L46: =INDIRECT(L$1&"!"&$B46) -> 0 | M46: =INDIRECT(M$1&"!"&$B46) -> 0 | ... Q46: =INDIRECT(Q$1&"!"&$B46) -> 0 | R46: =SUM(F46:Q46) -> 0
B47: I212 | D47: 即受注 件数 | F47: =INDIRECT(F$1&"!"&$B47) -> 0 | G47: =INDIRECT(G$1&"!"&$B47) -> 0 | H47: =INDIRECT(H$1&"!"&$B47) -> 0 | I47: =INDIRECT(I$1&"!"&$B47) -> 0 | J47: =INDIRECT(J$1&"!"&$B47) | K47: =INDIRECT(K$1&"!"&$B47) -> 0 | L47: =INDIRECT(L$1&"!"&$B47) | M47: =INDIRECT(M$1&"!"&$B47) -> 0 | ... Q47: =INDIRECT(Q$1&"!"&$B47) -> 0 | R47: =SUM(F47:Q47) -> 0
B48: I213 | D48: 戻り受注 件数 | F48: =INDIRECT(F$1&"!"&$B48) -> 0 | G48: =INDIRECT(G$1&"!"&$B48) | H48: =INDIRECT(H$1&"!"&$B48) -> 0 | I48: =INDIRECT(I$1&"!"&$B48) -> 0 | J48: =INDIRECT(J$1&"!"&$B48) -> 0 | K48: =INDIRECT(K$1&"!"&$B48) | L48: =INDIRECT(L$1&"!"&$B48) -> 0 | M48: =INDIRECT(M$1&"!"&$B48) | ... Q48: =INDIRECT(Q$1&"!"&$B48) | R48: =SUM(F48:Q48) -> 0
B49: I214 | D49: 受注率 | F49: =INDIRECT(F$1&"!"&$B49) -> 0 | G49: =INDIRECT(G$1&"!"&$B49) -> 0 | H49: =INDIRECT(H$1&"!"&$B49) -> 0 | I49: =INDIRECT(I$1&"!"&$B49) -> 0 | J49: =INDIRECT(J$1&"!"&$B49) -> 0 | K49: =INDIRECT(K$1&"!"&$B49) -> 0 | L49: =INDIRECT(L$1&"!"&$B49) -> 0 | M49: =INDIRECT(M$1&"!"&$B49) -> 0 | ... Q49: =INDIRECT(Q$1&"!"&$B49) -> 0 | R49: =SUM(R47:R48)/R46 -> #DIV/0!
B51: J211 | C51: =設定用!F11 -> その他 | D51: 面談対応件数 | F51: =INDIRECT(F$1&"!"&$B51) -> 0 | G51: =INDIRECT(G$1&"!"&$B51) -> 1 | H51: =INDIRECT(H$1&"!"&$B51) -> 0 | I51: =INDIRECT(I$1&"!"&$B51) -> 0 | J51: =INDIRECT(J$1&"!"&$B51) -> 0 | K51: =INDIRECT(K$1&"!"&$B51) -> 0 | L51: =INDIRECT(L$1&"!"&$B51) -> 0 | M51: =INDIRECT(M$1&"!"&$B51) -> 0 | ... Q51: =INDIRECT(Q$1&"!"&$B51) -> 0 | R51: =SUM(F51:Q51) -> 1
B52: J212 | D52: 即受注 件数 | F52: =INDIRECT(F$1&"!"&$B52) -> 0 | G52: =INDIRECT(G$1&"!"&$B52) -> 0 | H52: =INDIRECT(H$1&"!"&$B52) -> 0 | I52: =INDIRECT(I$1&"!"&$B52) -> 0 | J52: =INDIRECT(J$1&"!"&$B52) | K52: =INDIRECT(K$1&"!"&$B52) -> 0 | L52: =INDIRECT(L$1&"!"&$B52) | M52: =INDIRECT(M$1&"!"&$B52) -> 0 | ... Q52: =INDIRECT(Q$1&"!"&$B52) -> 0 | R52: =SUM(F52:Q52) -> 0
B53: J213 | D53: 戻り受注 件数 | F53: =INDIRECT(F$1&"!"&$B53) -> 0 | G53: =INDIRECT(G$1&"!"&$B53) -> 0.5 | H53: =INDIRECT(H$1&"!"&$B53) -> 0 | I53: =INDIRECT(I$1&"!"&$B53) -> 0 | J53: =INDIRECT(J$1&"!"&$B53) -> 0 | K53: =INDIRECT(K$1&"!"&$B53) | L53: =INDIRECT(L$1&"!"&$B53) -> 0 | M53: =INDIRECT(M$1&"!"&$B53) | ... Q53: =INDIRECT(Q$1&"!"&$B53) | R53: =SUM(F53:Q53) -> 0.5
B54: J214 | D54: 受注率 | F54: =INDIRECT(F$1&"!"&$B54) -> 0 | G54: =INDIRECT(G$1&"!"&$B54) -> 0 | H54: =INDIRECT(H$1&"!"&$B54) -> 0 | I54: =INDIRECT(I$1&"!"&$B54) -> 0 | J54: =INDIRECT(J$1&"!"&$B54) -> 0 | K54: =INDIRECT(K$1&"!"&$B54) -> 0 | L54: =INDIRECT(L$1&"!"&$B54) -> 0 | M54: =INDIRECT(M$1&"!"&$B54) -> 0 | ... Q54: =INDIRECT(Q$1&"!"&$B54) -> 0 | R54: =SUM(R52:R53)/R51 -> 0.5

Sheet 担当者別受注率集計
C2: 受注率 集計 | F2: 1月 | G2: 2月 | H2: 3月 | I2: 4月 | J2: 5月 | K2: 6月 | L2: 7月 | M2: 8月 | N2: 9月 | O2: 10月 | P2: 11月 | Q2: 12月 | R2: 年間
C3: 総計 | D3: 面談対応件数 | F3: =SUM(F13,F21,F29,F37,F45,F53,F61,F69,F77,F85,F93,F101) -> 1.8333333 | G3: =SUM(G13,G21,G29,G37,G45,G53,G61,G69,G77,G85,G93,G101) -> 3 | H3: =SUM(H13,H21,H29,H37,H45,H53,H61,H69,H77,H85,H93,H101) -> 0.28571429 | I3: =SUM(I13,I21,I29,I37,I45,I53,I61,I69,I77,I85,I93,I101) -> 1.3928571 | J3: =SUM(J13,J21,J29,J37,J45,J53,J61,J69,J77,J85,J93,J101) -> 0 | K3: =SUM(K13,K21,K29,K37,K45,K53,K61,K69,K77,K85,K93,K101) -> 0 | L3: =SUM(L13,L21,L29,L37,L45,L53,L61,L69,L77,L85,L93,L101) -> 0 | M3: =SUM(M13,M21,M29,M37,M45,M53,M61,M69,M77,M85,M93,M101) -> 0 | ... Q3: =SUM(Q13,Q21,Q29,Q37,Q45,Q53,Q61,Q69,Q77,Q85,Q93,Q101) -> 0 | R3: =SUM(F3:Q3) -> 6.5119048
D4: 受注件数 | F4: =SUM(F14,F22,F30,F38,F46,F54,F62,F70,F78,F86,F94,F102) -> 0 | G4: =SUM(G14,G22,G30,G38,G46,G54,G62,G70,G78,G86,G94,G102) -> 2 | H4: =SUM(H14,H22,H30,H38,H46,H54,H62,H70,H78,H86,H94,H102) -> 0 | I4: =SUM(I14,I22,I30,I38,I46,I54,I62,I70,I78,I86,I94,I102) -> 1 | J4: =SUM(J14,J22,J30,J38,J46,J54,J62,J70,J78,J86,J94,J102) -> 0 | K4: =SUM(K14,K22,K30,K38,K46,K54,K62,K70,K78,K86,K94,K102) -> 0 | L4: =SUM(L14,L22,L30,L38,L46,L54,L62,L70,L78,L86,L94,L102) -> 0 | M4: =SUM(M14,M22,M30,M38,M46,M54,M62,M70,M78,M86,M94,M102) -> 0 | ... Q4: =SUM(Q14,Q22,Q30,Q38,Q46,Q54,Q62,Q70,Q78,Q86,Q94,Q102) -> 0 | R4: =SUM(F4:Q4) -> 3
D5: 受注率 | F5: =F4/F3 -> 0 | G5: =G4/G3 -> 0.66666667 | H5: =H4/H3 -> 0 | I5: =I4/I3 -> 0.71794872 | J5: =J4/J3 -> #DIV/0! | K5: =K4/K3 -> #DIV/0! | L5: =L4/L3 -> #DIV/0! | M5: =M4/M3 -> #DIV/0! | ... R5: =R4/R3 -> 0.4606947
D6: 即受注 件数 | F6: =SUM(F16,F24,F32,F40,F48,F56,F64,F72,F80,F88,F96,,F104) -> 0 | G6: =SUM(G16,G24,G32,G40,G48,G56,G64,G72,G80,G88,G96,,G104) -> 2 | H6: =SUM(H16,H24,H32,H40,H48,H56,H64,H72,H80,H88,H96,,H104) -> 0 | I6: =SUM(I16,I24,I32,I40,I48,I56,I64,I72,I80,I88,I96,,I104) -> 1 | J6: =SUM(J16,J24,J32,J40,J48,J56,J64,J72,J80,J88,J96,,J104) -> 0 | K6: =SUM(K16,K24,K32,K40,K48,K56,K64,K72,K80,K88,K96,,K104) -> 0 | L6: =SUM(L16,L24,L32,L40,L48,L56,L64,L72,L80,L88,L96,,L104) -> 0 | M6: =SUM(M16,M24,M32,M40,M48,M56,M64,M72,M80,M88,M96,,M104) -> 0 | ... Q6: =SUM(Q16,Q24,Q32,Q40,Q48,Q56,Q64,Q72,Q80,Q88,Q96,,Q104) -> 0 | R6: =SUM(F6:Q6) -> 3
D7: 即受注率 | F7: =F6/F$3 -> 0 | G7: =G6/G$3 -> 0.66666667 | H7: =H6/H$3 -> 0 | I7: =I6/I$3 -> 0.71794872 | J7: =J6/J$3 -> #DIV/0! | K7: =K6/K$3 -> #DIV/0! | L7: =L6/L$3 -> #DIV/0! | M7: =M6/M$3 -> #DIV/0! | ... Q7: =Q6/Q$3 -> #DIV/0! | R7: =R6/R3 -> 0.4606947
D8: 戻り受注 件数 | F8: =SUM(F18,F26,F34,F42,F50,F58,F66,F74,F82,F90,F98,F106) -> 3 | G8: =SUM(G18,G26,G34,G42,G50,G58,G66,G74,G82,G90,G98,G106) -> 0 | H8: =SUM(H18,H26,H34,H42,H50,H58,H66,H74,H82,H90,H98,H106) -> 1 | I8: =SUM(I18,I26,I34,I42,I50,I58,I66,I74,I82,I90,I98,I106) -> 2 | J8: =SUM(J18,J26,J34,J42,J50,J58,J66,J74,J82,J90,J98,J106) -> 0 | K8: =SUM(K18,K26,K34,K42,K50,K58,K66,K74,K82,K90,K98,K106) -> 0 | L8: =SUM(L18,L26,L34,L42,L50,L58,L66,L74,L82,L90,L98,L106) -> 0 | M8: =SUM(M18,M26,M34,M42,M50,M58,M66,M74,M82,M90,M98,M106) -> 0 | ... Q8: =SUM(Q18,Q26,Q34,Q42,Q50,Q58,Q66,Q74,Q82,Q90,Q98,Q106) -> 0 | R8: =SUM(F8:Q8) -> 6
D9: 戻り受注率 | F9: =F8/F$3 -> 1.6363636 | G9: =G8/G$3 -> 0 | H9: =H8/H$3 -> 3.5 | I9: =I8/I$3 -> 1.4358974 | J9: =J8/J$3 -> #DIV/0! | K9: =K8/K$3 -> #DIV/0! | L9: =L8/L$3 -> #DIV/0! | M9: =M8/M$3 -> #DIV/0! | ... Q9: =Q8/Q$3 -> #DIV/0! | R9: =R8/R3 -> 0.9213894
F11: 1月 | G11: 2月 | H11: 3月 | I11: 4月 | J11: 5月 | K11: 6月 | L11: 7月 | M11: 8月 | N11: 9月 | O11: 10月 | P11: 11月 | Q11: 12月
C12: 受注率 集計 | F12: 1月 | G12: 2月 | H12: 3月 | I12: 4月 | J12: 5月 | K12: 6月 | L12: 7月 | M12: 8月 | N12: 9月 | O12: 10月 | P12: 11月 | Q12: 12月 | R12: 年間
B13: D218 | C13: =設定用!J6 -> 代表 | D13: 面談対応件数 | F13: =INDIRECT(F$11&"!"&$B13) -> - | G13: =INDIRECT(G$11&"!"&$B13) -> 0 | H13: =INDIRECT(H$11&"!"&$B13) -> - | I13: =INDIRECT(I$11&"!"&$B13) -> - | J13: =INDIRECT(J$11&"!"&$B13) -> - | K13: =INDIRECT(K$11&"!"&$B13) -> 0 | L13: =INDIRECT(L$11&"!"&$B13) -> - | M13: =INDIRECT(M$11&"!"&$B13) -> 0 | ... Q13: =INDIRECT(Q$11&"!"&$B13) -> 0 | R13: =SUM(F13:Q13) -> 0
B14: D219 | D14: 受注件数 | F14: =INDIRECT(F$11&"!"&$B14) -> 0 | G14: =INDIRECT(G$11&"!"&$B14) -> - | H14: =INDIRECT(H$11&"!"&$B14) -> 0 | I14: =INDIRECT(I$11&"!"&$B14) -> 0 | J14: =INDIRECT(J$11&"!"&$B14) -> 0 | K14: =INDIRECT(K$11&"!"&$B14) -> - | L14: =INDIRECT(L$11&"!"&$B14) -> 0 | M14: =INDIRECT(M$11&"!"&$B14) -> - | ... Q14: =INDIRECT(Q$11&"!"&$B14) -> - | R14: =SUM(F14:Q14) -> 0
B15: D220 | D15: 受注率 | F15: =INDIRECT(F$11&"!"&$B15) -> - | G15: =INDIRECT(G$11&"!"&$B15) -> 0 | H15: =INDIRECT(H$11&"!"&$B15) -> - | I15: =INDIRECT(I$11&"!"&$B15) -> - | J15: =INDIRECT(J$11&"!"&$B15) -> - | K15: =INDIRECT(K$11&"!"&$B15) -> 0 | L15: =INDIRECT(L$11&"!"&$B15) -> - | M15: =INDIRECT(M$11&"!"&$B15) -> 0 | ... Q15: =INDIRECT(Q$11&"!"&$B15) -> 0 | R15: =R14/R13 -> #DIV/0!
B16: D221 | D16: 即受注 件数 | F16: =INDIRECT(F$11&"!"&$B16) -> 0 | G16: =INDIRECT(G$11&"!"&$B16) -> - | H16: =INDIRECT(H$11&"!"&$B16) -> 0 | I16: =INDIRECT(I$11&"!"&$B16) -> 0 | J16: =INDIRECT(J$11&"!"&$B16) -> 0 | K16: =INDIRECT(K$11&"!"&$B16) -> - | L16: =INDIRECT(L$11&"!"&$B16) -> 0 | M16: =INDIRECT(M$11&"!"&$B16) -> - | ... Q16: =INDIRECT(Q$11&"!"&$B16) -> - | R16: =SUM(F16:Q16) -> 0
B17: D222 | D17: 即受注率 | F17: =INDIRECT(F$11&"!"&$B17) -> - | G17: =INDIRECT(G$11&"!"&$B17) -> 0 | H17: =INDIRECT(H$11&"!"&$B17) -> - | I17: =INDIRECT(I$11&"!"&$B17) -> - | J17: =INDIRECT(J$11&"!"&$B17) -> - | K17: =INDIRECT(K$11&"!"&$B17) -> 0 | L17: =INDIRECT(L$11&"!"&$B17) -> - | M17: =INDIRECT(M$11&"!"&$B17) -> 0 | ... Q17: =INDIRECT(Q$11&"!"&$B17) -> 0 | R17: =R16/R13 -> #DIV/0!
B18: D223 | D18: 戻り受注 件数 | F18: =INDIRECT(F$11&"!"&$B18) -> 0 | G18: =INDIRECT(G$11&"!"&$B18) -> - | H18: =INDIRECT(H$11&"!"&$B18) -> 0 | I18: =INDIRECT(I$11&"!"&$B18) -> 0 | J18: =INDIRECT(J$11&"!"&$B18) -> 0 | K18: =INDIRECT(K$11&"!"&$B18) -> - | L18: =INDIRECT(L$11&"!"&$B18) -> 0 | M18: =INDIRECT(M$11&"!"&$B18) -> - | ... Q18: =INDIRECT(Q$11&"!"&$B18) -> - | R18: =SUM(F18:Q18) -> 0
B19: D224 | D19: 戻り受注率 | F19: =INDIRECT(F$11&"!"&$B19) -> - | G19: =INDIRECT(G$11&"!"&$B19) -> 0 | H19: =INDIRECT(H$11&"!"&$B19) -> - | I19: =INDIRECT(I$11&"!"&$B19) -> - | J19: =INDIRECT(J$11&"!"&$B19) -> - | K19: =INDIRECT(K$11&"!"&$B19) -> 0 | L19: =INDIRECT(L$11&"!"&$B19) -> - | M19: =INDIRECT(M$11&"!"&$B19) -> 0 | ... Q19: =INDIRECT(Q$11&"!"&$B19) -> 0 | R19: =R18/R13 -> #DIV/0!
B21: E218 | C21: =設定用!J7 -> 黒田み | D21: 面談対応件数 | F21: =INDIRECT(F$11&"!"&$B21) -> - | G21: =INDIRECT(G$11&"!"&$B21) -> 0 | H21: =INDIRECT(H$11&"!"&$B21) -> - | I21: =INDIRECT(I$11&"!"&$B21) -> - | J21: =INDIRECT(J$11&"!"&$B21) -> - | K21: =INDIRECT(K$11&"!"&$B21) -> 0 | L21: =INDIRECT(L$11&"!"&$B21) -> - | M21: =INDIRECT(M$11&"!"&$B21) -> 0 | ... Q21: =INDIRECT(Q$11&"!"&$B21) -> 0 | R21: =SUM(F21:Q21) -> 0
B22: E219 | D22: 受注件数 | F22: =INDIRECT(F$11&"!"&$B22) -> 0 | G22: =INDIRECT(G$11&"!"&$B22) -> - | H22: =INDIRECT(H$11&"!"&$B22) -> 0 | I22: =INDIRECT(I$11&"!"&$B22) -> 0 | J22: =INDIRECT(J$11&"!"&$B22) -> 0 | K22: =INDIRECT(K$11&"!"&$B22) -> - | L22: =INDIRECT(L$11&"!"&$B22) -> 0 | M22: =INDIRECT(M$11&"!"&$B22) -> - | ... Q22: =INDIRECT(Q$11&"!"&$B22) -> - | R22: =SUM(F22:Q22) -> 0
B23: E220 | D23: 受注率 | F23: =INDIRECT(F$11&"!"&$B23) -> - | G23: =INDIRECT(G$11&"!"&$B23) -> 0 | H23: =INDIRECT(H$11&"!"&$B23) -> - | I23: =INDIRECT(I$11&"!"&$B23) -> - | J23: =INDIRECT(J$11&"!"&$B23) -> - | K23: =INDIRECT(K$11&"!"&$B23) -> 0 | L23: =INDIRECT(L$11&"!"&$B23) -> - | M23: =INDIRECT(M$11&"!"&$B23) -> 0 | ... Q23: =INDIRECT(Q$11&"!"&$B23) -> 0 | R23: =R22/R21 -> #DIV/0!
B24: E221 | D24: 即受注 件数 | F24: =INDIRECT(F$11&"!"&$B24) -> 0 | G24: =INDIRECT(G$11&"!"&$B24) -> - | H24: =INDIRECT(H$11&"!"&$B24) -> 0 | I24: =INDIRECT(I$11&"!"&$B24) -> 0 | J24: =INDIRECT(J$11&"!"&$B24) -> 0 | K24: =INDIRECT(K$11&"!"&$B24) -> - | L24: =INDIRECT(L$11&"!"&$B24) -> 0 | M24: =INDIRECT(M$11&"!"&$B24) -> - | ... Q24: =INDIRECT(Q$11&"!"&$B24) -> - | R24: =SUM(F24:Q24) -> 0
B25: E222 | D25: 即受注率 | F25: =INDIRECT(F$11&"!"&$B25) -> - | G25: =INDIRECT(G$11&"!"&$B25) -> 0 | H25: =INDIRECT(H$11&"!"&$B25) -> - | I25: =INDIRECT(I$11&"!"&$B25) -> - | J25: =INDIRECT(J$11&"!"&$B25) -> - | K25: =INDIRECT(K$11&"!"&$B25) -> 0 | L25: =INDIRECT(L$11&"!"&$B25) -> - | M25: =INDIRECT(M$11&"!"&$B25) -> 0 | ... Q25: =INDIRECT(Q$11&"!"&$B25) -> 0 | R25: =R24/R21 -> #DIV/0!
B26: E223 | D26: 戻り受注 件数 | F26: =INDIRECT(F$11&"!"&$B26) -> 0 | G26: =INDIRECT(G$11&"!"&$B26) -> - | H26: =INDIRECT(H$11&"!"&$B26) -> 0 | I26: =INDIRECT(I$11&"!"&$B26) -> 0 | J26: =INDIRECT(J$11&"!"&$B26) -> 0 | K26: =INDIRECT(K$11&"!"&$B26) -> - | L26: =INDIRECT(L$11&"!"&$B26) -> 0 | M26: =INDIRECT(M$11&"!"&$B26) -> - | ... Q26: =INDIRECT(Q$11&"!"&$B26) -> - | R26: =SUM(F26:Q26) -> 0
B27: E224 | D27: 戻り受注率 | F27: =INDIRECT(F$11&"!"&$B27) -> - | G27: =INDIRECT(G$11&"!"&$B27) -> 0 | H27: =INDIRECT(H$11&"!"&$B27) -> - | I27: =INDIRECT(I$11&"!"&$B27) -> - | J27: =INDIRECT(J$11&"!"&$B27) -> - | K27: =INDIRECT(K$11&"!"&$B27) -> 0 | L27: =INDIRECT(L$11&"!"&$B27) -> - | M27: =INDIRECT(M$11&"!"&$B27) -> 0 | ... Q27: =INDIRECT(Q$11&"!"&$B27) -> 0 | R27: =R26/R21 -> #DIV/0!
B29: F218 | C29: =設定用!J8 -> 山田 | D29: 面談対応件数 | F29: =INDIRECT(F$11&"!"&$B29) -> 0.66666667 | G29: =INDIRECT(G$11&"!"&$B29) -> 1 | H29: =INDIRECT(H$11&"!"&$B29) -> 0 | I29: =INDIRECT(I$11&"!"&$B29) -> 0 | J29: =INDIRECT(J$11&"!"&$B29) -> - | K29: =INDIRECT(K$11&"!"&$B29) -> 0 | L29: =INDIRECT(L$11&"!"&$B29) -> - | M29: =INDIRECT(M$11&"!"&$B29) -> 0 | ... Q29: =INDIRECT(Q$11&"!"&$B29) -> 0 | R29: =SUM(F29:Q29) -> 1.6666667
B30: F219 | D30: 受注件数 | F30: =INDIRECT(F$11&"!"&$B30) -> 0 | G30: =INDIRECT(G$11&"!"&$B30) -> 1 | H30: =INDIRECT(H$11&"!"&$B30) -> 0 | I30: =INDIRECT(I$11&"!"&$B30) -> 1 | J30: =INDIRECT(J$11&"!"&$B30) -> 0 | K30: =INDIRECT(K$11&"!"&$B30) -> - | L30: =INDIRECT(L$11&"!"&$B30) -> 0 | M30: =INDIRECT(M$11&"!"&$B30) -> - | ... Q30: =INDIRECT(Q$11&"!"&$B30) -> - | R30: =SUM(F30:Q30) -> 2
B31: F220 | D31: 受注率 | F31: =INDIRECT(F$11&"!"&$B31) -> 0 | G31: =INDIRECT(G$11&"!"&$B31) -> 1 | H31: =INDIRECT(H$11&"!"&$B31) -> 0 | I31: =INDIRECT(I$11&"!"&$B31) -> 0.25 | J31: =INDIRECT(J$11&"!"&$B31) -> - | K31: =INDIRECT(K$11&"!"&$B31) -> 0 | L31: =INDIRECT(L$11&"!"&$B31) -> - | M31: =INDIRECT(M$11&"!"&$B31) -> 0 | ... Q31: =INDIRECT(Q$11&"!"&$B31) -> 0 | R31: =R30/R29 -> 1.2
B32: F221 | D32: 即受注 件数 | F32: =INDIRECT(F$11&"!"&$B32) -> 0 | G32: =INDIRECT(G$11&"!"&$B32) -> 1 | H32: =INDIRECT(H$11&"!"&$B32) -> 0 | I32: =INDIRECT(I$11&"!"&$B32) -> 0 | J32: =INDIRECT(J$11&"!"&$B32) -> 0 | K32: =INDIRECT(K$11&"!"&$B32) -> - | L32: =INDIRECT(L$11&"!"&$B32) -> 0 | M32: =INDIRECT(M$11&"!"&$B32) -> - | ... Q32: =INDIRECT(Q$11&"!"&$B32) -> - | R32: =SUM(F32:Q32) -> 1
B33: F222 | D33: 即受注率 | F33: =INDIRECT(F$11&"!"&$B33) -> 0 | G33: =INDIRECT(G$11&"!"&$B33) -> 0 | H33: =INDIRECT(H$11&"!"&$B33) -> 0 | I33: =INDIRECT(I$11&"!"&$B33) -> 0 | J33: =INDIRECT(J$11&"!"&$B33) -> - | K33: =INDIRECT(K$11&"!"&$B33) -> 0 | L33: =INDIRECT(L$11&"!"&$B33) -> - | M33: =INDIRECT(M$11&"!"&$B33) -> 0 | ... Q33: =INDIRECT(Q$11&"!"&$B33) -> 0 | R33: =R32/R29 -> 0.6
B34: F223 | D34: 戻り受注 件数 | F34: =INDIRECT(F$11&"!"&$B34) -> 1 | G34: =INDIRECT(G$11&"!"&$B34) -> 0 | H34: =INDIRECT(H$11&"!"&$B34) -> 0 | I34: =INDIRECT(I$11&"!"&$B34) -> 2 | J34: =INDIRECT(J$11&"!"&$B34) -> 0 | K34: =INDIRECT(K$11&"!"&$B34) -> - | L34: =INDIRECT(L$11&"!"&$B34) -> 0 | M34: =INDIRECT(M$11&"!"&$B34) -> - | ... Q34: =INDIRECT(Q$11&"!"&$B34) -> - | R34: =SUM(F34:Q34) -> 3
B35: F224 | D35: 戻り受注率 | F35: =INDIRECT(F$11&"!"&$B35) -> 0.33333333 | G35: =INDIRECT(G$11&"!"&$B35) -> 0 | H35: =INDIRECT(H$11&"!"&$B35) -> 0 | I35: =INDIRECT(I$11&"!"&$B35) -> 0.5 | J35: =INDIRECT(J$11&"!"&$B35) -> - | K35: =INDIRECT(K$11&"!"&$B35) -> 0 | L35: =INDIRECT(L$11&"!"&$B35) -> - | M35: =INDIRECT(M$11&"!"&$B35) -> 0 | ... Q35: =INDIRECT(Q$11&"!"&$B35) -> 0 | R35: =R34/R29 -> 1.8
B37: G218 | C37: =設定用!J9 -> 奥章 | D37: 面談対応件数 | F37: =INDIRECT(F$11&"!"&$B37) -> - | G37: =INDIRECT(G$11&"!"&$B37) -> 0 | H37: =INDIRECT(H$11&"!"&$B37) -> - | I37: =INDIRECT(I$11&"!"&$B37) -> - | J37: =INDIRECT(J$11&"!"&$B37) -> - | K37: =INDIRECT(K$11&"!"&$B37) -> 0 | L37: =INDIRECT(L$11&"!"&$B37) -> - | M37: =INDIRECT(M$11&"!"&$B37) -> 0 | ... Q37: =INDIRECT(Q$11&"!"&$B37) -> 0 | R37: =SUM(F37:Q37) -> 0
B38: G219 | D38: 受注件数 | F38: =INDIRECT(F$11&"!"&$B38) -> 0 | G38: =INDIRECT(G$11&"!"&$B38) -> - | H38: =INDIRECT(H$11&"!"&$B38) -> 0 | I38: =INDIRECT(I$11&"!"&$B38) -> 0 | J38: =INDIRECT(J$11&"!"&$B38) -> 0 | K38: =INDIRECT(K$11&"!"&$B38) -> - | L38: =INDIRECT(L$11&"!"&$B38) -> 0 | M38: =INDIRECT(M$11&"!"&$B38) -> - | ... Q38: =INDIRECT(Q$11&"!"&$B38) -> - | R38: =SUM(F38:Q38) -> 0
B39: G220 | D39: 受注率 | F39: =INDIRECT(F$11&"!"&$B39) -> - | G39: =INDIRECT(G$11&"!"&$B39) -> 0 | H39: =INDIRECT(H$11&"!"&$B39) -> - | I39: =INDIRECT(I$11&"!"&$B39) -> - | J39: =INDIRECT(J$11&"!"&$B39) -> - | K39: =INDIRECT(K$11&"!"&$B39) -> 0 | L39: =INDIRECT(L$11&"!"&$B39) -> - | M39: =INDIRECT(M$11&"!"&$B39) -> 0 | ... Q39: =INDIRECT(Q$11&"!"&$B39) -> 0 | R39: =R38/R37 -> #DIV/0!
B40: G221 | D40: 即受注 件数 | F40: =INDIRECT(F$11&"!"&$B40) -> 0 | G40: =INDIRECT(G$11&"!"&$B40) -> - | H40: =INDIRECT(H$11&"!"&$B40) -> 0 | I40: =INDIRECT(I$11&"!"&$B40) -> 0 | J40: =INDIRECT(J$11&"!"&$B40) -> 0 | K40: =INDIRECT(K$11&"!"&$B40) -> - | L40: =INDIRECT(L$11&"!"&$B40) -> 0 | M40: =INDIRECT(M$11&"!"&$B40) -> - | ... Q40: =INDIRECT(Q$11&"!"&$B40) -> - | R40: =SUM(F40:Q40) -> 0
B41: G222 | D41: 即受注率 | F41: =INDIRECT(F$11&"!"&$B41) -> - | G41: =INDIRECT(G$11&"!"&$B41) -> 0 | H41: =INDIRECT(H$11&"!"&$B41) -> - | I41: =INDIRECT(I$11&"!"&$B41) -> - | J41: =INDIRECT(J$11&"!"&$B41) -> - | K41: =INDIRECT(K$11&"!"&$B41) -> 0 | L41: =INDIRECT(L$11&"!"&$B41) -> - | M41: =INDIRECT(M$11&"!"&$B41) -> 0 | ... Q41: =INDIRECT(Q$11&"!"&$B41) -> 0 | R41: =R40/R37 -> #DIV/0!
B42: G223 | D42: 戻り受注 件数 | F42: =INDIRECT(F$11&"!"&$B42) -> 0 | G42: =INDIRECT(G$11&"!"&$B42) -> - | H42: =INDIRECT(H$11&"!"&$B42) -> 0 | I42: =INDIRECT(I$11&"!"&$B42) -> 0 | J42: =INDIRECT(J$11&"!"&$B42) -> 0 | K42: =INDIRECT(K$11&"!"&$B42) -> - | L42: =INDIRECT(L$11&"!"&$B42) -> 0 | M42: =INDIRECT(M$11&"!"&$B42) -> - | ... Q42: =INDIRECT(Q$11&"!"&$B42) -> - | R42: =SUM(F42:Q42) -> 0
B43: G224 | D43: 戻り受注率 | F43: =INDIRECT(F$11&"!"&$B43) -> - | G43: =INDIRECT(G$11&"!"&$B43) -> 0 | H43: =INDIRECT(H$11&"!"&$B43) -> - | I43: =INDIRECT(I$11&"!"&$B43) -> - | J43: =INDIRECT(J$11&"!"&$B43) -> - | K43: =INDIRECT(K$11&"!"&$B43) -> 0 | L43: =INDIRECT(L$11&"!"&$B43) -> - | M43: =INDIRECT(M$11&"!"&$B43) -> 0 | ... Q43: =INDIRECT(Q$11&"!"&$B43) -> 0 | R43: =R42/R37 -> #DIV/0!
B45: H218 | C45: =設定用!J10 -> 山﨑 | D45: 面談対応件数 | F45: =INDIRECT(F$11&"!"&$B45) -> - | G45: =INDIRECT(G$11&"!"&$B45) -> 2 | H45: =INDIRECT(H$11&"!"&$B45) -> - | I45: =INDIRECT(I$11&"!"&$B45) -> - | J45: =INDIRECT(J$11&"!"&$B45) -> - | K45: =INDIRECT(K$11&"!"&$B45) -> 0 | L45: =INDIRECT(L$11&"!"&$B45) -> - | M45: =INDIRECT(M$11&"!"&$B45) -> 0 | ... Q45: =INDIRECT(Q$11&"!"&$B45) -> 0 | R45: =SUM(F45:Q45) -> 2
B46: H219 | D46: 受注件数 | F46: =INDIRECT(F$11&"!"&$B46) -> 0 | G46: =INDIRECT(G$11&"!"&$B46) -> 1 | H46: =INDIRECT(H$11&"!"&$B46) -> 0 | I46: =INDIRECT(I$11&"!"&$B46) -> 0 | J46: =INDIRECT(J$11&"!"&$B46) -> 0 | K46: =INDIRECT(K$11&"!"&$B46) -> - | L46: =INDIRECT(L$11&"!"&$B46) -> 0 | M46: =INDIRECT(M$11&"!"&$B46) -> - | ... Q46: =INDIRECT(Q$11&"!"&$B46) -> - | R46: =SUM(F46:Q46) -> 1
B47: H220 | D47: 受注率 | F47: =INDIRECT(F$11&"!"&$B47) -> - | G47: =INDIRECT(G$11&"!"&$B47) -> 2 | H47: =INDIRECT(H$11&"!"&$B47) -> - | I47: =INDIRECT(I$11&"!"&$B47) -> - | J47: =INDIRECT(J$11&"!"&$B47) -> - | K47: =INDIRECT(K$11&"!"&$B47) -> 0 | L47: =INDIRECT(L$11&"!"&$B47) -> - | M47: =INDIRECT(M$11&"!"&$B47) -> 0 | ... Q47: =INDIRECT(Q$11&"!"&$B47) -> 0 | R47: =R46/R45 -> 0.5
B48: H221 | D48: 即受注 件数 | F48: =INDIRECT(F$11&"!"&$B48) -> 0 | G48: =INDIRECT(G$11&"!"&$B48) -> 1 | H48: =INDIRECT(H$11&"!"&$B48) -> 0 | I48: =INDIRECT(I$11&"!"&$B48) -> 0 | J48: =INDIRECT(J$11&"!"&$B48) -> 0 | K48: =INDIRECT(K$11&"!"&$B48) -> - | L48: =INDIRECT(L$11&"!"&$B48) -> 0 | M48: =INDIRECT(M$11&"!"&$B48) -> - | ... Q48: =INDIRECT(Q$11&"!"&$B48) -> - | R48: =SUM(F48:Q48) -> 1
B49: H222 | D49: 即受注率 | F49: =INDIRECT(F$11&"!"&$B49) -> - | G49: =INDIRECT(G$11&"!"&$B49) -> 0 | H49: =INDIRECT(H$11&"!"&$B49) -> - | I49: =INDIRECT(I$11&"!"&$B49) -> - | J49: =INDIRECT(J$11&"!"&$B49) -> - | K49: =INDIRECT(K$11&"!"&$B49) -> 0 | L49: =INDIRECT(L$11&"!"&$B49) -> - | M49: =INDIRECT(M$11&"!"&$B49) -> 0 | ... Q49: =INDIRECT(Q$11&"!"&$B49) -> 0 | R49: =R48/R45 -> 0.5
B50: H223 | D50: 戻り受注 件数 | F50: =INDIRECT(F$11&"!"&$B50) -> 0 | G50: =INDIRECT(G$11&"!"&$B50) -> 0 | H50: =INDIRECT(H$11&"!"&$B50) -> 0 | I50: =INDIRECT(I$11&"!"&$B50) -> 0 | J50: =INDIRECT(J$11&"!"&$B50) -> 0 | K50: =INDIRECT(K$11&"!"&$B50) -> - | L50: =INDIRECT(L$11&"!"&$B50) -> 0 | M50: =INDIRECT(M$11&"!"&$B50) -> - | ... Q50: =INDIRECT(Q$11&"!"&$B50) -> - | R50: =SUM(F50:Q50) -> 0
B51: H224 | D51: 戻り受注率 | F51: =INDIRECT(F$11&"!"&$B51) -> - | G51: =INDIRECT(G$11&"!"&$B51) -> 0 | H51: =INDIRECT(H$11&"!"&$B51) -> - | I51: =INDIRECT(I$11&"!"&$B51) -> - | J51: =INDIRECT(J$11&"!"&$B51) -> - | K51: =INDIRECT(K$11&"!"&$B51) -> 0 | L51: =INDIRECT(L$11&"!"&$B51) -> - | M51: =INDIRECT(M$11&"!"&$B51) -> 0 | ... Q51: =INDIRECT(Q$11&"!"&$B51) -> 0 | R51: =R50/R45 -> 0
B53: D238 | C53: =設定用!J11 -> 鵜飼 | D53: 面談対応件数 | F53: =INDIRECT(F$11&"!"&$B53) -> 0.5 | G53: =INDIRECT(G$11&"!"&$B53) -> 0 | H53: =INDIRECT(H$11&"!"&$B53) -> - | I53: =INDIRECT(I$11&"!"&$B53) -> - | J53: =INDIRECT(J$11&"!"&$B53) -> - | K53: =INDIRECT(K$11&"!"&$B53) -> 0 | L53: =INDIRECT(L$11&"!"&$B53) -> - | M53: =INDIRECT(M$11&"!"&$B53) -> 0 | ... Q53: =INDIRECT(Q$11&"!"&$B53) -> 0 | R53: =SUM(F53:Q53) -> 0.5
B54: D239 | D54: 受注件数 | F54: =INDIRECT(F$11&"!"&$B54) -> 0 | G54: =INDIRECT(G$11&"!"&$B54) -> - | H54: =INDIRECT(H$11&"!"&$B54) -> 0 | I54: =INDIRECT(I$11&"!"&$B54) -> 0 | J54: =INDIRECT(J$11&"!"&$B54) -> 0 | K54: =INDIRECT(K$11&"!"&$B54) -> - | L54: =INDIRECT(L$11&"!"&$B54) -> 0 | M54: =INDIRECT(M$11&"!"&$B54) -> - | ... Q54: =INDIRECT(Q$11&"!"&$B54) -> - | R54: =SUM(F54:Q54) -> 0
B55: D240 | D55: 受注率 | F55: =INDIRECT(F$11&"!"&$B55) -> 0 | G55: =INDIRECT(G$11&"!"&$B55) -> 0 | H55: =INDIRECT(H$11&"!"&$B55) -> - | I55: =INDIRECT(I$11&"!"&$B55) -> - | J55: =INDIRECT(J$11&"!"&$B55) -> - | K55: =INDIRECT(K$11&"!"&$B55) -> 0 | L55: =INDIRECT(L$11&"!"&$B55) -> - | M55: =INDIRECT(M$11&"!"&$B55) -> 0 | ... Q55: =INDIRECT(Q$11&"!"&$B55) -> 0 | R55: =R54/R53 -> 0
B56: D241 | D56: 即受注 件数 | F56: =INDIRECT(F$11&"!"&$B56) -> 0 | G56: =INDIRECT(G$11&"!"&$B56) -> - | H56: =INDIRECT(H$11&"!"&$B56) -> 0 | I56: =INDIRECT(I$11&"!"&$B56) -> 0 | J56: =INDIRECT(J$11&"!"&$B56) -> 0 | K56: =INDIRECT(K$11&"!"&$B56) -> - | L56: =INDIRECT(L$11&"!"&$B56) -> 0 | M56: =INDIRECT(M$11&"!"&$B56) -> - | ... Q56: =INDIRECT(Q$11&"!"&$B56) -> - | R56: =SUM(F56:Q56) -> 0
B57: D242 | D57: 即受注率 | F57: =INDIRECT(F$11&"!"&$B57) -> - | G57: =INDIRECT(G$11&"!"&$B57) -> 0 | H57: =INDIRECT(H$11&"!"&$B57) -> - | I57: =INDIRECT(I$11&"!"&$B57) -> - | J57: =INDIRECT(J$11&"!"&$B57) -> - | K57: =INDIRECT(K$11&"!"&$B57) -> 0 | L57: =INDIRECT(L$11&"!"&$B57) -> - | M57: =INDIRECT(M$11&"!"&$B57) -> 0 | ... Q57: =INDIRECT(Q$11&"!"&$B57) -> 0 | R57: =R56/R53 -> 0
B58: D243 | D58: 戻り受注 件数 | F58: =INDIRECT(F$11&"!"&$B58) -> 1 | G58: =INDIRECT(G$11&"!"&$B58) -> - | H58: =INDIRECT(H$11&"!"&$B58) -> 0 | I58: =INDIRECT(I$11&"!"&$B58) -> 0 | J58: =INDIRECT(J$11&"!"&$B58) -> 0 | K58: =INDIRECT(K$11&"!"&$B58) -> - | L58: =INDIRECT(L$11&"!"&$B58) -> 0 | M58: =INDIRECT(M$11&"!"&$B58) -> - | ... Q58: =INDIRECT(Q$11&"!"&$B58) -> - | R58: =SUM(F58:Q58) -> 1
B59: D244 | D59: 戻り受注率 | F59: =INDIRECT(F$11&"!"&$B59) -> - | G59: =INDIRECT(G$11&"!"&$B59) -> 0 | H59: =INDIRECT(H$11&"!"&$B59) -> - | I59: =INDIRECT(I$11&"!"&$B59) -> - | J59: =INDIRECT(J$11&"!"&$B59) -> - | K59: =INDIRECT(K$11&"!"&$B59) -> 0 | L59: =INDIRECT(L$11&"!"&$B59) -> - | M59: =INDIRECT(M$11&"!"&$B59) -> 0 | ... Q59: =INDIRECT(Q$11&"!"&$B59) -> 0 | R59: =R58/R53 -> 2
B61: E238 | C61: =設定用!J12 -> 筆野 | D61: 面談対応件数 | F61: =INDIRECT(F$11&"!"&$B61) -> - | G61: =INDIRECT(G$11&"!"&$B61) -> 0 | H61: =INDIRECT(H$11&"!"&$B61) -> 0 | I61: =INDIRECT(I$11&"!"&$B61) -> - | J61: =INDIRECT(J$11&"!"&$B61) -> - | K61: =INDIRECT(K$11&"!"&$B61) -> 0 | L61: =INDIRECT(L$11&"!"&$B61) -> - | M61: =INDIRECT(M$11&"!"&$B61) -> 0 | ... Q61: =INDIRECT(Q$11&"!"&$B61) -> 0 | R61: =SUM(F61:Q61) -> 0
B62: E239 | D62: 受注件数 | F62: =INDIRECT(F$11&"!"&$B62) -> 0 | G62: =INDIRECT(G$11&"!"&$B62) -> - | H62: =INDIRECT(H$11&"!"&$B62) -> 0 | I62: =INDIRECT(I$11&"!"&$B62) -> 0 | J62: =INDIRECT(J$11&"!"&$B62) -> 0 | K62: =INDIRECT(K$11&"!"&$B62) -> - | L62: =INDIRECT(L$11&"!"&$B62) -> 0 | M62: =INDIRECT(M$11&"!"&$B62) -> - | ... Q62: =INDIRECT(Q$11&"!"&$B62) -> - | R62: =SUM(F62:Q62) -> 0
B63: E240 | D63: 受注率 | F63: =INDIRECT(F$11&"!"&$B63) -> - | G63: =INDIRECT(G$11&"!"&$B63) -> 0 | H63: =INDIRECT(H$11&"!"&$B63) -> 0 | I63: =INDIRECT(I$11&"!"&$B63) -> - | J63: =INDIRECT(J$11&"!"&$B63) -> - | K63: =INDIRECT(K$11&"!"&$B63) -> 0 | L63: =INDIRECT(L$11&"!"&$B63) -> - | M63: =INDIRECT(M$11&"!"&$B63) -> 0 | ... Q63: =INDIRECT(Q$11&"!"&$B63) -> 0 | R63: =R62/R61 -> #DIV/0!
B64: E241 | D64: 即受注 件数 | F64: =INDIRECT(F$11&"!"&$B64) -> 0 | G64: =INDIRECT(G$11&"!"&$B64) -> - | H64: =INDIRECT(H$11&"!"&$B64) -> 0 | I64: =INDIRECT(I$11&"!"&$B64) -> 0 | J64: =INDIRECT(J$11&"!"&$B64) -> 0 | K64: =INDIRECT(K$11&"!"&$B64) -> - | L64: =INDIRECT(L$11&"!"&$B64) -> 0 | M64: =INDIRECT(M$11&"!"&$B64) -> - | ... Q64: =INDIRECT(Q$11&"!"&$B64) -> - | R64: =SUM(F64:Q64) -> 0
B65: E242 | D65: 即受注率 | F65: =INDIRECT(F$11&"!"&$B65) -> 0 | G65: =INDIRECT(G$11&"!"&$B65) -> 0 | H65: =INDIRECT(H$11&"!"&$B65) -> 0 | I65: =INDIRECT(I$11&"!"&$B65) -> 0 | J65: =INDIRECT(J$11&"!"&$B65) -> - | K65: =INDIRECT(K$11&"!"&$B65) -> 0 | L65: =INDIRECT(L$11&"!"&$B65) -> - | M65: =INDIRECT(M$11&"!"&$B65) -> 0 | ... Q65: =INDIRECT(Q$11&"!"&$B65) -> 0 | R65: =R64/R61 -> #DIV/0!
B66: E243 | D66: 戻り受注 件数 | F66: =INDIRECT(F$11&"!"&$B66) -> 0 | G66: =INDIRECT(G$11&"!"&$B66) -> - | H66: =INDIRECT(H$11&"!"&$B66) -> 0 | I66: =INDIRECT(I$11&"!"&$B66) -> 0 | J66: =INDIRECT(J$11&"!"&$B66) -> 0 | K66: =INDIRECT(K$11&"!"&$B66) -> - | L66: =INDIRECT(L$11&"!"&$B66) -> 0 | M66: =INDIRECT(M$11&"!"&$B66) -> - | ... Q66: =INDIRECT(Q$11&"!"&$B66) -> - | R66: =SUM(F66:Q66) -> 0
B67: E244 | D67: 戻り受注率 | F67: =INDIRECT(F$11&"!"&$B67) -> 0 | G67: =INDIRECT(G$11&"!"&$B67) -> 0 | H67: =INDIRECT(H$11&"!"&$B67) -> 0 | I67: =INDIRECT(I$11&"!"&$B67) -> 0 | J67: =INDIRECT(J$11&"!"&$B67) -> - | K67: =INDIRECT(K$11&"!"&$B67) -> 0 | L67: =INDIRECT(L$11&"!"&$B67) -> - | M67: =INDIRECT(M$11&"!"&$B67) -> 0 | ... Q67: =INDIRECT(Q$11&"!"&$B67) -> 0 | R67: =R66/R61 -> #DIV/0!
B69: F238 | C69: =設定用!J13 -> 岡田 | D69: 面談対応件数 | F69: =INDIRECT(F$11&"!"&$B69) -> - | G69: =INDIRECT(G$11&"!"&$B69) -> 0 | H69: =INDIRECT(H$11&"!"&$B69) -> - | I69: =INDIRECT(I$11&"!"&$B69) -> - | J69: =INDIRECT(J$11&"!"&$B69) -> - | K69: =INDIRECT(K$11&"!"&$B69) -> 0 | L69: =INDIRECT(L$11&"!"&$B69) -> - | M69: =INDIRECT(M$11&"!"&$B69) -> 0 | ... Q69: =INDIRECT(Q$11&"!"&$B69) -> 0 | R69: =SUM(F69:Q69) -> 0
B70: F239 | D70: 受注件数 | F70: =INDIRECT(F$11&"!"&$B70) -> 0 | G70: =INDIRECT(G$11&"!"&$B70) -> - | H70: =INDIRECT(H$11&"!"&$B70) -> 0 | I70: =INDIRECT(I$11&"!"&$B70) -> 0 | J70: =INDIRECT(J$11&"!"&$B70) -> 0 | K70: =INDIRECT(K$11&"!"&$B70) -> - | L70: =INDIRECT(L$11&"!"&$B70) -> 0 | M70: =INDIRECT(M$11&"!"&$B70) -> - | ... Q70: =INDIRECT(Q$11&"!"&$B70) -> - | R70: =SUM(F70:Q70) -> 0
B71: F240 | D71: 受注率 | F71: =INDIRECT(F$11&"!"&$B71) -> - | G71: =INDIRECT(G$11&"!"&$B71) -> 0 | H71: =INDIRECT(H$11&"!"&$B71) -> - | I71: =INDIRECT(I$11&"!"&$B71) -> - | J71: =INDIRECT(J$11&"!"&$B71) -> - | K71: =INDIRECT(K$11&"!"&$B71) -> 0 | L71: =INDIRECT(L$11&"!"&$B71) -> - | M71: =INDIRECT(M$11&"!"&$B71) -> 0 | ... Q71: =INDIRECT(Q$11&"!"&$B71) -> 0 | R71: =R70/R69 -> #DIV/0!
B72: F241 | D72: 即受注 件数 | F72: =INDIRECT(F$11&"!"&$B72) -> 0 | G72: =INDIRECT(G$11&"!"&$B72) -> - | H72: =INDIRECT(H$11&"!"&$B72) -> 0 | I72: =INDIRECT(I$11&"!"&$B72) -> 0 | J72: =INDIRECT(J$11&"!"&$B72) -> 0 | K72: =INDIRECT(K$11&"!"&$B72) -> - | L72: =INDIRECT(L$11&"!"&$B72) -> 0 | M72: =INDIRECT(M$11&"!"&$B72) -> - | ... Q72: =INDIRECT(Q$11&"!"&$B72) -> - | R72: =SUM(F72:Q72) -> 0
B73: F242 | D73: 即受注率 | F73: =INDIRECT(F$11&"!"&$B73) -> - | G73: =INDIRECT(G$11&"!"&$B73) -> 0 | H73: =INDIRECT(H$11&"!"&$B73) -> - | I73: =INDIRECT(I$11&"!"&$B73) -> - | J73: =INDIRECT(J$11&"!"&$B73) -> - | K73: =INDIRECT(K$11&"!"&$B73) -> 0 | L73: =INDIRECT(L$11&"!"&$B73) -> - | M73: =INDIRECT(M$11&"!"&$B73) -> 0 | ... Q73: =INDIRECT(Q$11&"!"&$B73) -> 0 | R73: =R72/R69 -> #DIV/0!
B74: F243 | D74: 戻り受注 件数 | F74: =INDIRECT(F$11&"!"&$B74) -> 0 | G74: =INDIRECT(G$11&"!"&$B74) -> - | H74: =INDIRECT(H$11&"!"&$B74) -> 0 | I74: =INDIRECT(I$11&"!"&$B74) -> 0 | J74: =INDIRECT(J$11&"!"&$B74) -> 0 | K74: =INDIRECT(K$11&"!"&$B74) -> - | L74: =INDIRECT(L$11&"!"&$B74) -> 0 | M74: =INDIRECT(M$11&"!"&$B74) -> - | ... Q74: =INDIRECT(Q$11&"!"&$B74) -> - | R74: =SUM(F74:Q74) -> 0
B75: F244 | D75: 戻り受注率 | F75: =INDIRECT(F$11&"!"&$B75) -> - | G75: =INDIRECT(G$11&"!"&$B75) -> 0 | H75: =INDIRECT(H$11&"!"&$B75) -> - | I75: =INDIRECT(I$11&"!"&$B75) -> - | J75: =INDIRECT(J$11&"!"&$B75) -> - | K75: =INDIRECT(K$11&"!"&$B75) -> 0 | L75: =INDIRECT(L$11&"!"&$B75) -> - | M75: =INDIRECT(M$11&"!"&$B75) -> 0 | ... Q75: =INDIRECT(Q$11&"!"&$B75) -> 0 | R75: =R74/R69 -> #DIV/0!
B77: G238 | C77: =設定用!J14 -> 杉原 | D77: 面談対応件数 | F77: =INDIRECT(F$11&"!"&$B77) -> - | G77: =INDIRECT(G$11&"!"&$B77) -> 0 | H77: =INDIRECT(H$11&"!"&$B77) -> - | I77: =INDIRECT(I$11&"!"&$B77) -> 1 | J77: =INDIRECT(J$11&"!"&$B77) -> - | K77: =INDIRECT(K$11&"!"&$B77) -> 0 | L77: =INDIRECT(L$11&"!"&$B77) -> - | M77: =INDIRECT(M$11&"!"&$B77) -> 0 | ... Q77: =INDIRECT(Q$11&"!"&$B77) -> 0 | R77: =SUM(F77:Q77) -> 1
B78: G239 | D78: 受注件数 | F78: =INDIRECT(F$11&"!"&$B78) -> 0 | G78: =INDIRECT(G$11&"!"&$B78) -> - | H78: =INDIRECT(H$11&"!"&$B78) -> 0 | I78: =INDIRECT(I$11&"!"&$B78) -> 0 | J78: =INDIRECT(J$11&"!"&$B78) -> 0 | K78: =INDIRECT(K$11&"!"&$B78) -> - | L78: =INDIRECT(L$11&"!"&$B78) -> 0 | M78: =INDIRECT(M$11&"!"&$B78) -> - | ... Q78: =INDIRECT(Q$11&"!"&$B78) -> - | R78: =SUM(F78:Q78) -> 0
B79: G240 | D79: 受注率 | F79: =INDIRECT(F$11&"!"&$B79) -> - | G79: =INDIRECT(G$11&"!"&$B79) -> 0 | H79: =INDIRECT(H$11&"!"&$B79) -> - | I79: =INDIRECT(I$11&"!"&$B79) -> 0 | J79: =INDIRECT(J$11&"!"&$B79) -> - | K79: =INDIRECT(K$11&"!"&$B79) -> 0 | L79: =INDIRECT(L$11&"!"&$B79) -> - | M79: =INDIRECT(M$11&"!"&$B79) -> 0 | ... Q79: =INDIRECT(Q$11&"!"&$B79) -> 0 | R79: =R78/R77 -> 0
B80: G241 | D80: 即受注 件数 | F80: =INDIRECT(F$11&"!"&$B80) -> 0 | G80: =INDIRECT(G$11&"!"&$B80) -> - | H80: =INDIRECT(H$11&"!"&$B80) -> 0 | I80: =INDIRECT(I$11&"!"&$B80) -> 0 | J80: =INDIRECT(J$11&"!"&$B80) -> 0 | K80: =INDIRECT(K$11&"!"&$B80) -> - | L80: =INDIRECT(L$11&"!"&$B80) -> 0 | M80: =INDIRECT(M$11&"!"&$B80) -> - | ... Q80: =INDIRECT(Q$11&"!"&$B80) -> - | R80: =SUM(F80:Q80) -> 0
B81: G242 | D81: 即受注率 | F81: =INDIRECT(F$11&"!"&$B81) -> - | G81: =INDIRECT(G$11&"!"&$B81) -> 0 | H81: =INDIRECT(H$11&"!"&$B81) -> - | I81: =INDIRECT(I$11&"!"&$B81) -> - | J81: =INDIRECT(J$11&"!"&$B81) -> - | K81: =INDIRECT(K$11&"!"&$B81) -> 0 | L81: =INDIRECT(L$11&"!"&$B81) -> - | M81: =INDIRECT(M$11&"!"&$B81) -> 0 | ... Q81: =INDIRECT(Q$11&"!"&$B81) -> 0 | R81: =R80/R77 -> 0
B82: G243 | D82: 戻り受注 件数 | F82: =INDIRECT(F$11&"!"&$B82) -> 0 | G82: =INDIRECT(G$11&"!"&$B82) -> - | H82: =INDIRECT(H$11&"!"&$B82) -> 0 | I82: =INDIRECT(I$11&"!"&$B82) -> 0 | J82: =INDIRECT(J$11&"!"&$B82) -> 0 | K82: =INDIRECT(K$11&"!"&$B82) -> - | L82: =INDIRECT(L$11&"!"&$B82) -> 0 | M82: =INDIRECT(M$11&"!"&$B82) -> - | ... Q82: =INDIRECT(Q$11&"!"&$B82) -> - | R82: =SUM(F82:Q82) -> 0
B83: G244 | D83: 戻り受注率 | F83: =INDIRECT(F$11&"!"&$B83) -> - | G83: =INDIRECT(G$11&"!"&$B83) -> 0 | H83: =INDIRECT(H$11&"!"&$B83) -> - | I83: =INDIRECT(I$11&"!"&$B83) -> - | J83: =INDIRECT(J$11&"!"&$B83) -> - | K83: =INDIRECT(K$11&"!"&$B83) -> 0 | L83: =INDIRECT(L$11&"!"&$B83) -> - | M83: =INDIRECT(M$11&"!"&$B83) -> 0 | ... Q83: =INDIRECT(Q$11&"!"&$B83) -> 0 | R83: =R82/R77 -> 0
B85: H238 | C85: =設定用!J15 -> 時川 | D85: 面談対応件数 | F85: =INDIRECT(F$11&"!"&$B85) -> - | G85: =INDIRECT(G$11&"!"&$B85) -> 0 | H85: =INDIRECT(H$11&"!"&$B85) -> - | I85: =INDIRECT(I$11&"!"&$B85) -> - | J85: =INDIRECT(J$11&"!"&$B85) -> - | K85: =INDIRECT(K$11&"!"&$B85) -> 0 | L85: =INDIRECT(L$11&"!"&$B85) -> - | M85: =INDIRECT(M$11&"!"&$B85) -> 0 | ... Q85: =INDIRECT(Q$11&"!"&$B85) -> 0 | R85: =SUM(F85:Q85) -> 0
B86: H239 | D86: 受注件数 | F86: =INDIRECT(F$11&"!"&$B86) -> 0 | G86: =INDIRECT(G$11&"!"&$B86) -> - | H86: =INDIRECT(H$11&"!"&$B86) -> 0 | I86: =INDIRECT(I$11&"!"&$B86) -> 0 | J86: =INDIRECT(J$11&"!"&$B86) -> 0 | K86: =INDIRECT(K$11&"!"&$B86) -> - | L86: =INDIRECT(L$11&"!"&$B86) -> 0 | M86: =INDIRECT(M$11&"!"&$B86) -> - | ... Q86: =INDIRECT(Q$11&"!"&$B86) -> - | R86: =SUM(F86:Q86) -> 0
B87: H240 | D87: 受注率 | F87: =INDIRECT(F$11&"!"&$B87) -> - | G87: =INDIRECT(G$11&"!"&$B87) -> 0 | H87: =INDIRECT(H$11&"!"&$B87) -> - | I87: =INDIRECT(I$11&"!"&$B87) -> - | J87: =INDIRECT(J$11&"!"&$B87) -> - | K87: =INDIRECT(K$11&"!"&$B87) -> 0 | L87: =INDIRECT(L$11&"!"&$B87) -> - | M87: =INDIRECT(M$11&"!"&$B87) -> 0 | ... Q87: =INDIRECT(Q$11&"!"&$B87) -> 0 | R87: =R86/R85 -> #DIV/0!
B88: H241 | D88: 即受注 件数 | F88: =INDIRECT(F$11&"!"&$B88) -> 0 | G88: =INDIRECT(G$11&"!"&$B88) -> - | H88: =INDIRECT(H$11&"!"&$B88) -> 0 | I88: =INDIRECT(I$11&"!"&$B88) -> 0 | J88: =INDIRECT(J$11&"!"&$B88) -> 0 | K88: =INDIRECT(K$11&"!"&$B88) -> - | L88: =INDIRECT(L$11&"!"&$B88) -> 0 | M88: =INDIRECT(M$11&"!"&$B88) -> - | ... Q88: =INDIRECT(Q$11&"!"&$B88) -> - | R88: =SUM(F88:Q88) -> 0
B89: H242 | D89: 即受注率 | F89: =INDIRECT(F$11&"!"&$B89) -> - | G89: =INDIRECT(G$11&"!"&$B89) -> 0 | H89: =INDIRECT(H$11&"!"&$B89) -> - | I89: =INDIRECT(I$11&"!"&$B89) -> - | J89: =INDIRECT(J$11&"!"&$B89) -> - | K89: =INDIRECT(K$11&"!"&$B89) -> 0 | L89: =INDIRECT(L$11&"!"&$B89) -> - | M89: =INDIRECT(M$11&"!"&$B89) -> 0 | ... Q89: =INDIRECT(Q$11&"!"&$B89) -> 0 | R89: =R88/R85 -> #DIV/0!
B90: H243 | D90: 戻り受注 件数 | F90: =INDIRECT(F$11&"!"&$B90) -> 0 | G90: =INDIRECT(G$11&"!"&$B90) -> - | H90: =INDIRECT(H$11&"!"&$B90) -> 0 | I90: =INDIRECT(I$11&"!"&$B90) -> 0 | J90: =INDIRECT(J$11&"!"&$B90) -> 0 | K90: =INDIRECT(K$11&"!"&$B90) -> - | L90: =INDIRECT(L$11&"!"&$B90) -> 0 | M90: =INDIRECT(M$11&"!"&$B90) -> - | ... Q90: =INDIRECT(Q$11&"!"&$B90) -> - | R90: =SUM(F90:Q90) -> 0
B91: H244 | D91: 戻り受注率 | F91: =INDIRECT(F$11&"!"&$B91) -> - | G91: =INDIRECT(G$11&"!"&$B91) -> 0 | H91: =INDIRECT(H$11&"!"&$B91) -> - | I91: =INDIRECT(I$11&"!"&$B91) -> - | J91: =INDIRECT(J$11&"!"&$B91) -> - | K91: =INDIRECT(K$11&"!"&$B91) -> 0 | L91: =INDIRECT(L$11&"!"&$B91) -> - | M91: =INDIRECT(M$11&"!"&$B91) -> 0 | ... Q91: =INDIRECT(Q$11&"!"&$B91) -> 0 | R91: =R90/R85 -> #DIV/0!
B93: I238 | C93: =設定用!J16 -> 嶋津 | D93: 面談対応件数 | F93: =INDIRECT(F$11&"!"&$B93) -> 0.66666667 | G93: =INDIRECT(G$11&"!"&$B93) -> 0 | H93: =INDIRECT(H$11&"!"&$B93) -> 0.28571429 | I93: =INDIRECT(I$11&"!"&$B93) -> 0.14285714 | J93: =INDIRECT(J$11&"!"&$B93) -> - | K93: =INDIRECT(K$11&"!"&$B93) -> 0 | L93: =INDIRECT(L$11&"!"&$B93) -> - | M93: =INDIRECT(M$11&"!"&$B93) -> 0 | ... Q93: =INDIRECT(Q$11&"!"&$B93) -> 0 | R93: =SUM(F93:Q93) -> 1.0952381
B94: I239 | D94: 受注件数 | F94: =INDIRECT(F$11&"!"&$B94) -> 0 | G94: =INDIRECT(G$11&"!"&$B94) -> 0 | H94: =INDIRECT(H$11&"!"&$B94) -> 0 | I94: =INDIRECT(I$11&"!"&$B94) -> 0 | J94: =INDIRECT(J$11&"!"&$B94) -> 0 | K94: =INDIRECT(K$11&"!"&$B94) -> - | L94: =INDIRECT(L$11&"!"&$B94) -> 0 | M94: =INDIRECT(M$11&"!"&$B94) -> - | ... Q94: =INDIRECT(Q$11&"!"&$B94) -> - | R94: =SUM(F94:Q94) -> 0
B95: I240 | D95: 受注率 | F95: =INDIRECT(F$11&"!"&$B95) -> 0 | G95: =INDIRECT(G$11&"!"&$B95) -> 0 | H95: =INDIRECT(H$11&"!"&$B95) -> 0 | I95: =INDIRECT(I$11&"!"&$B95) -> 0 | J95: =INDIRECT(J$11&"!"&$B95) -> - | K95: =INDIRECT(K$11&"!"&$B95) -> 0 | L95: =INDIRECT(L$11&"!"&$B95) -> - | M95: =INDIRECT(M$11&"!"&$B95) -> 0 | ... Q95: =INDIRECT(Q$11&"!"&$B95) -> 0 | R95: =R94/R93 -> 0
B96: I241 | D96: 即受注 件数 | F96: =INDIRECT(F$11&"!"&$B96) -> 0 | G96: =INDIRECT(G$11&"!"&$B96) -> 0 | H96: =INDIRECT(H$11&"!"&$B96) -> 0 | I96: =INDIRECT(I$11&"!"&$B96) -> 0 | J96: =INDIRECT(J$11&"!"&$B96) -> 0 | K96: =INDIRECT(K$11&"!"&$B96) -> - | L96: =INDIRECT(L$11&"!"&$B96) -> 0 | M96: =INDIRECT(M$11&"!"&$B96) -> - | ... Q96: =INDIRECT(Q$11&"!"&$B96) -> - | R96: =SUM(F96:Q96) -> 0
B97: I242 | D97: 即受注率 | F97: =INDIRECT(F$11&"!"&$B97) -> - | G97: =INDIRECT(G$11&"!"&$B97) -> 0 | H97: =INDIRECT(H$11&"!"&$B97) -> - | I97: =INDIRECT(I$11&"!"&$B97) -> - | J97: =INDIRECT(J$11&"!"&$B97) -> - | K97: =INDIRECT(K$11&"!"&$B97) -> 0 | L97: =INDIRECT(L$11&"!"&$B97) -> - | M97: =INDIRECT(M$11&"!"&$B97) -> 0 | ... Q97: =INDIRECT(Q$11&"!"&$B97) -> 0 | R97: =R96/R93 -> 0
B98: I243 | D98: 戻り受注 件数 | F98: =INDIRECT(F$11&"!"&$B98) -> 0 | G98: =INDIRECT(G$11&"!"&$B98) -> 0 | H98: =INDIRECT(H$11&"!"&$B98) -> 1 | I98: =INDIRECT(I$11&"!"&$B98) -> 0 | J98: =INDIRECT(J$11&"!"&$B98) -> 0 | K98: =INDIRECT(K$11&"!"&$B98) -> - | L98: =INDIRECT(L$11&"!"&$B98) -> 0 | M98: =INDIRECT(M$11&"!"&$B98) -> - | ... Q98: =INDIRECT(Q$11&"!"&$B98) -> - | R98: =SUM(F98:Q98) -> 1
B99: I244 | D99: 戻り受注率 | F99: =INDIRECT(F$11&"!"&$B99) -> - | G99: =INDIRECT(G$11&"!"&$B99) -> 0 | H99: =INDIRECT(H$11&"!"&$B99) -> - | I99: =INDIRECT(I$11&"!"&$B99) -> - | J99: =INDIRECT(J$11&"!"&$B99) -> - | K99: =INDIRECT(K$11&"!"&$B99) -> 0 | L99: =INDIRECT(L$11&"!"&$B99) -> - | M99: =INDIRECT(M$11&"!"&$B99) -> 0 | ... Q99: =INDIRECT(Q$11&"!"&$B99) -> 0 | R99: =R98/R93 -> 0.91304348
B101: J238 | C101: =設定用!J17 -> 馬場 | D101: 面談対応件数 | F101: =INDIRECT(F$11&"!"&$B101) -> 0 | G101: =INDIRECT(G$11&"!"&$B101) -> 0 | H101: =INDIRECT(H$11&"!"&$B101) -> - | I101: =INDIRECT(I$11&"!"&$B101) -> 0.25 | J101: =INDIRECT(J$11&"!"&$B101) -> - | K101: =INDIRECT(K$11&"!"&$B101) -> 0 | L101: =INDIRECT(L$11&"!"&$B101) -> - | M101: =INDIRECT(M$11&"!"&$B101) -> 0 | ... Q101: =INDIRECT(Q$11&"!"&$B101) -> 0 | R101: =SUM(F101:Q101) -> 0.25
B102: J239 | D102: 受注件数 | F102: =INDIRECT(F$11&"!"&$B102) -> 0 | G102: =INDIRECT(G$11&"!"&$B102) -> 0 | H102: =INDIRECT(H$11&"!"&$B102) -> 0 | I102: =INDIRECT(I$11&"!"&$B102) -> 0 | J102: =INDIRECT(J$11&"!"&$B102) -> 0 | K102: =INDIRECT(K$11&"!"&$B102) -> - | L102: =INDIRECT(L$11&"!"&$B102) -> 0 | M102: =INDIRECT(M$11&"!"&$B102) -> - | ... Q102: =INDIRECT(Q$11&"!"&$B102) -> - | R102: =SUM(F102:Q102) -> 0
B103: J240 | D103: 受注率 | F103: =INDIRECT(F$11&"!"&$B103) -> 0 | G103: =INDIRECT(G$11&"!"&$B103) -> 0 | H103: =INDIRECT(H$11&"!"&$B103) -> - | I103: =INDIRECT(I$11&"!"&$B103) -> 0 | J103: =INDIRECT(J$11&"!"&$B103) -> - | K103: =INDIRECT(K$11&"!"&$B103) -> 0 | L103: =INDIRECT(L$11&"!"&$B103) -> - | M103: =INDIRECT(M$11&"!"&$B103) -> 0 | ... Q103: =INDIRECT(Q$11&"!"&$B103) -> 0 | R103: =R102/R101 -> 0
B104: J241 | D104: 即受注 件数 | F104: =INDIRECT(F$11&"!"&$B104) -> 0 | G104: =INDIRECT(G$11&"!"&$B104) -> 0 | H104: =INDIRECT(H$11&"!"&$B104) -> 0 | I104: =INDIRECT(I$11&"!"&$B104) -> 1 | J104: =INDIRECT(J$11&"!"&$B104) -> 0 | K104: =INDIRECT(K$11&"!"&$B104) -> - | L104: =INDIRECT(L$11&"!"&$B104) -> 0 | M104: =INDIRECT(M$11&"!"&$B104) -> - | ... Q104: =INDIRECT(Q$11&"!"&$B104) -> - | R104: =SUM(F104:Q104) -> 1
B105: J242 | D105: 即受注率 | F105: =INDIRECT(F$11&"!"&$B105) -> - | G105: =INDIRECT(G$11&"!"&$B105) -> 0 | H105: =INDIRECT(H$11&"!"&$B105) -> - | I105: =INDIRECT(I$11&"!"&$B105) -> - | J105: =INDIRECT(J$11&"!"&$B105) -> - | K105: =INDIRECT(K$11&"!"&$B105) -> 0 | L105: =INDIRECT(L$11&"!"&$B105) -> - | M105: =INDIRECT(M$11&"!"&$B105) -> 0 | ... Q105: =INDIRECT(Q$11&"!"&$B105) -> 0 | R105: =R104/R101 -> 4
B106: J243 | D106: 戻り受注 件数 | F106: =INDIRECT(F$11&"!"&$B106) -> 1 | G106: =INDIRECT(G$11&"!"&$B106) -> 0 | H106: =INDIRECT(H$11&"!"&$B106) -> 0 | I106: =INDIRECT(I$11&"!"&$B106) -> 0 | J106: =INDIRECT(J$11&"!"&$B106) -> 0 | K106: =INDIRECT(K$11&"!"&$B106) -> - | L106: =INDIRECT(L$11&"!"&$B106) -> 0 | M106: =INDIRECT(M$11&"!"&$B106) -> - | ... Q106: =INDIRECT(Q$11&"!"&$B106) -> - | R106: =SUM(F106:Q106) -> 1
B107: J244 | D107: 戻り受注率 | F107: =INDIRECT(F$11&"!"&$B107) -> - | G107: =INDIRECT(G$11&"!"&$B107) -> 0 | H107: =INDIRECT(H$11&"!"&$B107) -> - | I107: =INDIRECT(I$11&"!"&$B107) -> - | J107: =INDIRECT(J$11&"!"&$B107) -> - | K107: =INDIRECT(K$11&"!"&$B107) -> 0 | L107: =INDIRECT(L$11&"!"&$B107) -> - | M107: =INDIRECT(M$11&"!"&$B107) -> 0 | ... Q107: =INDIRECT(Q$11&"!"&$B107) -> 0 | R107: =R106/R101 -> 4
B109: K238 | C109: =設定用!J18 -> 和田 | D109: 面談対応件数 | F109: =INDIRECT(F$11&"!"&$B109) -> - | G109: =INDIRECT(G$11&"!"&$B109) -> 0 | H109: =INDIRECT(H$11&"!"&$B109) -> - | I109: =INDIRECT(I$11&"!"&$B109) -> - | J109: =INDIRECT(J$11&"!"&$B109) -> - | K109: =INDIRECT(K$11&"!"&$B109) -> 0 | L109: =INDIRECT(L$11&"!"&$B109) -> - | M109: =INDIRECT(M$11&"!"&$B109) -> 0 | ... Q109: =INDIRECT(Q$11&"!"&$B109) -> 0 | R109: =SUM(F109:Q109) -> 0
B110: K239 | D110: 受注件数 | F110: =INDIRECT(F$11&"!"&$B110) -> 0 | G110: =INDIRECT(G$11&"!"&$B110) -> - | H110: =INDIRECT(H$11&"!"&$B110) -> 0 | I110: =INDIRECT(I$11&"!"&$B110) -> 0 | J110: =INDIRECT(J$11&"!"&$B110) -> 0 | K110: =INDIRECT(K$11&"!"&$B110) -> - | L110: =INDIRECT(L$11&"!"&$B110) -> 0 | M110: =INDIRECT(M$11&"!"&$B110) -> - | ... Q110: =INDIRECT(Q$11&"!"&$B110) -> - | R110: =SUM(F110:Q110) -> 0
B111: K240 | D111: 受注率 | F111: =INDIRECT(F$11&"!"&$B111) -> - | G111: =INDIRECT(G$11&"!"&$B111) -> 0 | H111: =INDIRECT(H$11&"!"&$B111) -> - | I111: =INDIRECT(I$11&"!"&$B111) -> - | J111: =INDIRECT(J$11&"!"&$B111) -> - | K111: =INDIRECT(K$11&"!"&$B111) -> 0 | L111: =INDIRECT(L$11&"!"&$B111) -> - | M111: =INDIRECT(M$11&"!"&$B111) -> 0 | ... Q111: =INDIRECT(Q$11&"!"&$B111) -> 0 | R111: =R110/R109 -> #DIV/0!
B112: K241 | D112: 即受注 件数 | F112: =INDIRECT(F$11&"!"&$B112) -> 0 | G112: =INDIRECT(G$11&"!"&$B112) -> - | H112: =INDIRECT(H$11&"!"&$B112) -> 0 | I112: =INDIRECT(I$11&"!"&$B112) -> 0 | J112: =INDIRECT(J$11&"!"&$B112) -> 0 | K112: =INDIRECT(K$11&"!"&$B112) -> - | L112: =INDIRECT(L$11&"!"&$B112) -> 0 | M112: =INDIRECT(M$11&"!"&$B112) -> - | ... Q112: =INDIRECT(Q$11&"!"&$B112) -> - | R112: =SUM(F112:Q112) -> 0
B113: K242 | D113: 即受注率 | F113: =INDIRECT(F$11&"!"&$B113) -> - | G113: =INDIRECT(G$11&"!"&$B113) -> 0 | H113: =INDIRECT(H$11&"!"&$B113) -> - | I113: =INDIRECT(I$11&"!"&$B113) -> - | J113: =INDIRECT(J$11&"!"&$B113) -> - | K113: =INDIRECT(K$11&"!"&$B113) -> 0 | L113: =INDIRECT(L$11&"!"&$B113) -> - | M113: =INDIRECT(M$11&"!"&$B113) -> 0 | ... Q113: =INDIRECT(Q$11&"!"&$B113) -> 0 | R113: =R112/R109 -> #DIV/0!
B114: K243 | D114: 戻り受注 件数 | F114: =INDIRECT(F$11&"!"&$B114) -> 0 | G114: =INDIRECT(G$11&"!"&$B114) -> - | H114: =INDIRECT(H$11&"!"&$B114) -> 0 | I114: =INDIRECT(I$11&"!"&$B114) -> 0 | J114: =INDIRECT(J$11&"!"&$B114) -> 0 | K114: =INDIRECT(K$11&"!"&$B114) -> - | L114: =INDIRECT(L$11&"!"&$B114) -> 0 | M114: =INDIRECT(M$11&"!"&$B114) -> - | ... Q114: =INDIRECT(Q$11&"!"&$B114) -> - | R114: =SUM(F114:Q114) -> 0
...

Sheet 案件別受注率集計
C2: 受注率 集計 | F2: 1月 | G2: 2月 | H2: 3月 | I2: 4月 | J2: 5月 | K2: 6月 | L2: 7月 | M2: 8月 | N2: 9月 | O2: 10月 | P2: 11月 | Q2: 12月 | R2: 年間
C3: 総計 | D3: 面談対応件数 | F3: =SUM(F13,F21,F29,F37,F45,F53,F61,F69,F77,F85) -> 2.0939394 | G3: =SUM(G13,G21,G29,G37,G45,G53,G61,G69,G77,G85) -> 7 | H3: =SUM(H13,H21,H29,H37,H45,H53,H61,H69,H77,H85) -> 2.7670455 | I3: =SUM(I13,I21,I29,I37,I45,I53,I61,I69,I77,I85) -> 1.4393939 | J3: =SUM(J13,J21,J29,J37,J45,J53,J61,J69,J77,J85) -> 0 | K3: =SUM(K13,K21,K29,K37,K45,K53,K61,K69,K77,K85) -> 0 | L3: =SUM(L13,L21,L29,L37,L45,L53,L61,L69,L77,L85) -> 0 | M3: =SUM(M13,M21,M29,M37,M45,M53,M61,M69,M77,M85) -> 0 | ... Q3: =SUM(Q13,Q21,Q29,Q37,Q45,Q53,Q61,Q69,Q77,Q85) -> 0 | R3: =SUM(F3:Q3) -> 13.300379
D4: 受注件数 | F4: =SUM(F14,F22,F30,F38,F46,F54,F62,F70,F78,F86) -> 4 | G4: =SUM(G14,G22,G30,G38,G46,G54,G62,G70,G78,G86) -> 1.2357143 | H4: =SUM(H14,H22,H30,H38,H46,H54,H62,H70,H78,H86) -> 2 | I4: =SUM(I14,I22,I30,I38,I46,I54,I62,I70,I78,I86) -> 2 | J4: =SUM(J14,J22,J30,J38,J46,J54,J62,J70,J78,J86) -> 0 | K4: =SUM(K14,K22,K30,K38,K46,K54,K62,K70,K78,K86) -> 0 | L4: =SUM(L14,L22,L30,L38,L46,L54,L62,L70,L78,L86) -> 0 | M4: =SUM(M14,M22,M30,M38,M46,M54,M62,M70,M78,M86) -> 0 | ... Q4: =SUM(Q14,Q22,Q30,Q38,Q46,Q54,Q62,Q70,Q78,Q86) -> 0 | R4: =SUM(F4:Q4) -> 9.2357143
D5: 受注率 | F5: =F4/F3 -> 1.910275 | G5: =G4/G3 -> 0.17653061 | H5: =H4/H3 -> 0.72279261 | I5: =I4/I3 -> 1.3894737 | J5: =J4/J3 -> #DIV/0! | K5: =K4/K3 -> #DIV/0! | L5: =L4/L3 -> #DIV/0! | M5: =M4/M3 -> #DIV/0! | ... R5: =R4/R3 -> 0.69439483
D6: 即受注 件数 | F6: =SUM(F16,F24,F32,F40,F48,F56,F64,F72,F80,F88) -> 2 | G6: =SUM(G16,G24,G32,G40,G48,G56,G64,G72,G80,G88) -> 0.91428571 | H6: =SUM(H16,H24,H32,H40,H48,H56,H64,H72,H80,H88) -> 3 | I6: =SUM(I16,I24,I32,I40,I48,I56,I64,I72,I80,I88) -> 3 | J6: =SUM(J16,J24,J32,J40,J48,J56,J64,J72,J80,J88) -> 0 | K6: =SUM(K16,K24,K32,K40,K48,K56,K64,K72,K80,K88) -> 0 | L6: =SUM(L16,L24,L32,L40,L48,L56,L64,L72,L80,L88) -> 0 | M6: =SUM(M16,M24,M32,M40,M48,M56,M64,M72,M80,M88) -> 0 | ... Q6: =SUM(Q16,Q24,Q32,Q40,Q48,Q56,Q64,Q72,Q80,Q88) -> 0 | R6: =SUM(F6:Q6) -> 8.9142857
D7: 即受注率 | F7: =F6/F$3 -> 0.95513748 | G7: =G6/G$3 -> 0.13061224 | H7: =H6/H$3 -> 1.0841889 | I7: =I6/I$3 -> 2.0842105 | J7: =J6/J$3 -> #DIV/0! | K7: =K6/K$3 -> #DIV/0! | L7: =L6/L$3 -> #DIV/0! | M7: =M6/M$3 -> #DIV/0! | ... Q7: =Q6/Q$3 -> #DIV/0! | R7: =R6/R3 -> 0.67022796
D8: 戻り受注 件数 | F8: =SUM(F18,F26,F34,F42,F50,F58,F66,F74,F82,F90) -> 12 | G8: =SUM(G18,G26,G34,G42,G50,G58,G66,G74,G82,G90) -> 0 | H8: =SUM(H18,H26,H34,H42,H50,H58,H66,H74,H82,H90) -> 12 | I8: =SUM(I18,I26,I34,I42,I50,I58,I66,I74,I82,I90) -> 11 | J8: =SUM(J18,J26,J34,J42,J50,J58,J66,J74,J82,J90) -> 0 | K8: =SUM(K18,K26,K34,K42,K50,K58,K66,K74,K82,K90) -> 0 | L8: =SUM(L18,L26,L34,L42,L50,L58,L66,L74,L82,L90) -> 0 | M8: =SUM(M18,M26,M34,M42,M50,M58,M66,M74,M82,M90) -> 0 | ... Q8: =SUM(Q18,Q26,Q34,Q42,Q50,Q58,Q66,Q74,Q82,Q90) -> 0 | R8: =SUM(F8:Q8) -> 35
D9: 戻り受注率 | F9: =F8/F$3 -> 5.7308249 | G9: =G8/G$3 -> 0 | H9: =H8/H$3 -> 4.3367556 | I9: =I8/I$3 -> 7.6421053 | J9: =J8/J$3 -> #DIV/0! | K9: =K8/K$3 -> #DIV/0! | L9: =L8/L$3 -> #DIV/0! | M9: =M8/M$3 -> #DIV/0! | ... Q9: =Q8/Q$3 -> #DIV/0! | R9: =R8/R3 -> 2.631504
F11: 1月 | G11: 2月 | H11: 3月 | I11: 4月 | J11: 5月 | K11: 6月 | L11: 7月 | M11: 8月 | N11: 9月 | O11: 10月 | P11: 11月 | Q11: 12月
C12: 受注率 集計 | F12: 1月 | G12: 2月 | H12: 3月 | I12: 4月 | J12: 5月 | K12: 6月 | L12: 7月 | M12: 8月 | N12: 9月 | O12: 10月 | P12: 11月 | Q12: 12月 | R12: 年間
B13: D257 | C13: =設定用!D6 -> 相続手続き | D13: 面談対応件数 | F13: =INDIRECT(F$11&"!"&$B13) -> 0.36363636 | G13: =INDIRECT(G$11&"!"&$B13) -> 2 | H13: =INDIRECT(H$11&"!"&$B13) -> 0.27272727 | I13: =INDIRECT(I$11&"!"&$B13) -> 0.090909091 | J13: =INDIRECT(J$11&"!"&$B13) -> - | K13: =INDIRECT(K$11&"!"&$B13) -> 0 | L13: =INDIRECT(L$11&"!"&$B13) -> - | M13: =INDIRECT(M$11&"!"&$B13) -> 0 | ... Q13: =INDIRECT(Q$11&"!"&$B13) -> 0 | R13: =SUM(F13:Q13) -> 2.7272727
B14: D258 | D14: 受注件数 | F14: =INDIRECT(F$11&"!"&$B14) -> 0 | G14: =INDIRECT(G$11&"!"&$B14) -> 0.28571429 | H14: =INDIRECT(H$11&"!"&$B14) -> 1 | I14: =INDIRECT(I$11&"!"&$B14) -> 1 | J14: =INDIRECT(J$11&"!"&$B14) -> 0 | K14: =INDIRECT(K$11&"!"&$B14) -> - | L14: =INDIRECT(L$11&"!"&$B14) -> 0 | M14: =INDIRECT(M$11&"!"&$B14) -> - | ... Q14: =INDIRECT(Q$11&"!"&$B14) -> - | R14: =SUM(F14:Q14) -> 2.2857143
B15: D259 | D15: 受注率 | F15: =INDIRECT(F$11&"!"&$B15) -> 0 | G15: =INDIRECT(G$11&"!"&$B15) -> 2 | H15: =INDIRECT(H$11&"!"&$B15) -> 0.090909091 | I15: =INDIRECT(I$11&"!"&$B15) -> 0.090909091 | J15: =INDIRECT(J$11&"!"&$B15) -> - | K15: =INDIRECT(K$11&"!"&$B15) -> 0 | L15: =INDIRECT(L$11&"!"&$B15) -> - | M15: =INDIRECT(M$11&"!"&$B15) -> 0 | ... Q15: =INDIRECT(Q$11&"!"&$B15) -> 0 | R15: =R14/R13 -> 0.83809524
B16: D260 | D16: 即受注 件数 | F16: =INDIRECT(F$11&"!"&$B16) -> 1 | G16: =INDIRECT(G$11&"!"&$B16) -> 0.28571429 | H16: =INDIRECT(H$11&"!"&$B16) -> 1 | I16: =INDIRECT(I$11&"!"&$B16) -> 0 | J16: =INDIRECT(J$11&"!"&$B16) -> 0 | K16: =INDIRECT(K$11&"!"&$B16) -> - | L16: =INDIRECT(L$11&"!"&$B16) -> 0 | M16: =INDIRECT(M$11&"!"&$B16) -> - | ... Q16: =INDIRECT(Q$11&"!"&$B16) -> - | R16: =SUM(F16:Q16) -> 2.2857143
B17: D261 | D17: 即受注率 | F17: =INDIRECT(F$11&"!"&$B17) -> 0.090909091 | G17: =INDIRECT(G$11&"!"&$B17) -> 0 | H17: =INDIRECT(H$11&"!"&$B17) -> 0.090909091 | I17: =INDIRECT(I$11&"!"&$B17) -> 0 | J17: =INDIRECT(J$11&"!"&$B17) -> - | K17: =INDIRECT(K$11&"!"&$B17) -> 0 | L17: =INDIRECT(L$11&"!"&$B17) -> - | M17: =INDIRECT(M$11&"!"&$B17) -> 0 | ... Q17: =INDIRECT(Q$11&"!"&$B17) -> 0 | R17: =R16/R13 -> 0.83809524
B18: D262 | D18: 戻り受注 件数 | F18: =INDIRECT(F$11&"!"&$B18) -> 4 | G18: =INDIRECT(G$11&"!"&$B18) -> 0 | H18: =INDIRECT(H$11&"!"&$B18) -> 3 | I18: =INDIRECT(I$11&"!"&$B18) -> 3 | J18: =INDIRECT(J$11&"!"&$B18) -> 0 | K18: =INDIRECT(K$11&"!"&$B18) -> - | L18: =INDIRECT(L$11&"!"&$B18) -> 0 | M18: =INDIRECT(M$11&"!"&$B18) -> - | ... Q18: =INDIRECT(Q$11&"!"&$B18) -> - | R18: =SUM(F18:Q18) -> 10
B19: D263 | D19: 戻り受注率 | F19: =INDIRECT(F$11&"!"&$B19) -> 0.36363636 | G19: =INDIRECT(G$11&"!"&$B19) -> 2 | H19: =INDIRECT(H$11&"!"&$B19) -> 0.27272727 | I19: =INDIRECT(I$11&"!"&$B19) -> 0.27272727 | J19: =INDIRECT(J$11&"!"&$B19) -> - | K19: =INDIRECT(K$11&"!"&$B19) -> 0 | L19: =INDIRECT(L$11&"!"&$B19) -> - | M19: =INDIRECT(M$11&"!"&$B19) -> 0 | ... Q19: =INDIRECT(Q$11&"!"&$B19) -> 0 | R19: =R18/R13 -> 3.6666667
B21: E257 | C21: =設定用!D7 -> 名義変更 | D21: 面談対応件数 | F21: =INDIRECT(F$11&"!"&$B21) -> 0.5 | G21: =INDIRECT(G$11&"!"&$B21) -> 0 | H21: =INDIRECT(H$11&"!"&$B21) -> 1 | I21: =INDIRECT(I$11&"!"&$B21) -> 1 | J21: =INDIRECT(J$11&"!"&$B21) -> - | K21: =INDIRECT(K$11&"!"&$B21) -> 0 | L21: =INDIRECT(L$11&"!"&$B21) -> - | M21: =INDIRECT(M$11&"!"&$B21) -> 0 | ... Q21: =INDIRECT(Q$11&"!"&$B21) -> 0 | R21: =SUM(F21:Q21) -> 2.5
B22: E258 | D22: 受注件数 | F22: =INDIRECT(F$11&"!"&$B22) -> 0 | G22: =INDIRECT(G$11&"!"&$B22) -> 0 | H22: =INDIRECT(H$11&"!"&$B22) -> 0 | I22: =INDIRECT(I$11&"!"&$B22) -> 0 | J22: =INDIRECT(J$11&"!"&$B22) -> 0 | K22: =INDIRECT(K$11&"!"&$B22) -> - | L22: =INDIRECT(L$11&"!"&$B22) -> 0 | M22: =INDIRECT(M$11&"!"&$B22) -> - | ... Q22: =INDIRECT(Q$11&"!"&$B22) -> - | R22: =SUM(F22:Q22) -> 0
B23: E259 | D23: 受注率 | F23: =INDIRECT(F$11&"!"&$B23) -> 0 | G23: =INDIRECT(G$11&"!"&$B23) -> 0 | H23: =INDIRECT(H$11&"!"&$B23) -> 0 | I23: =INDIRECT(I$11&"!"&$B23) -> 0 | J23: =INDIRECT(J$11&"!"&$B23) -> - | K23: =INDIRECT(K$11&"!"&$B23) -> 0 | L23: =INDIRECT(L$11&"!"&$B23) -> - | M23: =INDIRECT(M$11&"!"&$B23) -> 0 | ... Q23: =INDIRECT(Q$11&"!"&$B23) -> 0 | R23: =R22/R21 -> 0
B24: E260 | D24: 即受注 件数 | F24: =INDIRECT(F$11&"!"&$B24) -> 0 | G24: =INDIRECT(G$11&"!"&$B24) -> 0 | H24: =INDIRECT(H$11&"!"&$B24) -> 0 | I24: =INDIRECT(I$11&"!"&$B24) -> 0 | J24: =INDIRECT(J$11&"!"&$B24) -> 0 | K24: =INDIRECT(K$11&"!"&$B24) -> - | L24: =INDIRECT(L$11&"!"&$B24) -> 0 | M24: =INDIRECT(M$11&"!"&$B24) -> - | ... Q24: =INDIRECT(Q$11&"!"&$B24) -> - | R24: =SUM(F24:Q24) -> 0
B25: E261 | D25: 即受注率 | F25: =INDIRECT(F$11&"!"&$B25) -> 0 | G25: =INDIRECT(G$11&"!"&$B25) -> 0 | H25: =INDIRECT(H$11&"!"&$B25) -> 0 | I25: =INDIRECT(I$11&"!"&$B25) -> 0 | J25: =INDIRECT(J$11&"!"&$B25) -> - | K25: =INDIRECT(K$11&"!"&$B25) -> 0 | L25: =INDIRECT(L$11&"!"&$B25) -> - | M25: =INDIRECT(M$11&"!"&$B25) -> 0 | ... Q25: =INDIRECT(Q$11&"!"&$B25) -> 0 | R25: =R24/R21 -> 0
B26: E262 | D26: 戻り受注 件数 | F26: =INDIRECT(F$11&"!"&$B26) -> 0 | G26: =INDIRECT(G$11&"!"&$B26) -> 0 | H26: =INDIRECT(H$11&"!"&$B26) -> 0 | I26: =INDIRECT(I$11&"!"&$B26) -> 0 | J26: =INDIRECT(J$11&"!"&$B26) -> 0 | K26: =INDIRECT(K$11&"!"&$B26) -> - | L26: =INDIRECT(L$11&"!"&$B26) -> 0 | M26: =INDIRECT(M$11&"!"&$B26) -> - | ... Q26: =INDIRECT(Q$11&"!"&$B26) -> - | R26: =SUM(F26:Q26) -> 0
B27: E263 | D27: 戻り受注率 | F27: =INDIRECT(F$11&"!"&$B27) -> 0 | G27: =INDIRECT(G$11&"!"&$B27) -> 0 | H27: =INDIRECT(H$11&"!"&$B27) -> 0 | I27: =INDIRECT(I$11&"!"&$B27) -> 0 | J27: =INDIRECT(J$11&"!"&$B27) -> - | K27: =INDIRECT(K$11&"!"&$B27) -> 0 | L27: =INDIRECT(L$11&"!"&$B27) -> - | M27: =INDIRECT(M$11&"!"&$B27) -> 0 | ... Q27: =INDIRECT(Q$11&"!"&$B27) -> 0 | R27: =R26/R21 -> 0
B29: F257 | C29: =設定用!D8 -> 相続税申告 | D29: 面談対応件数 | F29: =INDIRECT(F$11&"!"&$B29) -> 0.66666667 | G29: =INDIRECT(G$11&"!"&$B29) -> 0 | H29: =INDIRECT(H$11&"!"&$B29) -> 0 | I29: =INDIRECT(I$11&"!"&$B29) -> 0 | J29: =INDIRECT(J$11&"!"&$B29) -> - | K29: =INDIRECT(K$11&"!"&$B29) -> 0 | L29: =INDIRECT(L$11&"!"&$B29) -> - | M29: =INDIRECT(M$11&"!"&$B29) -> 0 | ... Q29: =INDIRECT(Q$11&"!"&$B29) -> 0 | R29: =SUM(F29:Q29) -> 0.66666667
B30: F258 | D30: 受注件数 | F30: =INDIRECT(F$11&"!"&$B30) -> 0 | G30: =INDIRECT(G$11&"!"&$B30) -> - | H30: =INDIRECT(H$11&"!"&$B30) -> 0 | I30: =INDIRECT(I$11&"!"&$B30) -> 0 | J30: =INDIRECT(J$11&"!"&$B30) -> 0 | K30: =INDIRECT(K$11&"!"&$B30) -> - | L30: =INDIRECT(L$11&"!"&$B30) -> 0 | M30: =INDIRECT(M$11&"!"&$B30) -> - | ... Q30: =INDIRECT(Q$11&"!"&$B30) -> - | R30: =SUM(F30:Q30) -> 0
B31: F259 | D31: 受注率 | F31: =INDIRECT(F$11&"!"&$B31) -> 0 | G31: =INDIRECT(G$11&"!"&$B31) -> 0 | H31: =INDIRECT(H$11&"!"&$B31) -> 0 | I31: =INDIRECT(I$11&"!"&$B31) -> 0 | J31: =INDIRECT(J$11&"!"&$B31) -> - | K31: =INDIRECT(K$11&"!"&$B31) -> 0 | L31: =INDIRECT(L$11&"!"&$B31) -> - | M31: =INDIRECT(M$11&"!"&$B31) -> 0 | ... Q31: =INDIRECT(Q$11&"!"&$B31) -> 0 | R31: =R30/R29 -> 0
B32: F260 | D32: 即受注 件数 | F32: =INDIRECT(F$11&"!"&$B32) -> 0 | G32: =INDIRECT(G$11&"!"&$B32) -> - | H32: =INDIRECT(H$11&"!"&$B32) -> 0 | I32: =INDIRECT(I$11&"!"&$B32) -> 0 | J32: =INDIRECT(J$11&"!"&$B32) -> 0 | K32: =INDIRECT(K$11&"!"&$B32) -> - | L32: =INDIRECT(L$11&"!"&$B32) -> 0 | M32: =INDIRECT(M$11&"!"&$B32) -> - | ... Q32: =INDIRECT(Q$11&"!"&$B32) -> - | R32: =SUM(F32:Q32) -> 0
B33: F261 | D33: 即受注率 | F33: =INDIRECT(F$11&"!"&$B33) -> 0 | G33: =INDIRECT(G$11&"!"&$B33) -> 0 | H33: =INDIRECT(H$11&"!"&$B33) -> 0 | I33: =INDIRECT(I$11&"!"&$B33) -> 0 | J33: =INDIRECT(J$11&"!"&$B33) -> - | K33: =INDIRECT(K$11&"!"&$B33) -> 0 | L33: =INDIRECT(L$11&"!"&$B33) -> - | M33: =INDIRECT(M$11&"!"&$B33) -> 0 | ... Q33: =INDIRECT(Q$11&"!"&$B33) -> 0 | R33: =R32/R29 -> 0
B34: F262 | D34: 戻り受注 件数 | F34: =INDIRECT(F$11&"!"&$B34) -> 1 | G34: =INDIRECT(G$11&"!"&$B34) -> - | H34: =INDIRECT(H$11&"!"&$B34) -> 0 | I34: =INDIRECT(I$11&"!"&$B34) -> 1 | J34: =INDIRECT(J$11&"!"&$B34) -> 0 | K34: =INDIRECT(K$11&"!"&$B34) -> - | L34: =INDIRECT(L$11&"!"&$B34) -> 0 | M34: =INDIRECT(M$11&"!"&$B34) -> - | ... Q34: =INDIRECT(Q$11&"!"&$B34) -> - | R34: =SUM(F34:Q34) -> 2
B35: F263 | D35: 戻り受注率 | F35: =INDIRECT(F$11&"!"&$B35) -> 0.33333333 | G35: =INDIRECT(G$11&"!"&$B35) -> 0 | H35: =INDIRECT(H$11&"!"&$B35) -> 0 | I35: =INDIRECT(I$11&"!"&$B35) -> 0.33333333 | J35: =INDIRECT(J$11&"!"&$B35) -> - | K35: =INDIRECT(K$11&"!"&$B35) -> 0 | L35: =INDIRECT(L$11&"!"&$B35) -> - | M35: =INDIRECT(M$11&"!"&$B35) -> 0 | ... Q35: =INDIRECT(Q$11&"!"&$B35) -> 0 | R35: =R34/R29 -> 3
B37: G257 | C37: =設定用!D9 -> 遺言書 | D37: 面談対応件数 | F37: =INDIRECT(F$11&"!"&$B37) -> 0 | G37: =INDIRECT(G$11&"!"&$B37) -> 2 | H37: =INDIRECT(H$11&"!"&$B37) -> 0.3125 | I37: =INDIRECT(I$11&"!"&$B37) -> 0 | J37: =INDIRECT(J$11&"!"&$B37) -> - | K37: =INDIRECT(K$11&"!"&$B37) -> 0 | L37: =INDIRECT(L$11&"!"&$B37) -> - | M37: =INDIRECT(M$11&"!"&$B37) -> 0 | ... Q37: =INDIRECT(Q$11&"!"&$B37) -> 0 | R37: =SUM(F37:Q37) -> 2.3125
B38: G258 | D38: 受注件数 | F38: =INDIRECT(F$11&"!"&$B38) -> 2 | G38: =INDIRECT(G$11&"!"&$B38) -> 0.2 | H38: =INDIRECT(H$11&"!"&$B38) -> 1 | I38: =INDIRECT(I$11&"!"&$B38) -> 0 | J38: =INDIRECT(J$11&"!"&$B38) -> 0 | K38: =INDIRECT(K$11&"!"&$B38) -> - | L38: =INDIRECT(L$11&"!"&$B38) -> 0 | M38: =INDIRECT(M$11&"!"&$B38) -> - | ... Q38: =INDIRECT(Q$11&"!"&$B38) -> - | R38: =SUM(F38:Q38) -> 3.2
B39: G259 | D39: 受注率 | F39: =INDIRECT(F$11&"!"&$B39) -> 0.28571429 | G39: =INDIRECT(G$11&"!"&$B39) -> 2 | H39: =INDIRECT(H$11&"!"&$B39) -> 0.0625 | I39: =INDIRECT(I$11&"!"&$B39) -> 0 | J39: =INDIRECT(J$11&"!"&$B39) -> - | K39: =INDIRECT(K$11&"!"&$B39) -> 0 | L39: =INDIRECT(L$11&"!"&$B39) -> - | M39: =INDIRECT(M$11&"!"&$B39) -> 0 | ... Q39: =INDIRECT(Q$11&"!"&$B39) -> 0 | R39: =R38/R37 -> 1.3837838
B40: G260 | D40: 即受注 件数 | F40: =INDIRECT(F$11&"!"&$B40) -> 0 | G40: =INDIRECT(G$11&"!"&$B40) -> 0.2 | H40: =INDIRECT(H$11&"!"&$B40) -> 2 | I40: =INDIRECT(I$11&"!"&$B40) -> 0 | J40: =INDIRECT(J$11&"!"&$B40) -> 0 | K40: =INDIRECT(K$11&"!"&$B40) -> - | L40: =INDIRECT(L$11&"!"&$B40) -> 0 | M40: =INDIRECT(M$11&"!"&$B40) -> - | ... Q40: =INDIRECT(Q$11&"!"&$B40) -> - | R40: =SUM(F40:Q40) -> 2.2
B41: G261 | D41: 即受注率 | F41: =INDIRECT(F$11&"!"&$B41) -> 0 | G41: =INDIRECT(G$11&"!"&$B41) -> 0 | H41: =INDIRECT(H$11&"!"&$B41) -> 0.125 | I41: =INDIRECT(I$11&"!"&$B41) -> 0 | J41: =INDIRECT(J$11&"!"&$B41) -> - | K41: =INDIRECT(K$11&"!"&$B41) -> 0 | L41: =INDIRECT(L$11&"!"&$B41) -> - | M41: =INDIRECT(M$11&"!"&$B41) -> 0 | ... Q41: =INDIRECT(Q$11&"!"&$B41) -> 0 | R41: =R40/R37 -> 0.95135135
B42: G262 | D42: 戻り受注 件数 | F42: =INDIRECT(F$11&"!"&$B42) -> 4 | G42: =INDIRECT(G$11&"!"&$B42) -> 0 | H42: =INDIRECT(H$11&"!"&$B42) -> 4 | I42: =INDIRECT(I$11&"!"&$B42) -> 4 | J42: =INDIRECT(J$11&"!"&$B42) -> 0 | K42: =INDIRECT(K$11&"!"&$B42) -> - | L42: =INDIRECT(L$11&"!"&$B42) -> 0 | M42: =INDIRECT(M$11&"!"&$B42) -> - | ... Q42: =INDIRECT(Q$11&"!"&$B42) -> - | R42: =SUM(F42:Q42) -> 12
B43: G263 | D43: 戻り受注率 | F43: =INDIRECT(F$11&"!"&$B43) -> 0.57142857 | G43: =INDIRECT(G$11&"!"&$B43) -> 1 | H43: =INDIRECT(H$11&"!"&$B43) -> 0.25 | I43: =INDIRECT(I$11&"!"&$B43) -> 0.5 | J43: =INDIRECT(J$11&"!"&$B43) -> - | K43: =INDIRECT(K$11&"!"&$B43) -> 0 | L43: =INDIRECT(L$11&"!"&$B43) -> - | M43: =INDIRECT(M$11&"!"&$B43) -> 0 | ... Q43: =INDIRECT(Q$11&"!"&$B43) -> 0 | R43: =R42/R37 -> 5.1891892
B45: H257 | C45: =設定用!D10 -> 生前対策 | D45: 面談対応件数 | F45: =INDIRECT(F$11&"!"&$B45) -> 0 | G45: =INDIRECT(G$11&"!"&$B45) -> 0 | H45: =INDIRECT(H$11&"!"&$B45) -> 0 | I45: =INDIRECT(I$11&"!"&$B45) -> 0 | J45: =INDIRECT(J$11&"!"&$B45) -> - | K45: =INDIRECT(K$11&"!"&$B45) -> 0 | L45: =INDIRECT(L$11&"!"&$B45) -> - | M45: =INDIRECT(M$11&"!"&$B45) -> 0 | ... Q45: =INDIRECT(Q$11&"!"&$B45) -> 0 | R45: =SUM(F45:Q45) -> 0
B46: H258 | D46: 受注件数 | F46: =INDIRECT(F$11&"!"&$B46) -> 2 | G46: =INDIRECT(G$11&"!"&$B46) -> 0 | H46: =INDIRECT(H$11&"!"&$B46) -> 0 | I46: =INDIRECT(I$11&"!"&$B46) -> 0 | J46: =INDIRECT(J$11&"!"&$B46) -> 0 | K46: =INDIRECT(K$11&"!"&$B46) -> - | L46: =INDIRECT(L$11&"!"&$B46) -> 0 | M46: =INDIRECT(M$11&"!"&$B46) -> - | ... Q46: =INDIRECT(Q$11&"!"&$B46) -> - | R46: =SUM(F46:Q46) -> 2
B47: H259 | D47: 受注率 | F47: =INDIRECT(F$11&"!"&$B47) -> 0.4 | G47: =INDIRECT(G$11&"!"&$B47) -> 0 | H47: =INDIRECT(H$11&"!"&$B47) -> 0 | I47: =INDIRECT(I$11&"!"&$B47) -> 0 | J47: =INDIRECT(J$11&"!"&$B47) -> - | K47: =INDIRECT(K$11&"!"&$B47) -> 0 | L47: =INDIRECT(L$11&"!"&$B47) -> - | M47: =INDIRECT(M$11&"!"&$B47) -> 0 | ... Q47: =INDIRECT(Q$11&"!"&$B47) -> 0 | R47: =R46/R45 -> #DIV/0!
B48: H260 | D48: 即受注 件数 | F48: =INDIRECT(F$11&"!"&$B48) -> 1 | G48: =INDIRECT(G$11&"!"&$B48) -> 0 | H48: =INDIRECT(H$11&"!"&$B48) -> 0 | I48: =INDIRECT(I$11&"!"&$B48) -> 2 | J48: =INDIRECT(J$11&"!"&$B48) -> 0 | K48: =INDIRECT(K$11&"!"&$B48) -> - | L48: =INDIRECT(L$11&"!"&$B48) -> 0 | M48: =INDIRECT(M$11&"!"&$B48) -> - | ... Q48: =INDIRECT(Q$11&"!"&$B48) -> - | R48: =SUM(F48:Q48) -> 3
B49: H261 | D49: 即受注率 | F49: =INDIRECT(F$11&"!"&$B49) -> 0.2 | G49: =INDIRECT(G$11&"!"&$B49) -> 0 | H49: =INDIRECT(H$11&"!"&$B49) -> 0 | I49: =INDIRECT(I$11&"!"&$B49) -> 0.33333333 | J49: =INDIRECT(J$11&"!"&$B49) -> - | K49: =INDIRECT(K$11&"!"&$B49) -> 0 | L49: =INDIRECT(L$11&"!"&$B49) -> - | M49: =INDIRECT(M$11&"!"&$B49) -> 0 | ... Q49: =INDIRECT(Q$11&"!"&$B49) -> 0 | R49: =R48/R45 -> #DIV/0!
B50: H262 | D50: 戻り受注 件数 | F50: =INDIRECT(F$11&"!"&$B50) -> 2 | G50: =INDIRECT(G$11&"!"&$B50) -> 0 | H50: =INDIRECT(H$11&"!"&$B50) -> 1 | I50: =INDIRECT(I$11&"!"&$B50) -> 1 | J50: =INDIRECT(J$11&"!"&$B50) -> 0 | K50: =INDIRECT(K$11&"!"&$B50) -> - | L50: =INDIRECT(L$11&"!"&$B50) -> 0 | M50: =INDIRECT(M$11&"!"&$B50) -> - | ... Q50: =INDIRECT(Q$11&"!"&$B50) -> - | R50: =SUM(F50:Q50) -> 4
B51: H263 | D51: 戻り受注率 | F51: =INDIRECT(F$11&"!"&$B51) -> 0.4 | G51: =INDIRECT(G$11&"!"&$B51) -> 0 | H51: =INDIRECT(H$11&"!"&$B51) -> 0.5 | I51: =INDIRECT(I$11&"!"&$B51) -> 0.16666667 | J51: =INDIRECT(J$11&"!"&$B51) -> - | K51: =INDIRECT(K$11&"!"&$B51) -> 0 | L51: =INDIRECT(L$11&"!"&$B51) -> - | M51: =INDIRECT(M$11&"!"&$B51) -> 0 | ... Q51: =INDIRECT(Q$11&"!"&$B51) -> 0 | R51: =R50/R45 -> #DIV/0!
B53: D276 | C53: =設定用!D11 -> 相続放棄 | D53: 面談対応件数 | F53: =INDIRECT(F$11&"!"&$B53) -> 0.36363636 | G53: =INDIRECT(G$11&"!"&$B53) -> 3 | H53: =INDIRECT(H$11&"!"&$B53) -> 0.18181818 | I53: =INDIRECT(I$11&"!"&$B53) -> 0.18181818 | J53: =INDIRECT(J$11&"!"&$B53) -> - | K53: =INDIRECT(K$11&"!"&$B53) -> 0 | L53: =INDIRECT(L$11&"!"&$B53) -> - | M53: =INDIRECT(M$11&"!"&$B53) -> 0 | ... Q53: =INDIRECT(Q$11&"!"&$B53) -> 0 | R53: =SUM(F53:Q53) -> 3.7272727
B54: D277 | D54: 受注件数 | F54: =INDIRECT(F$11&"!"&$B54) -> 0 | G54: =INDIRECT(G$11&"!"&$B54) -> 0.75 | H54: =INDIRECT(H$11&"!"&$B54) -> 0 | I54: =INDIRECT(I$11&"!"&$B54) -> 1 | J54: =INDIRECT(J$11&"!"&$B54) -> 0 | K54: =INDIRECT(K$11&"!"&$B54) -> - | L54: =INDIRECT(L$11&"!"&$B54) -> 0 | M54: =INDIRECT(M$11&"!"&$B54) -> - | ... Q54: =INDIRECT(Q$11&"!"&$B54) -> - | R54: =SUM(F54:Q54) -> 1.75
B55: D278 | D55: 受注率 | F55: =INDIRECT(F$11&"!"&$B55) -> 0 | G55: =INDIRECT(G$11&"!"&$B55) -> 3 | H55: =INDIRECT(H$11&"!"&$B55) -> 0 | I55: =INDIRECT(I$11&"!"&$B55) -> 0.090909091 | J55: =INDIRECT(J$11&"!"&$B55) -> - | K55: =INDIRECT(K$11&"!"&$B55) -> 0 | L55: =INDIRECT(L$11&"!"&$B55) -> - | M55: =INDIRECT(M$11&"!"&$B55) -> 0 | ... Q55: =INDIRECT(Q$11&"!"&$B55) -> 0 | R55: =R54/R53 -> 0.4695122
B56: D279 | D56: 即受注 件数 | F56: =INDIRECT(F$11&"!"&$B56) -> 0 | G56: =INDIRECT(G$11&"!"&$B56) -> 0.42857143 | H56: =INDIRECT(H$11&"!"&$B56) -> 0 | I56: =INDIRECT(I$11&"!"&$B56) -> 0 | J56: =INDIRECT(J$11&"!"&$B56) -> 0 | K56: =INDIRECT(K$11&"!"&$B56) -> - | L56: =INDIRECT(L$11&"!"&$B56) -> 0 | M56: =INDIRECT(M$11&"!"&$B56) -> - | ... Q56: =INDIRECT(Q$11&"!"&$B56) -> - | R56: =SUM(F56:Q56) -> 0.42857143
B57: D280 | D57: 即受注率 | F57: =INDIRECT(F$11&"!"&$B57) -> 0 | G57: =INDIRECT(G$11&"!"&$B57) -> 0 | H57: =INDIRECT(H$11&"!"&$B57) -> 0 | I57: =INDIRECT(I$11&"!"&$B57) -> 0 | J57: =INDIRECT(J$11&"!"&$B57) -> - | K57: =INDIRECT(K$11&"!"&$B57) -> 0 | L57: =INDIRECT(L$11&"!"&$B57) -> - | M57: =INDIRECT(M$11&"!"&$B57) -> 0 | ... Q57: =INDIRECT(Q$11&"!"&$B57) -> 0 | R57: =R56/R53 -> 0.11498258
B58: D281 | D58: 戻り受注 件数 | F58: =INDIRECT(F$11&"!"&$B58) -> 0 | G58: =INDIRECT(G$11&"!"&$B58) -> 0 | H58: =INDIRECT(H$11&"!"&$B58) -> 1 | I58: =INDIRECT(I$11&"!"&$B58) -> 1 | J58: =INDIRECT(J$11&"!"&$B58) -> 0 | K58: =INDIRECT(K$11&"!"&$B58) -> - | L58: =INDIRECT(L$11&"!"&$B58) -> 0 | M58: =INDIRECT(M$11&"!"&$B58) -> - | ... Q58: =INDIRECT(Q$11&"!"&$B58) -> - | R58: =SUM(F58:Q58) -> 2
B59: D282 | D59: 戻り受注率 | F59: =INDIRECT(F$11&"!"&$B59) -> 0 | G59: =INDIRECT(G$11&"!"&$B59) -> 0 | H59: =INDIRECT(H$11&"!"&$B59) -> 0.090909091 | I59: =INDIRECT(I$11&"!"&$B59) -> 0.090909091 | J59: =INDIRECT(J$11&"!"&$B59) -> - | K59: =INDIRECT(K$11&"!"&$B59) -> 0 | L59: =INDIRECT(L$11&"!"&$B59) -> - | M59: =INDIRECT(M$11&"!"&$B59) -> 0 | ... Q59: =INDIRECT(Q$11&"!"&$B59) -> 0 | R59: =R58/R53 -> 0.53658537
B61: E276 | C61: =設定用!D12 -> 複雑な相続 | D61: 面談対応件数 | F61: =INDIRECT(F$11&"!"&$B61) -> 0 | G61: =INDIRECT(G$11&"!"&$B61) -> 0 | H61: =INDIRECT(H$11&"!"&$B61) -> 1 | I61: =INDIRECT(I$11&"!"&$B61) -> 0 | J61: =INDIRECT(J$11&"!"&$B61) -> - | K61: =INDIRECT(K$11&"!"&$B61) -> 0 | L61: =INDIRECT(L$11&"!"&$B61) -> - | M61: =INDIRECT(M$11&"!"&$B61) -> 0 | ... Q61: =INDIRECT(Q$11&"!"&$B61) -> 0 | R61: =SUM(F61:Q61) -> 1
B62: E277 | D62: 受注件数 | F62: =INDIRECT(F$11&"!"&$B62) -> 0 | G62: =INDIRECT(G$11&"!"&$B62) -> - | H62: =INDIRECT(H$11&"!"&$B62) -> 0 | I62: =INDIRECT(I$11&"!"&$B62) -> 0 | J62: =INDIRECT(J$11&"!"&$B62) -> 0 | K62: =INDIRECT(K$11&"!"&$B62) -> - | L62: =INDIRECT(L$11&"!"&$B62) -> 0 | M62: =INDIRECT(M$11&"!"&$B62) -> - | ... Q62: =INDIRECT(Q$11&"!"&$B62) -> - | R62: =SUM(F62:Q62) -> 0
B63: E278 | D63: 受注率 | F63: =INDIRECT(F$11&"!"&$B63) -> 0 | G63: =INDIRECT(G$11&"!"&$B63) -> 0 | H63: =INDIRECT(H$11&"!"&$B63) -> 0 | I63: =INDIRECT(I$11&"!"&$B63) -> 0 | J63: =INDIRECT(J$11&"!"&$B63) -> - | K63: =INDIRECT(K$11&"!"&$B63) -> 0 | L63: =INDIRECT(L$11&"!"&$B63) -> - | M63: =INDIRECT(M$11&"!"&$B63) -> 0 | ... Q63: =INDIRECT(Q$11&"!"&$B63) -> 0 | R63: =R62/R61 -> 0
B64: E279 | D64: 即受注 件数 | F64: =INDIRECT(F$11&"!"&$B64) -> 0 | G64: =INDIRECT(G$11&"!"&$B64) -> 0 | H64: =INDIRECT(H$11&"!"&$B64) -> 0 | I64: =INDIRECT(I$11&"!"&$B64) -> 1 | J64: =INDIRECT(J$11&"!"&$B64) -> 0 | K64: =INDIRECT(K$11&"!"&$B64) -> - | L64: =INDIRECT(L$11&"!"&$B64) -> 0 | M64: =INDIRECT(M$11&"!"&$B64) -> - | ... Q64: =INDIRECT(Q$11&"!"&$B64) -> - | R64: =SUM(F64:Q64) -> 1
B65: E280 | D65: 即受注率 | F65: =INDIRECT(F$11&"!"&$B65) -> 0 | G65: =INDIRECT(G$11&"!"&$B65) -> 0 | H65: =INDIRECT(H$11&"!"&$B65) -> 0 | I65: =INDIRECT(I$11&"!"&$B65) -> 1 | J65: =INDIRECT(J$11&"!"&$B65) -> - | K65: =INDIRECT(K$11&"!"&$B65) -> 0 | L65: =INDIRECT(L$11&"!"&$B65) -> - | M65: =INDIRECT(M$11&"!"&$B65) -> 0 | ... Q65: =INDIRECT(Q$11&"!"&$B65) -> 0 | R65: =R64/R61 -> 1
B66: E281 | D66: 戻り受注 件数 | F66: =INDIRECT(F$11&"!"&$B66) -> 0 | G66: =INDIRECT(G$11&"!"&$B66) -> 0 | H66: =INDIRECT(H$11&"!"&$B66) -> 1 | I66: =INDIRECT(I$11&"!"&$B66) -> 0 | J66: =INDIRECT(J$11&"!"&$B66) -> 0 | K66: =INDIRECT(K$11&"!"&$B66) -> - | L66: =INDIRECT(L$11&"!"&$B66) -> 0 | M66: =INDIRECT(M$11&"!"&$B66) -> - | ... Q66: =INDIRECT(Q$11&"!"&$B66) -> - | R66: =SUM(F66:Q66) -> 1
B67: E282 | D67: 戻り受注率 | F67: =INDIRECT(F$11&"!"&$B67) -> 0 | G67: =INDIRECT(G$11&"!"&$B67) -> 0 | H67: =INDIRECT(H$11&"!"&$B67) -> 1 | I67: =INDIRECT(I$11&"!"&$B67) -> 0 | J67: =INDIRECT(J$11&"!"&$B67) -> - | K67: =INDIRECT(K$11&"!"&$B67) -> 0 | L67: =INDIRECT(L$11&"!"&$B67) -> - | M67: =INDIRECT(M$11&"!"&$B67) -> 0 | ... Q67: =INDIRECT(Q$11&"!"&$B67) -> 0 | R67: =R66/R61 -> 1
B69: F276 | C69: =設定用!D13 -> 非常に複雑な相続 | D69: 面談対応件数 | F69: =INDIRECT(F$11&"!"&$B69) -> 0 | G69: =INDIRECT(G$11&"!"&$B69) -> 0 | H69: =INDIRECT(H$11&"!"&$B69) -> 0 | I69: =INDIRECT(I$11&"!"&$B69) -> 0 | J69: =INDIRECT(J$11&"!"&$B69) -> - | K69: =INDIRECT(K$11&"!"&$B69) -> 0 | L69: =INDIRECT(L$11&"!"&$B69) -> - | M69: =INDIRECT(M$11&"!"&$B69) -> 0 | ... Q69: =INDIRECT(Q$11&"!"&$B69) -> 0 | R69: =SUM(F69:Q69) -> 0
B70: F277 | D70: 受注件数 | F70: =INDIRECT(F$11&"!"&$B70) -> 0 | G70: =INDIRECT(G$11&"!"&$B70) -> - | H70: =INDIRECT(H$11&"!"&$B70) -> 0 | I70: =INDIRECT(I$11&"!"&$B70) -> 0 | J70: =INDIRECT(J$11&"!"&$B70) -> 0 | K70: =INDIRECT(K$11&"!"&$B70) -> - | L70: =INDIRECT(L$11&"!"&$B70) -> 0 | M70: =INDIRECT(M$11&"!"&$B70) -> - | ... Q70: =INDIRECT(Q$11&"!"&$B70) -> - | R70: =SUM(F70:Q70) -> 0
B71: F278 | D71: 受注率 | F71: =INDIRECT(F$11&"!"&$B71) -> 0 | G71: =INDIRECT(G$11&"!"&$B71) -> 0 | H71: =INDIRECT(H$11&"!"&$B71) -> 0 | I71: =INDIRECT(I$11&"!"&$B71) -> 0 | J71: =INDIRECT(J$11&"!"&$B71) -> - | K71: =INDIRECT(K$11&"!"&$B71) -> 0 | L71: =INDIRECT(L$11&"!"&$B71) -> - | M71: =INDIRECT(M$11&"!"&$B71) -> 0 | ... Q71: =INDIRECT(Q$11&"!"&$B71) -> 0 | R71: =R70/R69 -> #DIV/0!
B72: F279 | D72: 即受注 件数 | F72: =INDIRECT(F$11&"!"&$B72) -> 0 | G72: =INDIRECT(G$11&"!"&$B72) -> - | H72: =INDIRECT(H$11&"!"&$B72) -> 0 | I72: =INDIRECT(I$11&"!"&$B72) -> 0 | J72: =INDIRECT(J$11&"!"&$B72) -> 0 | K72: =INDIRECT(K$11&"!"&$B72) -> - | L72: =INDIRECT(L$11&"!"&$B72) -> 0 | M72: =INDIRECT(M$11&"!"&$B72) -> - | ... Q72: =INDIRECT(Q$11&"!"&$B72) -> - | R72: =SUM(F72:Q72) -> 0
B73: F280 | D73: 即受注率 | F73: =INDIRECT(F$11&"!"&$B73) -> 0 | G73: =INDIRECT(G$11&"!"&$B73) -> 0 | H73: =INDIRECT(H$11&"!"&$B73) -> 0 | I73: =INDIRECT(I$11&"!"&$B73) -> 0 | J73: =INDIRECT(J$11&"!"&$B73) -> - | K73: =INDIRECT(K$11&"!"&$B73) -> 0 | L73: =INDIRECT(L$11&"!"&$B73) -> - | M73: =INDIRECT(M$11&"!"&$B73) -> 0 | ... Q73: =INDIRECT(Q$11&"!"&$B73) -> 0 | R73: =R72/R69 -> #DIV/0!
B74: F281 | D74: 戻り受注 件数 | F74: =INDIRECT(F$11&"!"&$B74) -> 0 | G74: =INDIRECT(G$11&"!"&$B74) -> - | H74: =INDIRECT(H$11&"!"&$B74) -> 0 | I74: =INDIRECT(I$11&"!"&$B74) -> 0 | J74: =INDIRECT(J$11&"!"&$B74) -> 0 | K74: =INDIRECT(K$11&"!"&$B74) -> - | L74: =INDIRECT(L$11&"!"&$B74) -> 0 | M74: =INDIRECT(M$11&"!"&$B74) -> - | ... Q74: =INDIRECT(Q$11&"!"&$B74) -> - | R74: =SUM(F74:Q74) -> 0
B75: F282 | D75: 戻り受注率 | F75: =INDIRECT(F$11&"!"&$B75) -> 0 | G75: =INDIRECT(G$11&"!"&$B75) -> 0 | H75: =INDIRECT(H$11&"!"&$B75) -> 0 | I75: =INDIRECT(I$11&"!"&$B75) -> 0 | J75: =INDIRECT(J$11&"!"&$B75) -> - | K75: =INDIRECT(K$11&"!"&$B75) -> 0 | L75: =INDIRECT(L$11&"!"&$B75) -> - | M75: =INDIRECT(M$11&"!"&$B75) -> 0 | ... Q75: =INDIRECT(Q$11&"!"&$B75) -> 0 | R75: =R74/R69 -> #DIV/0!
B77: G276 | C77: =設定用!D14 -> 民事信託 | D77: 面談対応件数 | F77: =INDIRECT(F$11&"!"&$B77) -> 0 | G77: =INDIRECT(G$11&"!"&$B77) -> 0 | H77: =INDIRECT(H$11&"!"&$B77) -> 0 | I77: =INDIRECT(I$11&"!"&$B77) -> 0 | J77: =INDIRECT(J$11&"!"&$B77) -> - | K77: =INDIRECT(K$11&"!"&$B77) -> 0 | L77: =INDIRECT(L$11&"!"&$B77) -> - | M77: =INDIRECT(M$11&"!"&$B77) -> 0 | ... Q77: =INDIRECT(Q$11&"!"&$B77) -> 0 | R77: =SUM(F77:Q77) -> 0
B78: G277 | D78: 受注件数 | F78: =INDIRECT(F$11&"!"&$B78) -> 0 | G78: =INDIRECT(G$11&"!"&$B78) -> - | H78: =INDIRECT(H$11&"!"&$B78) -> 0 | I78: =INDIRECT(I$11&"!"&$B78) -> 0 | J78: =INDIRECT(J$11&"!"&$B78) -> 0 | K78: =INDIRECT(K$11&"!"&$B78) -> - | L78: =INDIRECT(L$11&"!"&$B78) -> 0 | M78: =INDIRECT(M$11&"!"&$B78) -> - | ... Q78: =INDIRECT(Q$11&"!"&$B78) -> - | R78: =SUM(F78:Q78) -> 0
B79: G278 | D79: 受注率 | F79: =INDIRECT(F$11&"!"&$B79) -> 0 | G79: =INDIRECT(G$11&"!"&$B79) -> 0 | H79: =INDIRECT(H$11&"!"&$B79) -> 0 | I79: =INDIRECT(I$11&"!"&$B79) -> 0 | J79: =INDIRECT(J$11&"!"&$B79) -> - | K79: =INDIRECT(K$11&"!"&$B79) -> 0 | L79: =INDIRECT(L$11&"!"&$B79) -> - | M79: =INDIRECT(M$11&"!"&$B79) -> 0 | ... Q79: =INDIRECT(Q$11&"!"&$B79) -> 0 | R79: =R78/R77 -> #DIV/0!
B80: G279 | D80: 即受注 件数 | F80: =INDIRECT(F$11&"!"&$B80) -> 0 | G80: =INDIRECT(G$11&"!"&$B80) -> 0 | H80: =INDIRECT(H$11&"!"&$B80) -> 0 | I80: =INDIRECT(I$11&"!"&$B80) -> 0 | J80: =INDIRECT(J$11&"!"&$B80) -> 0 | K80: =INDIRECT(K$11&"!"&$B80) -> - | L80: =INDIRECT(L$11&"!"&$B80) -> 0 | M80: =INDIRECT(M$11&"!"&$B80) -> - | ... Q80: =INDIRECT(Q$11&"!"&$B80) -> - | R80: =SUM(F80:Q80) -> 0
B81: G280 | D81: 即受注率 | F81: =INDIRECT(F$11&"!"&$B81) -> 0 | G81: =INDIRECT(G$11&"!"&$B81) -> 0 | H81: =INDIRECT(H$11&"!"&$B81) -> 0 | I81: =INDIRECT(I$11&"!"&$B81) -> 0 | J81: =INDIRECT(J$11&"!"&$B81) -> - | K81: =INDIRECT(K$11&"!"&$B81) -> 0 | L81: =INDIRECT(L$11&"!"&$B81) -> - | M81: =INDIRECT(M$11&"!"&$B81) -> 0 | ... Q81: =INDIRECT(Q$11&"!"&$B81) -> 0 | R81: =R80/R77 -> #DIV/0!
B82: G281 | D82: 戻り受注 件数 | F82: =INDIRECT(F$11&"!"&$B82) -> 0 | G82: =INDIRECT(G$11&"!"&$B82) -> 0 | H82: =INDIRECT(H$11&"!"&$B82) -> 1 | I82: =INDIRECT(I$11&"!"&$B82) -> 0 | J82: =INDIRECT(J$11&"!"&$B82) -> 0 | K82: =INDIRECT(K$11&"!"&$B82) -> - | L82: =INDIRECT(L$11&"!"&$B82) -> 0 | M82: =INDIRECT(M$11&"!"&$B82) -> - | ... Q82: =INDIRECT(Q$11&"!"&$B82) -> - | R82: =SUM(F82:Q82) -> 1
B83: G282 | D83: 戻り受注率 | F83: =INDIRECT(F$11&"!"&$B83) -> 0 | G83: =INDIRECT(G$11&"!"&$B83) -> 0 | H83: =INDIRECT(H$11&"!"&$B83) -> 0.0625 | I83: =INDIRECT(I$11&"!"&$B83) -> 0 | J83: =INDIRECT(J$11&"!"&$B83) -> - | K83: =INDIRECT(K$11&"!"&$B83) -> 0 | L83: =INDIRECT(L$11&"!"&$B83) -> - | M83: =INDIRECT(M$11&"!"&$B83) -> 0 | ... Q83: =INDIRECT(Q$11&"!"&$B83) -> 0 | R83: =R82/R77 -> #DIV/0!
B85: H276 | C85: =設定用!D15 -> その他 | D85: 面談対応件数 | F85: =INDIRECT(F$11&"!"&$B85) -> 0.2 | G85: =INDIRECT(G$11&"!"&$B85) -> 0 | H85: =INDIRECT(H$11&"!"&$B85) -> 0 | I85: =INDIRECT(I$11&"!"&$B85) -> 0.16666667 | J85: =INDIRECT(J$11&"!"&$B85) -> - | K85: =INDIRECT(K$11&"!"&$B85) -> 0 | L85: =INDIRECT(L$11&"!"&$B85) -> - | M85: =INDIRECT(M$11&"!"&$B85) -> 0 | ... Q85: =INDIRECT(Q$11&"!"&$B85) -> 0 | R85: =SUM(F85:Q85) -> 0.36666667
B86: H277 | D86: 受注件数 | F86: =INDIRECT(F$11&"!"&$B86) -> 0 | G86: =INDIRECT(G$11&"!"&$B86) -> 0 | H86: =INDIRECT(H$11&"!"&$B86) -> 0 | I86: =INDIRECT(I$11&"!"&$B86) -> 0 | J86: =INDIRECT(J$11&"!"&$B86) -> 0 | K86: =INDIRECT(K$11&"!"&$B86) -> - | L86: =INDIRECT(L$11&"!"&$B86) -> 0 | M86: =INDIRECT(M$11&"!"&$B86) -> - | ... Q86: =INDIRECT(Q$11&"!"&$B86) -> - | R86: =SUM(F86:Q86) -> 0
B87: H278 | D87: 受注率 | F87: =INDIRECT(F$11&"!"&$B87) -> 0 | G87: =INDIRECT(G$11&"!"&$B87) -> 0 | H87: =INDIRECT(H$11&"!"&$B87) -> 0 | I87: =INDIRECT(I$11&"!"&$B87) -> 0 | J87: =INDIRECT(J$11&"!"&$B87) -> - | K87: =INDIRECT(K$11&"!"&$B87) -> 0 | L87: =INDIRECT(L$11&"!"&$B87) -> - | M87: =INDIRECT(M$11&"!"&$B87) -> 0 | ... Q87: =INDIRECT(Q$11&"!"&$B87) -> 0 | R87: =R86/R85 -> 0
B88: H279 | D88: 即受注 件数 | F88: =INDIRECT(F$11&"!"&$B88) -> 0 | G88: =INDIRECT(G$11&"!"&$B88) -> 0 | H88: =INDIRECT(H$11&"!"&$B88) -> 0 | I88: =INDIRECT(I$11&"!"&$B88) -> 0 | J88: =INDIRECT(J$11&"!"&$B88) -> 0 | K88: =INDIRECT(K$11&"!"&$B88) -> - | L88: =INDIRECT(L$11&"!"&$B88) -> 0 | M88: =INDIRECT(M$11&"!"&$B88) -> - | ... Q88: =INDIRECT(Q$11&"!"&$B88) -> - | R88: =SUM(F88:Q88) -> 0
B89: H280 | D89: 即受注率 | F89: =INDIRECT(F$11&"!"&$B89) -> 0 | G89: =INDIRECT(G$11&"!"&$B89) -> 0 | H89: =INDIRECT(H$11&"!"&$B89) -> 0 | I89: =INDIRECT(I$11&"!"&$B89) -> 0 | J89: =INDIRECT(J$11&"!"&$B89) -> - | K89: =INDIRECT(K$11&"!"&$B89) -> 0 | L89: =INDIRECT(L$11&"!"&$B89) -> - | M89: =INDIRECT(M$11&"!"&$B89) -> 0 | ... Q89: =INDIRECT(Q$11&"!"&$B89) -> 0 | R89: =R88/R85 -> 0
B90: H281 | D90: 戻り受注 件数 | F90: =INDIRECT(F$11&"!"&$B90) -> 1 | G90: =INDIRECT(G$11&"!"&$B90) -> 0 | H90: =INDIRECT(H$11&"!"&$B90) -> 1 | I90: =INDIRECT(I$11&"!"&$B90) -> 1 | J90: =INDIRECT(J$11&"!"&$B90) -> 0 | K90: =INDIRECT(K$11&"!"&$B90) -> - | L90: =INDIRECT(L$11&"!"&$B90) -> 0 | M90: =INDIRECT(M$11&"!"&$B90) -> - | ... Q90: =INDIRECT(Q$11&"!"&$B90) -> - | R90: =SUM(F90:Q90) -> 3
B91: H282 | D91: 戻り受注率 | F91: =INDIRECT(F$11&"!"&$B91) -> 0.2 | G91: =INDIRECT(G$11&"!"&$B91) -> 0 | H91: =INDIRECT(H$11&"!"&$B91) -> 0.5 | I91: =INDIRECT(I$11&"!"&$B91) -> 0.16666667 | J91: =INDIRECT(J$11&"!"&$B91) -> - | K91: =INDIRECT(K$11&"!"&$B91) -> 0 | L91: =INDIRECT(L$11&"!"&$B91) -> - | M91: =INDIRECT(M$11&"!"&$B91) -> 0 | ... Q91: =INDIRECT(Q$11&"!"&$B91) -> 0 | R91: =R90/R85 -> 8.1818182

Sheet 日別受電集計
B1: 1日 | C1: 2日 | D1: 3日 | E1: 4日 | F1: 5日 | G1: 6日 | H1: 7日 | I1: 8日 | J1: 9日 | K1: 10日 | L1: 11日 | M1: 12日 | N1: 13日 | O1: 14日 | P1: 15日 | Q1: 16日 | R1: 17日 | S1: 18日 | T1: 19日 | U1: 20日 | V1: 21日 | W1: 22日 | X1: 23日 | Y1: 24日 | Z1: 25日 | AA1: 26日 | AB1: 27日 | AC1: 28日 | AD1: 29日 | AE1: 30日 | AF1: 31日 | AG1: Ave.
A2: 1月 | B2: 45292 | C2: 45293 | D2: 45294 | E2: 45295 | F2: 45296 | G2: 45297 | H2: 45298 | I2: 45299 | J2: 45300 | K2: 45301 | L2: 45302 | M2: 45303 | N2: 45304 | O2: 45305 | P2: 45306 | Q2: 45307 | R2: 45308 | S2: 45309 | T2: 45310 | U2: 45311 | V2: 45312 | W2: 45313 | X2: 45314 | Y2: 45315 | Z2: 45316 | AA2: 45317 | AB2: 45318 | AC2: 45319 | AD2: 45320 | AE2: 45321 | AF2: 45322 | AG2: Ave.
B3: =CHOOSE(WEEKDAY(B2), "日", "月", "火", "水", "木", "金", "土") -> 月 | C3: =CHOOSE(WEEKDAY(C2), "日", "月", "火", "水", "木", "金", "土") -> 火 | D3: =CHOOSE(WEEKDAY(D2), "日", "月", "火", "水", "木", "金", "土") -> 水 | E3: =CHOOSE(WEEKDAY(E2), "日", "月", "火", "水", "木", "金", "土") -> 木 | F3: =CHOOSE(WEEKDAY(F2), "日", "月", "火", "水", "木", "金", "土") -> 金 | G3: =CHOOSE(WEEKDAY(G2), "日", "月", "火", "水", "木", "金", "土") -> 土 | H3: =CHOOSE(WEEKDAY(H2), "日", "月", "火", "水", "木", "金", "土") -> 日 | I3: =CHOOSE(WEEKDAY(I2), "日", "月", "火", "水", "木", "金", "土") -> 月 | ... AF3: =CHOOSE(WEEKDAY(AF2), "日", "月", "火", "水", "木", "金", "土") -> 水
A4: =SUM(B4:AF4) -> 0 | B4: =IF(TODAY()<=B2,"", COUNTIF('1月'!$C3:$C1013,B2)) -> 0 | C4: =IF(TODAY()<=C2,"", COUNTIF('1月'!$C3:$C1013,C2)) -> 0 | D4: =IF(TODAY()<=D2,"", COUNTIF('1月'!$C3:$C1013,D2)) -> 0 | E4: =IF(TODAY()<=E2,"", COUNTIF('1月'!$C3:$C1013,E2)) -> 0 | F4: =IF(TODAY()<=F2,"", COUNTIF('1月'!$C3:$C1013,F2)) -> 0 | G4: =IF(TODAY()<=G2,"", COUNTIF('1月'!$C3:$C1013,G2)) -> 0 | H4: =IF(TODAY()<=H2,"", COUNTIF('1月'!$C3:$C1013,H2)) -> 0 | I4: =IF(TODAY()<=I2,"", COUNTIF('1月'!$C3:$C1013,I2)) -> 0 | ... AF4: =IF(TODAY()<=AF2,"", COUNTIF('1月'!$C3:$C1013,AF2)) -> 0 | AG4: =IFERROR(AVERAGE(B4:AF4),0) -> 0
A6: 2月 | B6: 45323 | C6: 45324 | D6: 45325 | E6: 45326 | F6: 45327 | G6: 45328 | H6: 45329 | I6: 45330 | J6: 45331 | K6: 45332 | L6: 45333 | M6: 45334 | N6: 45335 | O6: 45336 | P6: 45337 | Q6: 45338 | R6: 45339 | S6: 45340 | T6: 45341 | U6: 45342 | V6: 45343 | W6: 45344 | X6: 45345 | Y6: 45346 | Z6: 45347 | AA6: 45348 | AB6: 45349 | AC6: 45350 | AD6: 45351 | AG6: Ave.
B7: =CHOOSE(WEEKDAY(B6), "日", "月", "火", "水", "木", "金", "土") -> 木 | C7: =CHOOSE(WEEKDAY(C6), "日", "月", "火", "水", "木", "金", "土") -> 金 | D7: =CHOOSE(WEEKDAY(D6), "日", "月", "火", "水", "木", "金", "土") -> 土 | E7: =CHOOSE(WEEKDAY(E6), "日", "月", "火", "水", "木", "金", "土") -> 日 | F7: =CHOOSE(WEEKDAY(F6), "日", "月", "火", "水", "木", "金", "土") -> 月 | G7: =CHOOSE(WEEKDAY(G6), "日", "月", "火", "水", "木", "金", "土") -> 火 | H7: =CHOOSE(WEEKDAY(H6), "日", "月", "火", "水", "木", "金", "土") -> 水 | I7: =CHOOSE(WEEKDAY(I6), "日", "月", "火", "水", "木", "金", "土") -> 木 | ... AF7: =CHOOSE(WEEKDAY(AF6), "日", "月", "火", "水", "木", "金", "土") -> 土
A8: =SUM(B8:AF8) -> 0 | B8: =IF(TODAY()<=B6,"", COUNTIF('2月'!$C3:$C1013,B6)) -> 0 | C8: =IF(TODAY()<=C6,"", COUNTIF('2月'!$C3:$C1013,C6)) -> 0 | D8: =IF(TODAY()<=D6,"", COUNTIF('2月'!$C3:$C1013,D6)) -> 0 | E8: =IF(TODAY()<=E6,"", COUNTIF('2月'!$C3:$C1013,E6)) -> 0 | F8: =IF(TODAY()<=F6,"", COUNTIF('2月'!$C3:$C1013,F6)) -> 0 | G8: =IF(TODAY()<=G6,"", COUNTIF('2月'!$C3:$C1013,G6)) -> 0 | H8: =IF(TODAY()<=H6,"", COUNTIF('2月'!$C3:$C1013,H6)) -> 0 | I8: =IF(TODAY()<=I6,"", COUNTIF('2月'!$C3:$C1013,I6)) -> 0 | ... AD8: =IF(TODAY()<=AD6,"", COUNTIF('2月'!$C3:$C1013,AD6)) -> 0 | AG8: =IFERROR(AVERAGE(B8:AF8),0) -> 0
A10: 3月 | B10: 45352 | C10: 45353 | D10: 45354 | E10: 45355 | F10: 45356 | G10: 45357 | H10: 45358 | I10: 45359 | J10: 45360 | K10: 45361 | L10: 45362 | M10: 45363 | N10: 45364 | O10: 45365 | P10: 45366 | Q10: 45367 | R10: 45368 | S10: 45369 | T10: 45370 | U10: 45371 | V10: 45372 | W10: 45373 | X10: 45374 | Y10: 45375 | Z10: 45376 | AA10: 45377 | AB10: 45378 | AC10: 45379 | AD10: 45380 | AE10: 45381 | AF10: 45382 | AG10: Ave.
B11: =CHOOSE(WEEKDAY(B10), "日", "月", "火", "水", "木", "金", "土") -> 金 | C11: =CHOOSE(WEEKDAY(C10), "日", "月", "火", "水", "木", "金", "土") -> 土 | D11: =CHOOSE(WEEKDAY(D10), "日", "月", "火", "水", "木", "金", "土") -> 日 | E11: =CHOOSE(WEEKDAY(E10), "日", "月", "火", "水", "木", "金", "土") -> 月 | F11: =CHOOSE(WEEKDAY(F10), "日", "月", "火", "水", "木", "金", "土") -> 火 | G11: =CHOOSE(WEEKDAY(G10), "日", "月", "火", "水", "木", "金", "土") -> 水 | H11: =CHOOSE(WEEKDAY(H10), "日", "月", "火", "水", "木", "金", "土") -> 木 | I11: =CHOOSE(WEEKDAY(I10), "日", "月", "火", "水", "木", "金", "土") -> 金 | ... AF11: =CHOOSE(WEEKDAY(AF10), "日", "月", "火", "水", "木", "金", "土") -> 日
A12: =SUM(B12:AF12) -> 0 | B12: =IF(TODAY()<=B10,"", COUNTIF('3月'!$C3:$C1013,B10)) -> 0 | C12: =IF(TODAY()<=C10,"", COUNTIF('3月'!$C3:$C1013,C10)) -> 0 | D12: =IF(TODAY()<=D10,"", COUNTIF('3月'!$C3:$C1013,D10)) -> 0 | E12: =IF(TODAY()<=E10,"", COUNTIF('3月'!$C3:$C1013,E10)) -> 0 | F12: =IF(TODAY()<=F10,"", COUNTIF('3月'!$C3:$C1013,F10)) -> 0 | G12: =IF(TODAY()<=G10,"", COUNTIF('3月'!$C3:$C1013,G10)) -> 0 | H12: =IF(TODAY()<=H10,"", COUNTIF('3月'!$C3:$C1013,H10)) -> 0 | I12: =IF(TODAY()<=I10,"", COUNTIF('3月'!$C3:$C1013,I10)) -> 0 | ... AF12: =IF(TODAY()<=AF10,"", COUNTIF('3月'!$C3:$C1013,AF10)) -> 0 | AG12: =IFERROR(AVERAGE(B12:AF12),0) -> 0
A14: 4月 | B14: 45383 | C14: 45384 | D14: 45385 | E14: 45386 | F14: 45387 | G14: 45388 | H14: 45389 | I14: 45390 | J14: 45391 | K14: 45392 | L14: 45393 | M14: 45394 | N14: 45395 | O14: 45396 | P14: 45397 | Q14: 45398 | R14: 45399 | S14: 45400 | T14: 45401 | U14: 45402 | V14: 45403 | W14: 45404 | X14: 45405 | Y14: 45406 | Z14: 45407 | AA14: 45408 | AB14: 45409 | AC14: 45410 | AD14: 45411 | AE14: 45412 | AG14: Ave.
B15: =CHOOSE(WEEKDAY(B14), "日", "月", "火", "水", "木", "金", "土") -> 月 | C15: =CHOOSE(WEEKDAY(C14), "日", "月", "火", "水", "木", "金", "土") -> 火 | D15: =CHOOSE(WEEKDAY(D14), "日", "月", "火", "水", "木", "金", "土") -> 水 | E15: =CHOOSE(WEEKDAY(E14), "日", "月", "火", "水", "木", "金", "土") -> 木 | F15: =CHOOSE(WEEKDAY(F14), "日", "月", "火", "水", "木", "金", "土") -> 金 | G15: =CHOOSE(WEEKDAY(G14), "日", "月", "火", "水", "木", "金", "土") -> 土 | H15: =CHOOSE(WEEKDAY(H14), "日", "月", "火", "水", "木", "金", "土") -> 日 | I15: =CHOOSE(WEEKDAY(I14), "日", "月", "火", "水", "木", "金", "土") -> 月 | ... AF15: =CHOOSE(WEEKDAY(AF14), "日", "月", "火", "水", "木", "金", "土") -> 土
A16: =SUM(B16:AF16) -> 0 | B16: =IF(TODAY()<=B14,"", COUNTIF('4月'!$C3:$C1013,B14)) -> 0 | C16: =IF(TODAY()<=C14,"", COUNTIF('4月'!$C3:$C1013,C14)) -> 0 | D16: =IF(TODAY()<=D14,"", COUNTIF('4月'!$C3:$C1013,D14)) -> 0 | E16: =IF(TODAY()<=E14,"", COUNTIF('4月'!$C3:$C1013,E14)) -> 0 | F16: =IF(TODAY()<=F14,"", COUNTIF('4月'!$C3:$C1013,F14)) -> 0 | G16: =IF(TODAY()<=G14,"", COUNTIF('4月'!$C3:$C1013,G14)) -> 0 | H16: =IF(TODAY()<=H14,"", COUNTIF('4月'!$C3:$C1013,H14)) -> 0 | I16: =IF(TODAY()<=I14,"", COUNTIF('4月'!$C3:$C1013,I14)) -> 0 | ... AE16: =IF(TODAY()<=AE14,"", COUNTIF('4月'!$C3:$C1013,AE14)) -> 0 | AG16: =IFERROR(AVERAGE(B16:AF16),0) -> 0
A18: 5月 | B18: 45413 | C18: 45414 | D18: 45415 | E18: 45416 | F18: 45417 | G18: 45418 | H18: 45419 | I18: 45420 | J18: 45421 | K18: 45422 | L18: 45423 | M18: 45424 | N18: 45425 | O18: 45426 | P18: 45427 | Q18: 45428 | R18: 45429 | S18: 45430 | T18: 45431 | U18: 45432 | V18: 45433 | W18: 45434 | X18: 45435 | Y18: 45436 | Z18: 45437 | AA18: 45438 | AB18: 45439 | AC18: 45440 | AD18: 45441 | AE18: 45442 | AF18: 45443 | AG18: Ave.
B19: =CHOOSE(WEEKDAY(B18), "日", "月", "火", "水", "木", "金", "土") -> 水 | C19: =CHOOSE(WEEKDAY(C18), "日", "月", "火", "水", "木", "金", "土") -> 木 | D19: =CHOOSE(WEEKDAY(D18), "日", "月", "火", "水", "木", "金", "土") -> 金 | E19: =CHOOSE(WEEKDAY(E18), "日", "月", "火", "水", "木", "金", "土") -> 土 | F19: =CHOOSE(WEEKDAY(F18), "日", "月", "火", "水", "木", "金", "土") -> 日 | G19: =CHOOSE(WEEKDAY(G18), "日", "月", "火", "水", "木", "金", "土") -> 月 | H19: =CHOOSE(WEEKDAY(H18), "日", "月", "火", "水", "木", "金", "土") -> 火 | I19: =CHOOSE(WEEKDAY(I18), "日", "月", "火", "水", "木", "金", "土") -> 水 | ... AF19: =CHOOSE(WEEKDAY(AF18), "日", "月", "火", "水", "木", "金", "土") -> 金
A20: =SUM(B20:AF20) -> 0 | B20: =IF(TODAY()<=B18,"", COUNTIF('5月'!$C3:$C1013,B18)) -> 0 | C20: =IF(TODAY()<=C18,"", COUNTIF('5月'!$C3:$C1013,C18)) -> 0 | D20: =IF(TODAY()<=D18,"", COUNTIF('5月'!$C3:$C1013,D18)) -> 0 | E20: =IF(TODAY()<=E18,"", COUNTIF('5月'!$C3:$C1013,E18)) -> 0 | F20: =IF(TODAY()<=F18,"", COUNTIF('5月'!$C3:$C1013,F18)) -> 0 | G20: =IF(TODAY()<=G18,"", COUNTIF('5月'!$C3:$C1013,G18)) -> 0 | H20: =IF(TODAY()<=H18,"", COUNTIF('5月'!$C3:$C1013,H18)) -> 0 | I20: =IF(TODAY()<=I18,"", COUNTIF('5月'!$C3:$C1013,I18)) -> 0 | ... AF20: =IF(TODAY()<=AF18,"", COUNTIF('5月'!$C3:$C1013,AF18)) -> 0 | AG20: =IFERROR(AVERAGE(B20:AF20),0) -> 0
A22: 6月 | B22: 45444 | C22: 45445 | D22: 45446 | E22: 45447 | F22: 45448 | G22: 45449 | H22: 45450 | I22: 45451 | J22: 45452 | K22: 45453 | L22: 45454 | M22: 45455 | N22: 45456 | O22: 45457 | P22: 45458 | Q22: 45459 | R22: 45460 | S22: 45461 | T22: 45462 | U22: 45463 | V22: 45464 | W22: 45465 | X22: 45466 | Y22: 45467 | Z22: 45468 | AA22: 45469 | AB22: 45470 | AC22: 45471 | AD22: 45472 | AE22: 45473 | AG22: Ave.
B23: =CHOOSE(WEEKDAY(B22), "日", "月", "火", "水", "木", "金", "土") -> 土 | C23: =CHOOSE(WEEKDAY(C22), "日", "月", "火", "水", "木", "金", "土") -> 日 | D23: =CHOOSE(WEEKDAY(D22), "日", "月", "火", "水", "木", "金", "土") -> 月 | E23: =CHOOSE(WEEKDAY(E22), "日", "月", "火", "水", "木", "金", "土") -> 火 | F23: =CHOOSE(WEEKDAY(F22), "日", "月", "火", "水", "木", "金", "土") -> 水 | G23: =CHOOSE(WEEKDAY(G22), "日", "月", "火", "水", "木", "金", "土") -> 木 | H23: =CHOOSE(WEEKDAY(H22), "日", "月", "火", "水", "木", "金", "土") -> 金 | I23: =CHOOSE(WEEKDAY(I22), "日", "月", "火", "水", "木", "金", "土") -> 土 | ... AF23: =CHOOSE(WEEKDAY(AF22), "日", "月", "火", "水", "木", "金", "土") -> 土
A24: =SUM(B24:AF24) -> 0 | B24: =IF(TODAY()<=B22,"", COUNTIF('6月'!$C3:$C1013,B22)) -> 0 | C24: =IF(TODAY()<=C22,"", COUNTIF('6月'!$C3:$C1013,C22)) -> 0 | D24: =IF(TODAY()<=D22,"", COUNTIF('6月'!$C3:$C1013,D22)) -> 0 | E24: =IF(TODAY()<=E22,"", COUNTIF('6月'!$C3:$C1013,E22)) -> 0 | F24: =IF(TODAY()<=F22,"", COUNTIF('6月'!$C3:$C1013,F22)) -> 0 | G24: =IF(TODAY()<=G22,"", COUNTIF('6月'!$C3:$C1013,G22)) -> 0 | H24: =IF(TODAY()<=H22,"", COUNTIF('6月'!$C3:$C1013,H22)) -> 0 | I24: =IF(TODAY()<=I22,"", COUNTIF('6月'!$C3:$C1013,I22)) -> 0 | ... AE24: =IF(TODAY()<=AE22,"", COUNTIF('6月'!$C3:$C1013,AE22)) -> 0 | AG24: =IFERROR(AVERAGE(B24:AF24),0) -> 0
A26: 7月 | B26: 45474 | C26: 45475 | D26: 45476 | E26: 45477 | F26: 45478 | G26: 45479 | H26: 45480 | I26: 45481 | J26: 45482 | K26: 45483 | L26: 45484 | M26: 45485 | N26: 45486 | O26: 45487 | P26: 45488 | Q26: 45489 | R26: 45490 | S26: 45491 | T26: 45492 | U26: 45493 | V26: 45494 | W26: 45495 | X26: 45496 | Y26: 45497 | Z26: 45498 | AA26: 45499 | AB26: 45500 | AC26: 45501 | AD26: 45502 | AE26: 45503 | AF26: 45504 | AG26: Ave.
B27: =CHOOSE(WEEKDAY(B26), "日", "月", "火", "水", "木", "金", "土") -> 月 | C27: =CHOOSE(WEEKDAY(C26), "日", "月", "火", "水", "木", "金", "土") -> 火 | D27: =CHOOSE(WEEKDAY(D26), "日", "月", "火", "水", "木", "金", "土") -> 水 | E27: =CHOOSE(WEEKDAY(E26), "日", "月", "火", "水", "木", "金", "土") -> 木 | F27: =CHOOSE(WEEKDAY(F26), "日", "月", "火", "水", "木", "金", "土") -> 金 | G27: =CHOOSE(WEEKDAY(G26), "日", "月", "火", "水", "木", "金", "土") -> 土 | H27: =CHOOSE(WEEKDAY(H26), "日", "月", "火", "水", "木", "金", "土") -> 日 | I27: =CHOOSE(WEEKDAY(I26), "日", "月", "火", "水", "木", "金", "土") -> 月 | ... AF27: =CHOOSE(WEEKDAY(AF26), "日", "月", "火", "水", "木", "金", "土") -> 水
A28: =SUM(B28:AF28) -> 0 | B28: =IF(TODAY()<=B26,"", COUNTIF('7月'!$C3:$C1013,B26)) -> 0 | C28: =IF(TODAY()<=C26,"", COUNTIF('7月'!$C3:$C1013,C26)) -> 0 | D28: =IF(TODAY()<=D26,"", COUNTIF('7月'!$C3:$C1013,D26)) -> 0 | E28: =IF(TODAY()<=E26,"", COUNTIF('7月'!$C3:$C1013,E26)) -> 0 | F28: =IF(TODAY()<=F26,"", COUNTIF('7月'!$C3:$C1013,F26)) -> 0 | G28: =IF(TODAY()<=G26,"", COUNTIF('7月'!$C3:$C1013,G26)) -> 0 | H28: =IF(TODAY()<=H26,"", COUNTIF('7月'!$C3:$C1013,H26)) -> 0 | I28: =IF(TODAY()<=I26,"", COUNTIF('7月'!$C3:$C1013,I26)) -> 0 | ... AF28: =IF(TODAY()<=AF26,"", COUNTIF('7月'!$C3:$C1013,AF26)) -> 0 | AG28: =IFERROR(AVERAGE(B28:AF28),0) -> 0
A30: 8月 | B30: 45505 | C30: 45506 | D30: 45507 | E30: 45508 | F30: 45509 | G30: 45510 | H30: 45511 | I30: 45512 | J30: 45513 | K30: 45514 | L30: 45515 | M30: 45516 | N30: 45517 | O30: 45518 | P30: 45519 | Q30: 45520 | R30: 45521 | S30: 45522 | T30: 45523 | U30: 45524 | V30: 45525 | W30: 45526 | X30: 45527 | Y30: 45528 | Z30: 45529 | AA30: 45530 | AB30: 45531 | AC30: 45532 | AD30: 45533 | AE30: 45534 | AF30: 45535 | AG30: Ave.
B31: =CHOOSE(WEEKDAY(B30), "日", "月", "火", "水", "木", "金", "土") -> 木 | C31: =CHOOSE(WEEKDAY(C30), "日", "月", "火", "水", "木", "金", "土") -> 金 | D31: =CHOOSE(WEEKDAY(D30), "日", "月", "火", "水", "木", "金", "土") -> 土 | E31: =CHOOSE(WEEKDAY(E30), "日", "月", "火", "水", "木", "金", "土") -> 日 | F31: =CHOOSE(WEEKDAY(F30), "日", "月", "火", "水", "木", "金", "土") -> 月 | G31: =CHOOSE(WEEKDAY(G30), "日", "月", "火", "水", "木", "金", "土") -> 火 | H31: =CHOOSE(WEEKDAY(H30), "日", "月", "火", "水", "木", "金", "土") -> 水 | I31: =CHOOSE(WEEKDAY(I30), "日", "月", "火", "水", "木", "金", "土") -> 木 | ... AF31: =CHOOSE(WEEKDAY(AF30), "日", "月", "火", "水", "木", "金", "土") -> 土
A32: =SUM(B32:AF32) -> 0 | B32: =IF(TODAY()<=B30,"", COUNTIF('8月'!$C6:$C1013,B30)) -> 0 | C32: =IF(TODAY()<=C30,"", COUNTIF('8月'!$C6:$C1013,C30)) -> 0 | D32: =IF(TODAY()<=D30,"", COUNTIF('8月'!$C6:$C1013,D30)) -> 0 | E32: =IF(TODAY()<=E30,"", COUNTIF('8月'!$C6:$C1013,E30)) -> 0 | F32: =IF(TODAY()<=F30,"", COUNTIF('8月'!$C6:$C1013,F30)) -> 0 | G32: =IF(TODAY()<=G30,"", COUNTIF('8月'!$C6:$C1013,G30)) -> 0 | H32: =IF(TODAY()<=H30,"", COUNTIF('8月'!$C6:$C1013,H30)) -> 0 | I32: =IF(TODAY()<=I30,"", COUNTIF('8月'!$C6:$C1013,I30)) -> 0 | ... AF32: =IF(TODAY()<=AF30,"", COUNTIF('8月'!$C6:$C1013,AF30)) -> 0 | AG32: =IFERROR(AVERAGE(B32:AF32),0) -> 0
A34: 9月 | B34: 45536 | C34: 45537 | D34: 45538 | E34: 45539 | F34: 45540 | G34: 45541 | H34: 45542 | I34: 45543 | J34: 45544 | K34: 45545 | L34: 45546 | M34: 45547 | N34: 45548 | O34: 45549 | P34: 45550 | Q34: 45551 | R34: 45552 | S34: 45553 | T34: 45554 | U34: 45555 | V34: 45556 | W34: 45557 | X34: 45558 | Y34: 45559 | Z34: 45560 | AA34: 45561 | AB34: 45562 | AC34: 45563 | AD34: 45564 | AE34: 45565 | AG34: Ave.
B35: =CHOOSE(WEEKDAY(B34), "日", "月", "火", "水", "木", "金", "土") -> 日 | C35: =CHOOSE(WEEKDAY(C34), "日", "月", "火", "水", "木", "金", "土") -> 月 | D35: =CHOOSE(WEEKDAY(D34), "日", "月", "火", "水", "木", "金", "土") -> 火 | E35: =CHOOSE(WEEKDAY(E34), "日", "月", "火", "水", "木", "金", "土") -> 水 | F35: =CHOOSE(WEEKDAY(F34), "日", "月", "火", "水", "木", "金", "土") -> 木 | G35: =CHOOSE(WEEKDAY(G34), "日", "月", "火", "水", "木", "金", "土") -> 金 | H35: =CHOOSE(WEEKDAY(H34), "日", "月", "火", "水", "木", "金", "土") -> 土 | I35: =CHOOSE(WEEKDAY(I34), "日", "月", "火", "水", "木", "金", "土") -> 日 | ... AF35: =CHOOSE(WEEKDAY(AF34), "日", "月", "火", "水", "木", "金", "土") -> 土
A36: =SUM(B36:AF36) -> 0 | B36: =IF(TODAY()<=B34,"", COUNTIF('9月'!$C9:$C1013,B34)) -> 0 | C36: =IF(TODAY()<=C34,"", COUNTIF('9月'!$C9:$C1013,C34)) -> 0 | D36: =IF(TODAY()<=D34,"", COUNTIF('9月'!$C9:$C1013,D34)) -> 0 | E36: =IF(TODAY()<=E34,"", COUNTIF('9月'!$C9:$C1013,E34)) -> 0 | F36: =IF(TODAY()<=F34,"", COUNTIF('9月'!$C9:$C1013,F34)) -> 0 | G36: =IF(TODAY()<=G34,"", COUNTIF('9月'!$C9:$C1013,G34)) -> 0 | H36: =IF(TODAY()<=H34,"", COUNTIF('9月'!$C9:$C1013,H34)) -> 0 | I36: =IF(TODAY()<=I34,"", COUNTIF('9月'!$C9:$C1013,I34)) -> 0 | ... L36: =IF(TODAY()<=L34,"", COUNTIF('9月'!$C9:$C1013,L34)) -> 0 | M36: =IF(TODAY()<M34,"", COUNTIF('9月'!$C9:$C1013,M34)) -> 0 | N36: =IF(TODAY()<N34,"", COUNTIF('9月'!$C9:$C1013,N34)) -> 0 | O36: =IF(TODAY()<O34,"", COUNTIF('9月'!$C9:$C1013,O34)) -> 0 | P36: =IF(TODAY()<P34,"", COUNTIF('9月'!$C9:$C1013,P34)) -> 0 | Q36: =IF(TODAY()<Q34,"", COUNTIF('9月'!$C9:$C1013,Q34)) -> 0 | R36: =IF(TODAY()<R34,"", COUNTIF('9月'!$C9:$C1013,R34)) -> 0 | S36: =IF(TODAY()<S34,"", COUNTIF('9月'!$C9:$C1013,S34)) -> 0 | T36: =IF(TODAY()<T34,"", COUNTIF('9月'!$C9:$C1013,T34)) -> 0 | ... AE36: =IF(TODAY()<AE34,"", COUNTIF('9月'!$C9:$C1013,AE34)) -> 0 | AG36: =IFERROR(AVERAGE(B36:AF36),0) -> 0
A38: 10月 | B38: 45566 | C38: 45567 | D38: 45568 | E38: 45569 | F38: 45570 | G38: 45571 | H38: 45572 | I38: 45573 | J38: 45574 | K38: 45575 | L38: 45576 | M38: 45577 | N38: 45578 | O38: 45579 | P38: 45580 | Q38: 45581 | R38: 45582 | S38: 45583 | T38: 45584 | U38: 45585 | V38: 45586 | W38: 45587 | X38: 45588 | Y38: 45589 | Z38: 45590 | AA38: 45591 | AB38: 45592 | AC38: 45593 | AD38: 45594 | AE38: 45595 | AF38: 45596 | AG38: Ave.
B39: =CHOOSE(WEEKDAY(B38), "日", "月", "火", "水", "木", "金", "土") -> 火 | C39: =CHOOSE(WEEKDAY(C38), "日", "月", "火", "水", "木", "金", "土") -> 水 | D39: =CHOOSE(WEEKDAY(D38), "日", "月", "火", "水", "木", "金", "土") -> 木 | E39: =CHOOSE(WEEKDAY(E38), "日", "月", "火", "水", "木", "金", "土") -> 金 | F39: =CHOOSE(WEEKDAY(F38), "日", "月", "火", "水", "木", "金", "土") -> 土 | G39: =CHOOSE(WEEKDAY(G38), "日", "月", "火", "水", "木", "金", "土") -> 日 | H39: =CHOOSE(WEEKDAY(H38), "日", "月", "火", "水", "木", "金", "土") -> 月 | I39: =CHOOSE(WEEKDAY(I38), "日", "月", "火", "水", "木", "金", "土") -> 火 | ... AF39: =CHOOSE(WEEKDAY(AF38), "日", "月", "火", "水", "木", "金", "土") -> 木
A40: =SUM(B40:AF40) -> 0 | B40: =IF(TODAY()<=B38,"", COUNTIF('10月'!$C6:$C1013,B38)) -> 0 | C40: =IF(TODAY()<=C38,"", COUNTIF('10月'!$C6:$C1013,C38)) -> 0 | D40: =IF(TODAY()<=D38,"", COUNTIF('10月'!$C6:$C1013,D38)) -> 0 | E40: =IF(TODAY()<=E38,"", COUNTIF('10月'!$C6:$C1013,E38)) -> 0 | F40: =IF(TODAY()<=F38,"", COUNTIF('10月'!$C6:$C1013,F38)) -> 0 | G40: =IF(TODAY()<=G38,"", COUNTIF('10月'!$C6:$C1013,G38)) -> 0 | H40: =IF(TODAY()<=H38,"", COUNTIF('10月'!$C6:$C1013,H38)) -> 0 | I40: =IF(TODAY()<=I38,"", COUNTIF('10月'!$C6:$C1013,I38)) -> 0 | ... AF40: =IF(TODAY()<=AF38,"", COUNTIF('10月'!$C6:$C1013,AF38)) -> 0 | AG40: =IFERROR(AVERAGE(B40:AF40),0) -> 0 | AH40: =AG40*31 -> 0
A42: 11月 | B42: 45597 | C42: 45598 | D42: 45599 | E42: 45600 | F42: 45601 | G42: 45602 | H42: 45603 | I42: 45604 | J42: 45605 | K42: 45606 | L42: 45607 | M42: 45608 | N42: 45609 | O42: 45610 | P42: 45611 | Q42: 45612 | R42: 45613 | S42: 45614 | T42: 45615 | U42: 45616 | V42: 45617 | W42: 45618 | X42: 45619 | Y42: 45620 | Z42: 45621 | AA42: 45622 | AB42: 45623 | AC42: 45624 | AD42: 45625 | AE42: 45626 | AG42: Ave.
B43: =CHOOSE(WEEKDAY(B42), "日", "月", "火", "水", "木", "金", "土") -> 金 | C43: =CHOOSE(WEEKDAY(C42), "日", "月", "火", "水", "木", "金", "土") -> 土 | D43: =CHOOSE(WEEKDAY(D42), "日", "月", "火", "水", "木", "金", "土") -> 日 | E43: =CHOOSE(WEEKDAY(E42), "日", "月", "火", "水", "木", "金", "土") -> 月 | F43: =CHOOSE(WEEKDAY(F42), "日", "月", "火", "水", "木", "金", "土") -> 火 | G43: =CHOOSE(WEEKDAY(G42), "日", "月", "火", "水", "木", "金", "土") -> 水 | H43: =CHOOSE(WEEKDAY(H42), "日", "月", "火", "水", "木", "金", "土") -> 木 | I43: =CHOOSE(WEEKDAY(I42), "日", "月", "火", "水", "木", "金", "土") -> 金 | ... AF43: =CHOOSE(WEEKDAY(AF42), "日", "月", "火", "水", "木", "金", "土") -> 土
A44: =SUM(B44:AF44) -> 0 | B44: =IF(TODAY()<=B42,"", COUNTIF('11月'!$C9:$C1013,B42)) -> 0 | C44: =IF(TODAY()<=C42,"", COUNTIF('11月'!$C9:$C1013,C42)) -> 0 | D44: =IF(TODAY()<=D42,"", COUNTIF('11月'!$C9:$C1013,D42)) -> 0 | E44: =IF(TODAY()<=E42,"", COUNTIF('11月'!$C9:$C1013,E42)) -> 0 | F44: =IF(TODAY()<=F42,"", COUNTIF('11月'!$C9:$C1013,F42)) -> 0 | G44: =IF(TODAY()<=G42,"", COUNTIF('11月'!$C9:$C1013,G42)) -> 0 | H44: =IF(TODAY()<=H42,"", COUNTIF('11月'!$C9:$C1013,H42)) -> 0 | I44: =IF(TODAY()<=I42,"", COUNTIF('11月'!$C9:$C1013,I42)) -> 0 | ... AE44: =IF(TODAY()<=AE42,"", COUNTIF('11月'!$C9:$C1013,AE42)) -> 0 | AG44: =IFERROR(AVERAGE(B44:AF44),0) -> 0
A46: 12月 | B46: 45627 | C46: 45628 | D46: 45629 | E46: 45630 | F46: 45631 | G46: 45632 | H46: 45633 | I46: 45634 | J46: 45635 | K46: 45636 | L46: 45637 | M46: 45638 | N46: 45639 | O46: 45640 | P46: 45641 | Q46: 45642 | R46: 45643 | S46: 45644 | T46: 45645 | U46: 45646 | V46: 45647 | W46: 45648 | X46: 45649 | Y46: 45650 | Z46: 45651 | AA46: 45652 | AB46: 45653 | AC46: 45654 | AD46: 45655 | AE46: 45656 | AF46: 45657 | AG46: Ave.
B47: =CHOOSE(WEEKDAY(B46), "日", "月", "火", "水", "木", "金", "土") -> 日 | C47: =CHOOSE(WEEKDAY(C46), "日", "月", "火", "水", "木", "金", "土") -> 月 | D47: =CHOOSE(WEEKDAY(D46), "日", "月", "火", "水", "木", "金", "土") -> 火 | E47: =CHOOSE(WEEKDAY(E46), "日", "月", "火", "水", "木", "金", "土") -> 水 | F47: =CHOOSE(WEEKDAY(F46), "日", "月", "火", "水", "木", "金", "土") -> 木 | G47: =CHOOSE(WEEKDAY(G46), "日", "月", "火", "水", "木", "金", "土") -> 金 | H47: =CHOOSE(WEEKDAY(H46), "日", "月", "火", "水", "木", "金", "土") -> 土 | I47: =CHOOSE(WEEKDAY(I46), "日", "月", "火", "水", "木", "金", "土") -> 日 | ... AF47: =CHOOSE(WEEKDAY(AF46), "日", "月", "火", "水", "木", "金", "土") -> 火
A48: =SUM(B48:AF48) -> 0 | B48: =IF(TODAY()<=B46,"", COUNTIF('12月'!$C9:$C1013,B46)) -> 0 | C48: =IF(TODAY()<=C46,"", COUNTIF('12月'!$C9:$C1013,C46)) -> 0 | D48: =IF(TODAY()<=D46,"", COUNTIF('12月'!$C9:$C1013,D46)) -> 0 | E48: =IF(TODAY()<=E46,"", COUNTIF('12月'!$C9:$C1013,E46)) -> 0 | F48: =IF(TODAY()<=F46,"", COUNTIF('12月'!$C9:$C1013,F46)) -> 0 | G48: =IF(TODAY()<=G46,"", COUNTIF('12月'!$C9:$C1013,G46)) -> 0 | H48: =IF(TODAY()<=H46,"", COUNTIF('12月'!$C9:$C1013,H46)) -> 0 | I48: =IF(TODAY()<=I46,"", COUNTIF('12月'!$C9:$C1013,I46)) -> 0 | ... AF48: =IF(TODAY()<=AF46,"", COUNTIF('12月'!$C9:$C1013,AF46)) -> 0 | AG48: =IFERROR(AVERAGE(B48:AF48),0) -> 0
A50: 合計 | B50: Ave. | C50: 1週間Ave.
A51: =SUM(A4,A8,A12,A16,A20,A24,A28,A32,A36,A40,A44,A48) -> 0 | B51: =IFERROR(AVERAGE(B4:AF4,B8:AC8,B12:AF12,B16:AE16,B20:AF20,B24:AE24,B28:AF28,B32:AF32,B36:AE36,B40:AF40,B44:AE44,B48:AF48),0) -> 0 | C51: {=INDEX($A$2:$AG$48,MATCH(TEXT(TODAY()-1,"M")&"月",$A$2:$A$48,0)+2,MATCH(TEXT(TODAY()-1,"d")&"日",$1:$1,0)) +INDEX($A$2:$AG$48,MATCH(TEXT(TODAY()-2,"M")&"月",$A$2:$A$48,0)+2,MATCH(TEXT(TODAY()-2,"d")&"日",$1:$1,0)) +INDEX($A$2:$AG$48,MATCH(TEXT(TODAY()-3,"M")&"月",$A$2:$A$48,0)+2,MATCH(TEXT(TODAY()-3,"d")&"日",$1:$1,0)) +INDEX($A$2:$AG$48,MATCH(TEXT(TODAY()-4,"M")&"月",$A$2:$A$48,0)+2,MATCH(TEXT(TODAY()-4,"d")&"日",$1:$1,0)) +INDEX($A$2:$AG$48,MATCH(TEXT(TODAY()-5,"M")&"月",$A$2:$A$48,0)+2,MATCH(TEXT(TODAY()-5,"d")&"日",$1:$1,0)) +INDEX($A$2:$AG$48,MATCH(TEXT(TODAY()-6,"M")&"月",$A$2:$A$48,0)+2,MATCH(TEXT(TODAY()-6,"d")&"日",$1:$1,0)) +INDEX($A$2:$AG$48,MATCH(TEXT(TODAY()-7,"M")&"月",$A$2:$A$48,0)+2,MATCH(TEXT(TODAY()-7,"d")&"日",$1:$1,0))/7} -> 0
A53: スラック通知情報エリア
A54: =TEXT(TODAY()-1,"m")&"月" -> 5月 | B54: =TEXT(TODAY()-1,"d")&"日" -> 10日 | C54: =TEXT(TODAY()-1,"m")&"月" -> 5月 | D54: 合計 | E54: =TEXT(TODAY()-1,"m")&"月" -> 5月 | F54: Ave. | G54: 2024年累計 | I54: 2024年累計Ave. | L54: 中期目標Ave. | N54: 長期目標Ave. | P54: 1週間Ave.
A55: {=INDEX($A$2:$AG$48,MATCH(A54,$A$2:$A$48,0)+2,MATCH(B54,$1:$1,0))} -> 0 | C55: {=INDEX($A$2:$AG$48,MATCH(C54,$A$2:$A$48,0)+2,1)} -> 0 | E55: {=INDEX($A$2:$AG$48,MATCH(E54,$A$2:$A$48,0)+2,MATCH(F54,$1:$1,0))} -> 0 | G55: =A51 -> 0 | I55: =B51 -> 0 | L55: 2.5 | N55: 3.2 | P55: =C51 -> 0
L56: 予算削減前 Ave.+0.2 | N56: 月間受電100件
B106: 金 | C106: 土 | D106: 日 | E106: 月 | F106: 火 | G106: 水 | H106: 木 | I106: 金 | J106: 土 | K106: 日 | L106: 月 | M106: 火 | N106: 水 | O106: 木 | P106: 金 | Q106: 土 | R106: 日 | S106: 月 | T106: 火 | U106: 水 | V106: 木 | W106: 金 | X106: 土 | Y106: 日 | Z106: 月 | AA106: 火 | AB106: 水 | AC106: 木 | AD106: 金 | AE106: 土
B107: 45200 | C107: 45201 | D107: 45202 | E107: 45203 | F107: 45204 | G107: 45205 | H107: 45206 | I107: 45207 | J107: 45208 | K107: 45209 | L107: 45210 | M107: 45211 | N107: 45212 | O107: 45213 | P107: 45214 | Q107: 45215 | R107: 45216 | S107: 45217 | T107: 45218 | U107: 45219 | V107: 45220 | W107: 45221 | X107: 45222 | Y107: 45223 | Z107: 45224 | AA107: 45225 | AB107: 45226 | AC107: 45227 | AD107: 45228 | AE107: 45229
B108: 日 | C108: 月 | D108: 火 | E108: 水 | F108: 木 | G108: 金 | H108: 土 | I108: 日 | J108: 月 | K108: 火 | L108: 水 | M108: 木 | N108: 金 | O108: 土 | P108: 日 | Q108: 月 | R108: 火 | S108: 水 | T108: 木 | U108: 金 | V108: 土 | W108: 日 | X108: 月 | Y108: 火 | Z108: 水 | AA108: 木 | AB108: 金 | AC108: 土 | AD108: 日 | AE108: 月

Sheet 1月
B2: ★2026年1月 | J2: 総計 | L2: ★面談結果未入力 | O2: =設定用!H6 -> Ｓ：即受注
D3: 総計 | E3: =設定用!B6 -> 横浜本店 | F3: =設定用!B7 -> 藤沢支店 | G3: =設定用!B8 -> 渋谷支店 | I3: 面談対応件数 | J3: =D207 -> 32 | K3: 未入力1 | L3: =IFERROR("管理表番号（"&VLOOKUP(K3,$A$10:$U$199,2,FALSE)&"）／面談担当者："&VLOOKUP(K3,$A$10:$U$199,21,FALSE),"") | O3: =設定用!H7 -> Ｓ：戻り受注
B4: 受信件数 | D4: =SUM(E4:I4) -> 55 | E4: =COUNTIF($F$9:$F$199,E3) -> 55 | F4: =COUNTIF($F$9:$F$199,F3) -> 0 | G4: =COUNTIF($F$9:$F$199,G3) -> 0 | I4: 即受注件数 | J4: =D208 -> 12 | K4: 未入力2 | L4: =IFERROR("管理表番号（"&VLOOKUP(K4,$A$10:$U$199,2,FALSE)&"）／面談担当者："&VLOOKUP(K4,$A$10:$U$199,21,FALSE),"")
B5: 面談予約件数 | D5: =SUM(E5:I5) -> 35 | E5: =COUNTIFS($F$9:$F$199,E3,$R$9:$R$199,"<>") -> 35 | F5: =COUNTIFS($F$9:$F$199,F3,$R$9:$R$199,"<>") -> 0 | G5: =COUNTIFS($F$9:$F$199,G3,$R$9:$R$199,"<>") -> 0 | I5: 戻り受注件数 | J5: =D209 -> 4 | K5: 未入力3 | L5: =IFERROR("管理表番号（"&VLOOKUP(K5,$A$10:$U$199,2,FALSE)&"）／面談担当者："&VLOOKUP(K5,$A$10:$U$199,21,FALSE),"")
B6: 面談獲得率 | D6: =IFERROR(D5/D4,"") -> 0.63636364 | E6: =IFERROR(E5/E4,"") -> 0.63636364 | F6: =IFERROR(F5/F4,"") | G6: =IFERROR(G5/G4,"") | I6: 受注率 | J6: =D210 -> 0.5 | K6: 未入力4 | L6: =IFERROR("管理表番号（"&VLOOKUP(K6,$A$10:$U$199,2,FALSE)&"）／面談担当者："&VLOOKUP(K6,$A$10:$U$199,21,FALSE),"") | N6: //
B8: ＮＯ | C8: 日付 | D8: 時間 | E8: 担当 | F8: 受信 事務所 | G8: 媒体 | H8: お名前 （ひらがな記入） | K8: お住まい住所 or アナウンス | L8: 電話番号 | M8: 相談の概要 | N8: 問い合わせ内容 | O8: 対応 | P8: 面談場所 | Q8: 面談備考 | R8: 面談日 | S8: 曜日 | T8: 時間 | U8: 面談担当 | V8: 管理担当 | W8: 面談結果 | X8: 対応
A9: =Y9&Z9 -> 0 | B9: 1 | C9: 46027 | D9: 12：30 | E9: 宮田 | F9: 横浜本店 | G9: HP | H9: おおつかなおき様 | K9: 横浜 | L9: 080-5410-9922 | M9: 相続手続き | N9: 【相談者】おおつかなおき様 【TEL】080-5410-9922 【被相続人】お父様 【相続人】なおき様とお姉さまの計2名 【相続財産】 不動産：自宅（土地：お父様のお母様と共有名義、建物：お父様の単独名義） 預貯金：ゆうちょ銀行、横浜銀行に各20万円ずつ 有価証券：なし その他：なし 【遺言書】なし 【相続税】なし 【相談内容】 不動産の名義変更について、お父様のお母様と共有名義なので、名義変更の期間等あるので知りたい。 また、お父様は離婚しており、再婚等はしていないとの事。 面談の日程ですが、この日時を指定しており、面談場所は空いていますが、難しい場合は再度こちらから連絡してリスケ等行う旨伝えてあります。 | O9: 無料相談にお越しください | P9: 藤沢支店 | R9: 46031 | S9: 金 | T9: 17：30 | U9: 花井 | W9: Ｓ：即受注 | X9: 依頼人の父（章弘）と章弘の母（大塚ひろ子）で共有で所有している不動産（章弘の自宅）について換価分割をする旨の依頼。 なお、章弘については金融資産もあることから相続一式にて手続。生命保険の開示と債務調査も行うこととしている。 | Y9: =IF(R9="","", IF(AND(R9<TODAY(),W9=""),"未入力","")) | Z9: =COUNTIF($Y$9:Y9,"未入力") -> 0
A10: =Y10&Z10 -> 0 | B10: 2 | C10: 46027 | D10: 14：03 | E10: 宮田 | F10: 横浜本店 | G10: HP | H10: とみざわえみ様 | K10: 横浜 | L10: 080-6793-5615 | M10: 複雑な相続 | N10: 当日はえみ様と妹様とお母様の計3名でいらっしゃるとの事。 【相談者】とみざわえみ様 【TEL】080-6793-5615 【被相続人】お父様（R7.8.3） 【相続人】前妻との子3名、後妻の計4名（後妻との子はわからない） 【相続財産】 不動産：自宅（後妻との購入物はわからない） 預貯金：1つ（他9口座見つかる） 有価証券：あり 車：ベンツ（事故車） 【遺言書】あり 【相談内容】 生前に（ベンツで）事故を起こしていて、後妻の弁護士の方から遺言書や財産目録が送られてきて、亡くなったことを知った。送付された日はR7.11.12若しくは13との事。 財産目録に預貯金として1つしか記載がなかったため、おかしいと思い自分で調査したところ、他に9口座見つかり、現在残高証明書を請求中。また、有価証券の方も口座が見つかっているが、中身はまだ確認ができていないため、あるのかないのかもわからない。ただ、口座は見つかっているため、多分ありそう。 遺言書の中身は家屋は前妻の方にその他資産は後妻に分ける内容であった。 えみ様は限定承認とかを考えていて、先ずは期間伸長の申し立てを行おうと思っている。 当日はわからない書類とかがあったら持ってきていただけるとの事。 細かい内容に関しては当日にお話しいただけるとの事で終話いたしました。 | O10: 無料相談にお越しください | P10: 横浜本店 | R10: 46039 | S10: 土 | T10: 10：00 | U10: 森谷 | W10: Ｅ：他社紹介 | X10: 弁護士紹介 | Y10: =IF(R10="","", IF(AND(R10<TODAY(),W10=""),"未入力","")) | Z10: =COUNTIF($Y$9:Y10,"未入力") -> 0
A11: =Y11&Z11 -> 0 | B11: 3 | C11: 46023 | D11: 0.40277778 | E11: 久田 | F11: 横浜本店 | G11: HP | H11: こばやし きくこ様 | K11: 江東区 | L11: 090-1695-9183 | M11: 遺言書 | N11: 2023年9月に、ひのいわ葬祭様のご紹介により五十嵐さんが無料相談を対応された方です。 ※小林俊樹様（こばやし としき）で、相続ステーションにて氏名検索をすると面談情報が確認できます。 相談内容：こばやし様のお母様に関する遺言書の作成について 現在、お母様は長野県内の施設にお住まいで、すでに遺言書の文案は完成しているとのことです。 今後は、その文案をもとに公証役場にて公正証書遺言を作成されたいそうです。 当日はこばやし様お一人でご来所される予定です。 090-1695-9183 | O11: 無料相談にお越しください | P11: 横浜本店 | R11: 46031 | S11: 金 | T11: 0.625 | U11: 五十嵐 | W11: Ｂ：見込み低 | X11: 長野の公証役場にご自身で電話して進めてみる | Y11: =IF(R11="","", IF(AND(R11<TODAY(),W11=""),"未入力","")) | Z11: =COUNTIF($Y$9:Y11,"未入力") -> 0
A12: =Y12&Z12 -> 0 | B12: 4 | C12: 46023 | D12: 0.41666667 | E12: 久田 | F12: 横浜本店 | G12: HP | H12: いのうえ よういち様 | K12: 横須賀市 | L12: 080-7286-9438 | M12: 生前対策 | N12: 令和5年に故井上弓美様（よういち様の叔父様）の相談手続きをご依頼いただいていたお客様です。 ※当時のご契約者様：井上道雄様（よういち様のお父様） 相談内容：現在施設に入居中のお父様の将来的な相続手続について 推定相続人：よういち様、妹様 ※お母様は昨年にご逝去 ①現在父が固定資産税を払っている、祖父名義の鹿児島県の土地・家屋 →相続はせず放棄したい ②空き家状態である父名義の横須賀市の実家 →いずれ処分したいため、遺品整理や売却を依頼したい ③父名義の預金 →よういち様と妹様で分ける予定のため、手続きの流れを知りたい 当日はよういち様お一人でご来所される予定です。 鹿児島県と横須賀市の不動産の納税通知書をお持ちいただけます。 080-7286-9438 | O12: 無料相談にお越しください | P12: 横浜本店 | R12: 46035 | S12: 火 | T12: 0.41666667 | U12: 伊藤 | W12: Ｓ：戻り受注 | X12: 過去客・・・家族信託で受注 | Y12: =IF(R12="","", IF(AND(R12<TODAY(),W12=""),"未入力","")) | Z12: =COUNTIF($Y$9:Y12,"未入力") -> 0
A13: =Y13&Z13 -> 0 | B13: 5 | C13: 46028 | D13: 15：34 | E13: 宮川 | F13: 横浜本店 | G13: HP | H13: あだち ひさふみ | K13: 渋谷市 | L13: 090-3066-6436 | M13: 遺言書 | N13: ■相談者様：アダチ ヒサフミ様 ■ご連絡先：090-3066-6436 ■お困りごと 前妻との間にも子供がいるが、今の配偶者にきちんと財産を遺したい。 | O13: 無料相談にお越しください | P13: 渋谷支店 | R13: 46031 | S13: 金 | T13: 10：00 | U13: 山田 | W13: Ｂ：見込み低 | X13: 妻、養女とした妻の子、前妻との子、前々妻との子の４名が相続人。自身の財産は少なくしており、相続税評価では2,200万円程。遺留分の請求を懸念している。執行者をつけない公正証書遺言を提案。家族と検討に。相談者はソニー生命の副部長。 | Y13: =IF(R13="","", IF(AND(R13<TODAY(),W13=""),"未入力","")) | Z13: =COUNTIF($Y$9:Y13,"未入力") -> 0
A14: =Y14&Z14 -> 0 | B14: 6 | C14: 46028 | D14: 10：00 | E14: 久田 | F14: 横浜本店 | G14: HP | H14: はやし あきひろ様 | K14: 横浜市 | L14: 080-8722-9939 | M14: 相続税申告 | N14: 被相続人：お父様（Ｒ8/1/3ご逝去） 相続人：ご長男様、ご長女様 はやし様はご長女様の旦那様 不動産：なし（生前に売却済み） 預貯金：4200～300万円程 生命保険：1300万円 当日ははやし様、ご長女のお二人でいらっしゃいます。 080-8722-9939 ☆面談日程ほぼ確定ですが、ご長女様とご相談されてからお決めになりたいそうなので、仮で抑えております。確定次第はやし様よりご連絡いただける予定です。 →1/7 日程確定（久田） →1/8 はやし様より再度お電話あり、日程変更を承りました。（安井） | O14: 無料相談にお越しください | P14: 横浜本店 | R14: 46031 | S14: 金 | T14: 10：00 | U14: 伊藤 | W14: Ｂ：見込み低 | X14: 過去客 （そごう前相談会で遺言書作成したお客様・・・担当 杉原さん/越川さん） 被相続人：髙石功様（たかいし いさお）オーシャンにて遺言公正証書作成者（執行者は林様） 相続人：娘の林礼子様 兄 の二名 相続財産は、預金 （4,400万円ほど）+生命保険の非課税枠からのはみだし（300万円ほど） 相続税申告あり・・・・申告は林様の夫がやるご意向 兄との関係が微妙なので、専門家を入れるかな？と検討している。 兄に確認し、執行者代行の依頼の可否の結論を出す。 | Y14: =IF(R14="","", IF(AND(R14<TODAY(),W14=""),"未入力","")) | Z14: =COUNTIF($Y$9:Y14,"未入力") -> 0
A15: =Y15&Z15 -> 0 | B15: 7 | C15: 46028 | D15: 17：50 | E15: 久田 | F15: 横浜本店 | G15: HP | H15: まつむら ゆうじ様 | K15: 横浜 | L15: 080-5646-0466 | M15: 相続税申告 | N15: 被相続人：お母様（Ｒ7.9ご逝去） 相続人：まつむら様、弟様 計2名 不動産：ご自宅（土地・家屋） 預貯金：3000万円ほど 相続税の申告が必要な場合、10ヶ月の期限があることはお伝え済みです。 当日は、弟様とお二人でご来所いただける予定です。 ☆面談日程調整中です。 お電話がありましたら、日程の確定と面談場所のご案内をお願いいたします。 土曜日を希望する可能性大です！ →1/6 再度お電話いただき日程調整いたしました（宮田） | O15: 無料相談にお越しください | P15: 横浜本店 | R15: 46032 | S15: 土 | T15: 13：00 | U15: 新井 | W15: Ｓ：即受注 | X15: 相続税申告有の相続手続き及び査定を受任 | Y15: =IF(R15="","", IF(AND(R15<TODAY(),W15=""),"未入力","")) | Z15: =COUNTIF($Y$9:Y15,"未入力") -> 0
A16: =Y16&Z16 -> 0 | B16: 8 | C16: 46029 | D16: 9：35 | E16: 上田 | F16: 横浜本店 | G16: HP | H16: ひろさき様 | L16: 01-7277-3831 | M16: その他 | N16: 銀行から借り入れがあり、返済等対応が遅れてしまい、一括返済をしろと言われている。 家のローンもあるため、競売にかけられてしまうかもですが、それは避けたいとのこと。 どうすればいいか | O16: 他社紹介 | Y16: =IF(R16="","", IF(AND(R16<TODAY(),W16=""),"未入力","")) | Z16: =COUNTIF($Y$9:Y16,"未入力") -> 0
A17: =Y17&Z17 -> 0 | B17: 9 | C17: 46029 | D17: 15：50 | E17: 菅家 | F17: 横浜本店 | G17: HP | H17: あべ ゆうたろう様 | K17: 横浜 | L17: 080-5069-2657 | M17: 相続手続き | N17: 被相続人 祖父 相続人 子3名 相談者 あべ ゆうたろう様 孫 祖父名義の不動産について、名義変更のご相談 2023年に一度OCで相談しており、その際にはすぐには手続きをせず、改めて手続きをしないとと思い今回お電話をいただきました。 意向としては、相談者母に名義を変更したいとのことです。 可能であれば納税通知書などご用意くださいとお伝えしました。 当日は相談者のみご来所されます。 | O17: 無料相談にお越しください | P17: 藤沢支店 | R17: 46037 | S17: 木 | T17: 16：00 | U17: 角田 | W17: Ｓ：即受注 | X17: 相続登記のみ受注。10年以上前の相続。抵当権の債務者変更可能性有り | Y17: =IF(R17="","", IF(AND(R17<TODAY(),W17=""),"未入力","")) | Z17: =COUNTIF($Y$9:Y17,"未入力") -> 0
A18: =Y18&Z18 -> 0 | B18: 10 | C18: 46030 | D18: 18：15 | E18: 久田 | F18: 横浜本店 | G18: HP | H18: いながき あいみ様 | K18: 横浜 | L18: 090-7527-3963 | M18: 相続放棄 | N18: 被相続人：祖母（令和7年1月6日にご逝去された旨を知った） 令和2年に、美菜子先生および蔭山さんがご担当されたお客様です。 最初は、他の相続人から「預金の解約手続きを進めるため、戸籍と印鑑証明書を送ってほしい」と依頼を受けたものの、相続放棄を検討しているため、送付してよいか分からないとのご相談でお電話をいただきました。 弊所からは「送らないほうがよい」とお伝えしましたが、他の相続人とは一切交流がなく、その旨をどのような言い方で伝えればよいか悩まれているご様子でした。 相続放棄のお手続きの流れを知りたいそうです。 ※ご面談日については、山田先生承認済みです。 090-7527-3963 | O18: 無料相談にお越しください | P18: 横浜本店 | R18: 46033 | S18: 日 | T18: 17：00 | U18: 山田 | W18: Ｓ：即受注 | X18: 色々とごたごたもしているので放棄したい。２名分で受注。 | Y18: =IF(R18="","", IF(AND(R18<TODAY(),W18=""),"未入力","")) | Z18: =COUNTIF($Y$9:Y18,"未入力") -> 0
A19: =Y19&Z19 -> 0 | B19: 11 | C19: 46030 | D19: 9：45 | E19: 上田 | F19: 横浜本店 | G19: HP | H19: てらうち じゅんこ様 | K19: 横浜 | L19: 045-241-3258 | M19: 生前対策 | N19: お母様についての生前対策 母の推定相続人は３名いる。（長女、長女の夫（養子縁組）、長男） 長男に関しては最近兄妹であることを聞いた。それまでは従兄弟だと思っていた。 財産は不動産建物が持分、預金があり、どうやって相続をするのがよいのかというご相談から生前対策の話を持ち込みました。 長男とは連絡が取れなさそうとのこと。 旦那様と日程調整して、お電話いただけます。 1/9 日程調整いただきお電話いただくも、ご希望日1/24(土)ｸﾚｱで対応できる面談員がおらず。 1/28(水)午前中の空き状況を聞かれたので、本日時点では複数名空きがあるとお伝えしました。 再度旦那様と調整しお電話いただくこととなりました。(菅家) 1/19 再度ご連絡いただき面談日確定いたしました。(久田) | O19: 無料相談にお越しください | P19: 横浜本店 | R19: 46050 | S19: 水 | T19: 10：00 | U19: 新井 | W19: Ｓ：戻り受注 | X19: 公正証書遺言作成で受任 | Y19: =IF(R19="","", IF(AND(R19<TODAY(),W19=""),"未入力","")) | Z19: =COUNTIF($Y$9:Y19,"未入力") -> 0
A20: =Y20&Z20 -> 0 | B20: 12 | C20: 46030 | D20: 20：00 | E20: 小泉 | F20: 横浜本店 | G20: HP | H20: かきた あやの様 | K20: 横浜 | L20: 080-5054-9481 | M20: 生前対策 | N20: 母からの生前贈与について相談です。 父が亡くなり、父所有の持家を母が相続・売却予定です(不動産屋の見積によると1億相当)。売却益で母用の中古マンションを購入予定ではありますが現金が残る予定。また過去の投資などによる預貯金もあります。 母には100歳近い母(私から見た祖母)と独身子供無しの兄(私から見た叔父)もおり、それぞれ持家と預貯金があります。 母としては私と兄および私と兄の子(未成年/母から見た孫)に相続・贈与を希望していますがどう手を付けたらいいか分かりません。 何を、誰に、いつまでに、いくら、どう贈与すべきがご相談させて頂けますと幸いです。 【ご案内内容】 ・不動産売却については現在複数見積もりを取っていいる状況（確定はまだ） ・相続についてはこれから →不動産事業部もいるので、相続から売却、生前対策までまとめてお手伝いできるとご案内しアポイントとなりました。 お母様と日程を調整をしてお電話いただきます。 | O20: 無料相談にお越しください | P20: 渋谷支店 | R20: 46050 | S20: 水 | T20: 10：00 | U20: 角田 | W20: Ｂ：見込み低 | X20: 生前贈与の相談が主。特に生前贈与しなければいけない事情ではなく、他親族から相続して財産が多くなるので、相続税対策で検討したいとのこと。 | Y20: =IF(R20="","", IF(AND(R20<TODAY(),W20=""),"未入力","")) | Z20: =COUNTIF($Y$9:Y20,"未入力") -> 0
A21: =Y21&Z21 -> 0 | B21: 13 | C21: 46031 | D21: 11：09 | E21: 宮田 | F21: 横浜本店 | G21: HP | H21: やまざき りえ様 | K21: 横須賀 | L21: 090-5763-0007 | M21: 遺言書 | N21: 当日は、相談者様と相談者の旦那様の計2名様でお越しくださいます。 【相談者】やまざきりえ様（ご長女様） 【TEL】090-5763-0007 【遺言者】お母様（85歳） 【家族構成】 お父様（昨年ご逝去）、お母様、子ども計4名（ご長男様、次男様、ご長女様、次女様） 【内容】 昨年にお父様を亡くされてバタバタしていた。 少し落ち着いてきたので遺言書の検討をしている。 作るのであれば公正証書が良いとの事。 四兄弟なため、一般的には多く、主にご長女様である相談者がお母様の面倒とかをみている。 急に相続となった際は、相談者がお手続きとかを進めて行くことになると思うので、みんなでもめたくない。 遺言書に何を記載するのかとかがわからず教えてほしい。 主に不動産がメインであって、預貯金とかも書いた方が良いのかわからないとの事。 生前贈与は孫に行いたいとおっしゃっていました。 | O21: 無料相談にお越しください | P21: 横浜本店 | R21: 46039 | S21: 土 | T21: 13：00 | U21: 鵜飼 | W21: Ｂ：見込み低 | X21: ご主人様の相続手続においても税理士を入れて二次相続を検討したほうが良い旨をお伝え。 | Y21: =IF(R21="","", IF(AND(R21<TODAY(),W21=""),"未入力","")) | Z21: =COUNTIF($Y$9:Y21,"未入力") -> 0
A22: =Y22&Z22 -> 0 | B22: 14 | C22: 46031 | D22: 15：00 | E22: 菅家 | F22: 横浜本店 | G22: HP | H22: 女性 | K22: 横浜 | L22: 080-5089-3350 | M22: 生前対策 | N22: 茨城県の不動産(田畑)について。 母の相続の際に自分が相続した茨城の不動産について、ご自身の相続の際に子供たちに子の土地を残したくないと。 田畑の不動産については扱いが厳しいので、国庫帰属や今のうちに贈与などを活用して、実際に相続が発生した際には相続放棄をするなどが、対策になると思いますとお伝え。 限定承認のお話しなどがあがりましたので、もしご希望であれば無料相談ご活用くださいとご案内。お客様は江東区にお住いのようで、一度子供たちと相談の上必要があれば再度連絡しますとのこと。 | O22: 無料相談にお越しください | X22: ご主人様の相続手続は税理士に相談済みとのことで、はっきりとした回答はもらえず。不動産の査定も複数社依頼済みで、ご提案しましたが、現状は必要ないとのことでした。 | Y22: =IF(R22="","", IF(AND(R22<TODAY(),W22=""),"未入力","")) | Z22: =COUNTIF($Y$9:Y22,"未入力") -> 0
A23: =Y23&Z23 -> 0 | B23: 15 | C23: 46031 | D23: 15：05 | E23: 宮田 | F23: 横浜本店 | G23: HP | H23: 女性 | M23: その他 | N23: R8.1.4に亡くなられたお母様の年金のお手続きに対しての質問でした。 配偶者とはすでに離婚していて、お電話口様の一人っ子でした。 管轄の年金事務所を伝え、お手続きを行ってみてもし相続について質問があったらまたお電話いただけるとの事です。 | Y23: =IF(R23="","", IF(AND(R23<TODAY(),W23=""),"未入力","")) | Z23: =COUNTIF($Y$9:Y23,"未入力") -> 0
A24: =Y24&Z24 -> 0 | B24: 16 | C24: 46031 | D24: 15：40 | E24: 菅家 | F24: 横浜本店 | G24: HP | H24: はた かずき様 | K24: 浦和 | L24: 090-1857-8389 | M24: 遺言書 | N24: 公正証書遺言についてのご相談 ご相談者様は公正証書遺言の作成をご検討されており、作成後に遺言書を保管してくれるところを探していると。 祖母の相続の際、ご相談者様に全て相続させる旨の遺言書があったにもかかわらず、法定相続人ではないので見せることはできないと弁護士に言われて困った経験があると。 なのでご自身の相続の際に、保管と他の相続人や遺贈先への連絡を対応してくれるところに遺言書を預けたいようです。 ※公証役場や法務局で預けられることはご存じのようで、そのうえで公的機関ではなく企業に預けるのもありかと考えているとのことです。 オーシャンでは保管と連絡のみのご依頼は受けていない旨、遺言執行者をオーシャンにするか、または相続が発生した際にはオーシャンにご依頼いただくのであれば対応可能である旨をお伝えしました。(山田先生と安井さんの案件で受けたことがあるようです。) 遺言書の内容などもまだ決めていないとのことで、場合によっては遺言書作成からご提案をお願いいたします。 | O24: 無料相談にお越しください | P24: 渋谷支店 | R24: 46038 | S24: 金 | T24: 15：00 | U24: 伊藤 | W24: Ｂ：見込み低 | X24: 遺言公正証書は自分で作成するが、保管・受遺者への連絡をお願いしたい。 受遺者には作成したことは秘密にしたい。 受遺者は知人で家族・親族ではないため、死亡の事実を知る事が出来ない場合もある。 イキイキを執行者に選任していただければ、預かりますが、死亡の連絡が入るようにしていただきたい。 とお伝えし検討いただきます。 法務局保管の指定者通知制度を利用し、連絡が入るようにすることも検討。 | Y24: =IF(R24="","", IF(AND(R24<TODAY(),W24=""),"未入力","")) | Z24: =COUNTIF($Y$9:Y24,"未入力") -> 0
A25: =Y25&Z25 -> 0 | B25: 17 | C25: 46032 | D25: 14：00 | E25: 渡部 | F25: 横浜本店 | G25: メール | H25: はせがわ ようこ | L25: 050-5210-0683 | M25: 相続手続き | N25: 1/10 14：00 着信のみ 渡部 【お問い合わせの内容】 不動産の名義変更について 【お問い合わせの詳細】 相続にあたり貴社でお願いする場合の不動産鑑定と登記費用もろもろについてご教示頂きたく存じます。 辻堂元町2丁目 宅地 地番3071番17 171.76平米 所有権 建物 木造 1階 62.10平米 2階 57.13平米 一住 60/200 路線価 215D 計画道路予定地 事業決定していません 面談については取り急ぎ費用と鑑定結果をメールでご教示頂きましてからご相談させて頂きたく存じます。 それではよろしくお願い致します。 【個別のご要望】 相続不動産の無料査定を希望する 【WEB面談の希望】 WEB面談を希望する | Y25: =IF(R25="","", IF(AND(R25<TODAY(),W25=""),"未入力","")) | Z25: =COUNTIF($Y$9:Y25,"未入力") -> 0
A26: =Y26&Z26 -> 0 | B26: 18 | C26: 46032 | D26: 14：40 | E26: 安井 | F26: 横浜本店 | G26: HP | H26: まつだ ようこ様 | K26: 横浜 | L26: 080-5373-3086 | M26: 相続手続き | N26: 被相続人：お母様（令和6年11月にご逝去） 相続人：まつだ様含めたお子様2名様のみ 相続財産：ご自宅の土地建物、預貯金 ※株式は無し お困りごと：相続手続きの流れ、全体像についてお知りになりたい 当日はまつだ様のみでご来所予定です。 納税通知書あればお持ちいただけます。 080-5373-3086 | O26: 無料相談にお越しください | P26: 藤沢支店 | R26: 46038 | S26: 金 | T26: 10：00 | U26: 新井 | W26: Ｂ：見込み低 | X26: 戸籍や相関図、協議書まで作成済み。基本的には費用をかけず、自分でやりたい。 登記についても、法務局への相談に行っているそうです。 一部名義が入っている兄の持ち分を自分へ贈与することも検討中。 お見積りをお渡しし、終了。 | Y26: =IF(R26="","", IF(AND(R26<TODAY(),W26=""),"未入力","")) | Z26: =COUNTIF($Y$9:Y26,"未入力") -> 0
A27: =Y27&Z27 -> 0 | B27: 19 | C27: 46033 | D27: 12：30 | E27: 田中 | F27: 横浜本店 | G27: HP | H27: さほだ きよし様 | K27: 横浜 | L27: 090-2242-7573 | M27: 遺言書 | N27: 遺言書の作成についてのご相談 名前：さほだ きよし様 電話：090-2242-7573 推定相続人：2名 長女・長男 財産：土地と預貯金 ご自身のご相続が発生した際に、面倒を見てくれている長女に財産を多く渡したい。 親子での話し合いだけでもいいのか。遺言書を残した方がいいのかご相談されたいとの事。 長女に遺言書を書いてほしいといわれて、ご連絡いただいた。 ☆面談日程調整中です。 長女とご来所希望のため、改めてご連絡がきます。お電話がありましたら、日程の確定と面談場所のご案内をお願いいたします。 | Y27: =IF(R27="","", IF(AND(R27<TODAY(),W27=""),"未入力","")) | Z27: =COUNTIF($Y$9:Y27,"未入力") -> 0
A28: =Y28&Z28 -> 0 | B28: 20 | C28: 46034 | D28: 13：00 | E28: 上田 | F28: 横浜本店 | G28: HP | H28: 男性 | K28: 携帯 | L28: 090-1734-6099 | M28: 生前対策 | N28: 身元保証でどのような内容のことをやっているのか知りたいという内容で無料相談のご案内をいたしましたが、今聞けないのなら大丈夫ですとのことで終話いたしました。 | Y28: =IF(R28="","", IF(AND(R28<TODAY(),W28=""),"未入力","")) | Z28: =COUNTIF($Y$9:Y28,"未入力") -> 0
A29: =Y29&Z29 -> 0 | B29: 21 | C29: 46034 | D29: 17：45 | E29: 上田 | F29: 横浜本店 | G29: HP | H29: あとべ えみ | K29: 横浜 | L29: 090-8729-3534 | M29: 相続放棄 | N29: 被相続人：お母様（令和7年11月にご逝去、亡くなったのを知ったのは12/29） 相続人：長女、次女(相談者） 相続財産：負債（家賃滞納が２年） お困りごと：相続放棄のご検討 40年ほどお母様とは会っておらず、亡くなったのを知った日はお姉様からの連絡。 死後一ヵ月ほど経ってから発見されたそうで、警察がお姉様、お姉様から相談者に連絡があったそうです。 腐敗で部屋の片づけもあるとのこと。相談者様は生活保護を受けていて、まとめて放棄されたいとのことです。 090-8729-3534 | P29: 横浜本店 | R29: 46037 | S29: 木 | T29: 10：00 | U29: 山田 | W29: Ｓ：即受注 | X29: 母やその親族とは疎遠。姉とも折り合いが悪い。個別に放棄する。１名放棄で受任。 | Y29: =IF(R29="","", IF(AND(R29<TODAY(),W29=""),"未入力","")) | Z29: =COUNTIF($Y$9:Y29,"未入力") -> 0
A30: =Y30&Z30 -> 0 | B30: 22 | C30: 46035 | D30: 46035 | E30: 菅家 | F30: 横浜本店 | G30: HP | H30: 男性 | K30: 東京 | L30: 090-4412-2533 | M30: その他 | N30: 不動産の贈与及び売買のご相談 ご連絡先の甥にあたる方が、父親の相続で取得した不動産（複数あり）について、兄弟間での贈与または売買を検討しているとのこと。 お電話での詳細のご案内が難しいため、一度無料相談にお越しくださいとご案内。 一度検討して必要があれば連絡しますとのことでした。 | O30: 無料相談にお越しください | Y30: =IF(R30="","", IF(AND(R30<TODAY(),W30=""),"未入力","")) | Z30: =COUNTIF($Y$9:Y30,"未入力") -> 0
A31: =Y31&Z31 -> 0 | B31: 23 | C31: 46035 | D31: 15：30 | E31: 久田 | F31: 横浜本店 | G31: 過去客 | H31: うちだ ゆたか様 | K31: 横浜 | L31: 090-8478-7486 | M31: 相続手続き | N31: 被相続人：お母様（R8.1.9ご逝去） 相続人：ゆたか様 計1名様 不動産：なし 預貯金：300万円程 ※残高不明口座あり 株・有価証券：なし 2020年にお父様の相続手続きを鵜飼さんと土屋さんでご担当されたお客様です。 090-8478-7486 | O31: 無料相談にお越しください | P31: 藤沢支店 | R31: 46041 | S31: 月 | T31: 17：00 | U31: 鵜飼 | W31: Ｓ：即受注 | X31: 相続人一人。戸籍取得と預貯金解約で受注。 | Y31: =IF(R31="","", IF(AND(R31<TODAY(),W31=""),"未入力","")) | Z31: =COUNTIF($Y$9:Y31,"未入力") -> 0
A32: =Y32&Z32 -> 0 | B32: 24 | C32: 46036 | D32: 12：20 | E32: 伊藤 | F32: 横浜本店 | G32: HP | H32: 日向 勝也様（ひゅうが かつや様） | K32: 横浜 | L32: 090-2205-0378 | M32: 生前対策 | N32: ご自身の生前対策のご相談 ・・・・司法書士希望 現在、横須賀の介護付き老人ホームに入居中。 ご自身に「任意後見人」が付いている（多分司法書士）が、1年前からケンカ状態で、信頼関係ゼロ。 相談事 ・生前対策 ・後見人の変更（オーシャンには身元保証部門がある旨を、軽く伝えております） 当日は、財産の資料をお持ちいただきます。 090-2205-0378 1/26 ご体調が優れないとのことで、キャンセルになりました。（久田） | O32: 無料相談にお越しください | P32: 横浜本店 | Y32: =IF(R32="","", IF(AND(R32<TODAY(),W32=""),"未入力","")) | Z32: =COUNTIF($Y$9:Y32,"未入力") -> 0
A33: =Y33&Z33 -> 0 | B33: 25 | C33: 46036 | D33: 14：30 | E33: 久田 | F33: 横浜本店 | G33: HP | H33: すずき なおみ様 | K33: 横浜 | L33: 090-2242-7573 | M33: 生前対策 | N33: すずき様のお父様の今後発生するご相続のお手続きについてご相談されたいそうです。 推定相続人：すずき様、お子様 計2名様 不動産：ご自宅 預貯金：2000万～3000万円程 株・有価証券：なし 相続発生時の手続きの流れや遺産分割の決め方等をご相談されたいそうです。 090-2242-7573 | O33: 無料相談にお越しください | P33: 横浜本店 | R33: 46041 | S33: 月 | T33: 11：00 | U33: 新井 | W33: Ａ：見込み高 | X33: ご長女様に多く財産を残したいと希望をされており、遺言書の作成をご提案いたしました。 ただ、お父様は生前に相続人に話しをすれば、遺言書なくても大丈夫と話をしており、遺言書がない場合のリスクや相続手続きの煩雑さをきちんとお伝えし、最終的には遺言書を作成すべきということは伝わりました。 ただ、ご相続人にきちんとその旨の遺言を作成すると伝えたいとのお話なので、お伝えした後、またご連絡をいただくことになっております。 | Y33: =IF(R33="","", IF(AND(R33<TODAY(),W33=""),"未入力","")) | Z33: =COUNTIF($Y$9:Y33,"未入力") -> 0
A34: =Y34&Z34 -> 0 | B34: 26 | C34: 46036 | D34: 16：30 | E34: 安井 | F34: 横浜本店 | G34: HP | H34: やまざき やすのぶ様 | K34: 横浜 | L34: 070-6639-2925 | M34: 相続手続き | N34: 被相続人：お父様（R6.6.23ご逝去） 相続人：お母様、やまざき様含めお子様3名様 相続財産：ご自宅の土地、建物（金融資産は無し） お困りごと：ご相続人の一人である妹様と少々関係がこじれているとのこと（連絡は取れるものの、話をするとすぐ揉めてしまうそうです）。妹様はご自宅の1階で古本屋を営んでいるそうですが、やまざき様としては、今回の相続をきっかけとしてお母様の施設入居費用の捻出の為にご自宅の売却を検討しているようです。 そのこともあり、妹様とどのように話を進め、相続手続きを行うべきか悩まれているとのことです。 当日は不動産の資料をお持ちいただけます。 また、やまざき様と弟様の2名でご来所予定です。 070-6639-2925 | O34: 無料相談にお越しください | P34: 藤沢支店 | R34: 46067 | S34: 土 | T34: 10：00 | U34: 嶋津 | W34: Ａ：見込み高・後追い要 | X34: 相続登記（報酬）86,900円と経費10万円程度、家族信託（報酬）418,000円と経費10万円程度をご提案した。 一旦ご家族でご検討いただけるとのこと。 | Y34: =IF(R34="","", IF(AND(R34<TODAY(),W34=""),"未入力","")) | Z34: =COUNTIF($Y$9:Y34,"未入力") -> 0
A35: =Y35&Z35 -> 0 | B35: 27 | C35: 46037 | D35: 11：00 | E35: 菅家 | F35: 横浜本店 | G35: HP | H35: ないとう たかし様 | K35: 横浜 | L35: 080-2634-5985 | M35: その他 | N35: 本人訴訟を起こすにあたり加害者の相続人を確認するため、戸籍謄本の請求をお願いするか検討しているとのこと。 ご連絡者は犯罪に巻き込まれた被害者。加害者3名のうち1名が突然ご逝去された。 3名を被告人として同時に訴訟を起こしたいと考えており、そのために加害者の相続人を確認したい。 嶋津さんに相談をしたところ、まずは無料相談に来ていいただいて対応可否から確認が必要ではないかという話になりました。 日程調整の為保留にしておりましたが、切られてしまいました。折り返し連絡しましたがお出になりません。 もし再度ご連絡があれば、嶋津さんで調整願います。(嶋津さんに承認いただいております。) 1/15 宮田受電 日程を確認し日程調整しました。 面談当日は30分とかの短い時間で行いたい意向 また、事前に話しているから面談時にもう一度同じ話はしたくないし社内で共有されない事務所なのかと疑うので、当日は内容をある程度知っている状況でお話しするとの事でした。 尚、契約はする意向でいて、当日は印鑑を持ってくるとの事。 着手金は全額一括で払うのは不審に思ってしまうことから2回に分けて、一番初めの1回目で半分、最終の2回目で残りの報酬と実費の精算を行いたいとのこと。 こちらに関しては、「私の方からは決めることはできないので、当日説明します」とはお伝えしています。 色々と難しいとは思いますがよろしくお願いいたします。 | O35: 無料相談にお越しください | P35: 藤沢支店 | R35: 46065 | S35: 木 | T35: 13：00 | U35: 嶋津 | W35: Ｓ：即受注 | X35: 隣家の方の相続人に対し、不法行為に基づく損害賠償請求をなさりたいとのこと。 戸籍等収集手続きとして、報酬33,000円と実費がかかる旨ご説明したところ、ご依頼をいただきました。 | Y35: =IF(R35="","", IF(AND(R35<TODAY(),W35=""),"未入力","")) | Z35: =COUNTIF($Y$9:Y35,"未入力") -> 0
B36: 28 | C36: 46037 | D36: 14：45 | E36: 安井 | F36: 横浜本店 | G36: HP | H36: ほんじょう りょうこ様 | K36: 横浜 | L36: 090-6125-8236 | M36: 名義変更 | N36: 被相続人：お父様（30年前にご逝去） 相続人：お母様、ほんじょう様含めたお子様2名様で計3名様 相続財産：ご自宅のマンション お困りごと：お父様名義になっているままの自宅マンションの名義をお母様に変更されたいとのこと。 納税通知書があればお持ちいただけます。 当日は、ほんじょう様とお母様の2名でいらっしゃる予定です。 090-6125-8236 | O36: 無料相談にお越しください | P36: 横浜本店 | R36: 46049 | S36: 火 | T36: 13：00 | U36: 角田 | X36: 検討２週間。ご連絡いただける予定。 | Y36: =IF(R36="","", IF(AND(R36<TODAY(),W36=""),"未入力","")) -> 未入力 | Z36: =COUNTIF($Y$9:Y36,"未入力") -> 1
A37: =Y37&Z37 -> 1 | B37: 29 | C37: 46038 | D37: 10：15 | E37: 久田 | F37: 横浜本店 | G37: HP | H37: おおや しげただ様 | K37: 横浜 | L37: 090-2723-3358 | M37: 相続手続き | N37: 被相続人：お母様（R7.3.1） 相続人：おおや様 1名様 不動産：ご自宅 大和市 預金・株・有価証券等はなし 相続登記の手続きについてお知りなりたいそうです。 090-2723-3358 | O37: 無料相談にお越しください | P37: 藤沢支店 | R37: 46046 | S37: 土 | T37: 10：00 | U37: 藤田（早） | W37: Ｓ：即受注 | X37: お母様の相続に際し、必要書類等をご案内したところ、結果即受注となりました。 | Y37: =IF(R37="","", IF(AND(R37<TODAY(),W37=""),"未入力","")) | Z37: =COUNTIF($Y$9:Y37,"未入力") -> 1
A38: =Y38&Z38 -> 1 | B38: 30 | C38: 46039 | D38: 9：30 | E38: 安井 | F38: 横浜本店 | G38: HP | H38: あんどう ふみこ様 | K38: 横浜 | L38: 090-1103-1265 | M38: 生前対策 | N38: ★生前対策についてのご相談 対象者：お父様、お母様 相続財産：お父様→不動産及び金融資産、お母様→金融資産のみ お困りごと：現状はお二人ともお元気だそうですので、今のうちに生前対策について確認しておきたい。相続税対策についても聞きたいとのこと。 090-1103-1265 | O38: 無料相談にお越しください | P38: 横浜本店 | R38: 46042 | S38: 火 | T38: 18：30 | U38: 新井 | W38: Ｂ：見込み低 | X38: 今まで自分がしてきた生前対策が間違ってないかの確認でした。 遺言書の公正証書への書き換えを提案し、終了としています。 | Y38: =IF(R38="","", IF(AND(R38<TODAY(),W38=""),"未入力","")) | Z38: =COUNTIF($Y$9:Y38,"未入力") -> 1
A39: =Y39&Z39 -> 1 | B39: 31 | C39: 46039 | D39: 14：30 | E39: 宮田 | F39: 横浜本店 | G39: HP | H39: 女性 | K39: 横浜 | L39: 090-7187-5214 | M39: 生前対策 | N39: 地方に土地建物があり、他ではお店をやっている。預金は少ない 家族構成としては夫婦と子ども2人 まだ健康なうちに今後のことについて考えておきたい。 地方の土地建物は買いたいと言っているところがある。 土地は奥様名義、建物は夫婦で共有名義 現状の価格についてもお話しすることが可能とお話ししたところ、興味があるっぽく食いついてきました。 面談については予約とのことで、日程調整して再度折り返しいただくことになりました。 場所は横浜が良いとの事で道についてもご説明しております。 ※名前についてはお聞きすることができずに申し訳ございません。 | O39: 無料相談にお越しください | P39: 横浜本店 | Y39: =IF(R39="","", IF(AND(R39<TODAY(),W39=""),"未入力","")) | Z39: =COUNTIF($Y$9:Y39,"未入力") -> 1
A40: =Y40&Z40 -> 1 | B40: 32 | C40: 46041 | D40: 9：50 | E40: 久田 | F40: 横浜本店 | G40: HP | H40: くまがい みよこ様 | K40: 茅ヶ崎市 | L40: 090-6544-1959 | M40: 遺言書 | N40: 遺言者：くまがい様のご両親 お父様は寝たきりの状態だが、意思判断能力はあるそうです。 既に遺言書の内容は決まっていて、作成の仕方等をご相談されたいそうです。 当日は、くまがい様お一人でご来所されます。 （ご契約者様がご両親であること、意思確認のために直接話す必要がある旨はお伝え済みです。） 090-6544-1959 | O40: 無料相談にお越しください | P40: 藤沢支店 | R40: 46042 | S40: 火 | T40: 10：00 | U40: 新井 | W40: Ａ：見込み高・後追い要 | X40: 父母の遺言書作成の希望がございました。金額の心配をしておりましたが、想定よりも金額が低く、依頼したいと話をしていましたが、現在旦那様のお母様が今月又は来月には亡くなりそうで、バタバタしているので、依頼をするのは少し後になりそうとのこと。 | Y40: =IF(R40="","", IF(AND(R40<TODAY(),W40=""),"未入力","")) | Z40: =COUNTIF($Y$9:Y40,"未入力") -> 1
A41: =Y41&Z41 -> 1 | B41: 33 | C41: 46041 | D41: 0.39236111 | E41: 嶋津 | F41: 横浜本店 | G41: HP | H41: ねぎし としこ様 | L41: 090-9146-7787 | M41: 生前対策 | N41: ★生前対策についてのご相談 対象者：お母様 相続財産：お母様→不動産 zoomにて相談に乗ってもらいたいとのこと | O41: 無料相談にお越しください | Y41: =IF(R41="","", IF(AND(R41<TODAY(),W41=""),"未入力","")) | Z41: =COUNTIF($Y$9:Y41,"未入力") -> 1
A42: =Y42&Z42 -> 1 | B42: 34 | C42: 46041 | D42: 11：00 | E42: 安井 | F42: 横浜本店 | G42: HP 過去客 | H42: ほりの ゆり様 | K42: 横浜 | L42: 090-4172-9317 | M42: 名義変更 | N42: ★令和7年8月に齋藤さん／宮田さんで担当したお客様のお姉様です。 田舎の土地が残っており、改めて相談したいとのこと。 被相続人：後藤光子様（R7.7.21ご逝去） 相続人：ほりの様、後藤篤様（前回のCL）の計2名 相続財産：宮城県にある土地の持分のみ お困りごと：全て手続きは終わったと思っていたが、上記土地の存在を役所から聞いたのでそれも名義変更しなければとご連絡いただきました。篤様ともお話いただいたうえで当該土地の相続人はほりの様になったということで、今回の契約者はほりの様になる予定です。 また、当日は前回の手続資料一式をお持ちいただける予定です。 希望日時に齋藤さんで調整するのが難しかった為角田さんで入れました。よろしくお願いします。 090-4172-9317 | O42: 無料相談にお越しください | P42: 横浜本店 | R42: 46048 | S42: 月 | T42: 13：00 | U42: 角田 | W42: Ｓ：即受注 | X42: 過去客。相続登記で受注。 | Y42: =IF(R42="","", IF(AND(R42<TODAY(),W42=""),"未入力","")) | Z42: =COUNTIF($Y$9:Y42,"未入力") -> 1
A43: =Y43&Z43 -> 1 | B43: 35 | C43: 46041 | D43: 13：30 | E43: 上田 | F43: 横浜本店 | G43: HP | H43: 男性 | L43: 080-6860-0513 | M43: 遺言書 | N43: お父様の遺言書作成のお問い合わせ 意思、判断能力は問題ないが、末期がんのため様態が変わる恐れあり。 危急時遺言も視野にいれている。 お父様のお話の上で再度お電話いただけます。 | O43: 無料相談にお越しください | Y43: =IF(R43="","", IF(AND(R43<TODAY(),W43=""),"未入力","")) | Z43: =COUNTIF($Y$9:Y43,"未入力") -> 1
A44: =Y44&Z44 -> 1 | B44: 36 | C44: 46041 | D44: 15：30 | E44: 久田 上村？ 上田？ | F44: 横浜本店 | G44: HP | H44: いづか よしこ 契約者は もりかわ ふみこ 様 （いづか様の母） | L44: 080-6723-7852 | M44: 遺言書 | N44: 遺言者：森川文子様 （お母様（現在95歳）） お母様は、現在横浜市港北区の施設にお住まいで、意思判断能力はあり、字も書けるとのことです。 遺言書の作成をご希望されております。 ☆無料相談にはお電話口様お一人でご来所いただき、実際にご契約する運びとなれば、施設に直接伺うorZoomで意思確認をさせていただく流れをお伝えいたしました。現在はご検討中です。 | O44: 無料相談にお越しください | P44: 横浜本店 | R44: 46045 | S44: 金 | T44: 13：00 | U44: 梅澤 | W44: Ｓ：戻り受注 | X44: 相見積もり。 弟と連絡が取れず、このままもし母が亡くなると相続手続きが進まなくなるので、遺言書を作りたいとの希望。母の施設での出張作成を希望している。料金表を提示するも、他社にも聞いてみたいとの事で、相見積もりとなった。佳子様は元銀行員。 1/27戻り受注（契約者：森川文子様） | Y44: =IF(R44="","", IF(AND(R44<TODAY(),W44=""),"未入力","")) | Z44: =COUNTIF($Y$9:Y44,"未入力") -> 1
A45: =Y45&Z45 -> 1 | B45: 37 | C45: 46041 | D45: 0.86805556 | E45: 石井 | F45: 横浜本店 | G45: HP | H45: いとう のりひろ | K45: 横浜 | L45: 090-6471-9618 | M45: 遺言書 | N45: 遺言者：お母様（現在85歳） 遺言者：母 受遺者：長男、次男(相談者） 財産としては、不動産、預金がある。 長男はタイに住んでいて、戻ってこなさそう？なので預金、次男には不動産をという内容で作成をご検討されているとのことです。 お母様の判断能力は問題ないが、昨年から骨折等で介護施設にご入所されているとのこと。 | O45: 無料相談にお越しください | P45: 横浜本店 | R45: 46053 | S45: 土 | T45: 16：00 | U45: 新井 | W45: Ｓ：戻り受注 | X45: 公正証書遺言で受注 | Y45: =IF(R45="","", IF(AND(R45<TODAY(),W45=""),"未入力","")) | Z45: =COUNTIF($Y$9:Y45,"未入力") -> 1
A46: =Y46&Z46 -> 1 | B46: 38 | C46: 46042 | D46: 15：30 | E46: 宮田 | F46: 横浜本店 | G46: HP | H46: すぎやま たかし | K46: 横浜 | L46: 090-4207-4973 | M46: 遺言書 | N46: ・相談者様氏名：杉山 隆 様 (すぎやま たかし) ・相談者TEL：090-4207-4973 (内容) ■相談者の叔父・叔母ご夫婦両名の生前対策（遺言書）、相続の相談。 ・叔父(92歳)、叔母(93歳)、子どもなし ■資産 ・不動産：大船に戸建て(土地建物)あり。叔父叔母夫婦で1/2の割合で共有している。 ※大船駅付近を指しているかもしれませんので、所在地は横浜市栄区の可能性があります。 ・金融資産：叔父／2000万円ほど、叔母／3000万円ほどの金融資産あり。 ※確実ではなく曖昧なため近日中に再度確認する予定とのこと ■相談事 ・12月～1月に叔母がご入院をされると相談者に連絡が入り、叔父も足が悪い状況。 そのため、今後はもう長くないと悟って、終活をしてるか確認したところしてなかった。 よって、今回の相談を考えるに至ったご様子。 エンディングノートを書いた方が良いと提案済み。 ・エンディングノートを書かれてみてはと伝えたところ、寄附にも興味があるような反応。 できれば面談時に寄附先の紹介もお願いいたします。 ・本人は来た方が良いのか聞かれたところ、 「足が悪いようですし、ご面談の際はすぎやま様お一人で問題ございません。」 とお伝えしております。そのため、すぎやま様1名でお越しになるかと思います。 1/25 すぎやま様よりTELあり。当事者の方が入院してしまったそうで、一旦予約はキャンセル。 またご状況が落ち着かれたら、改めてご連絡いただけるとのこと。（安井） | O46: 無料相談にお越しください | P46: 横浜本店 | Y46: =IF(R46="","", IF(AND(R46<TODAY(),W46=""),"未入力","")) | Z46: =COUNTIF($Y$9:Y46,"未入力") -> 1
A47: =Y47&Z47 -> 1 | B47: 39 | C47: 46042 | D47: 18：30 | E47: 安井 | F47: 横浜本店 | G47: HP | H47: あんざい たいが様 | K47: 横浜 | L47: 080-7694-3257 | M47: 相続手続き | N47: 1/24 日程変更ご希望のご連絡あり再度調整いたしました。（上田） 被相続人：お父様（R7.1.4ご逝去、中国籍） 相続人：奥様（中国籍）、あんざい様（前妻のお子様だそうです、前妻もあんざい様も中国籍） 相続財産：日光市にある自宅の土地・建物、預貯金、自動車1台 お困りごと：相続手続きの全体像についてお聞きになりたいそうです。お父様とあんざい様は2年に1回会うかどうかの仲だったそうで、上記財産はあくまでもご自身が把握している分と仰っていました。 メールアドレス→sbsg.love@gmail.com 電話番号→080-7694-3257 | O47: 無料相談にお越しください | P47: 横浜本店 | Q47: Zoomでの面談希望 | R47: 46051 | S47: 木 | T47: 12：30 | U47: 新井 | W47: Ｂ：見込み低 | X47: 被相続人：中国籍※香港、相続人：全員中国籍※香港と大連の手続きとなります。 金融の財産調査はお客様が行う予定で、その他の資料収集、お手紙遺産分割協議書等書類作成、登記などをお願いしたいと思っている。 一度資料収集については、他行政書士と連携して行うことになる旨をお伝えし、お見積りをご提示することにしています。 | Y47: =IF(R47="","", IF(AND(R47<TODAY(),W47=""),"未入力","")) | Z47: =COUNTIF($Y$9:Y47,"未入力") -> 1
A48: =Y48&Z48 -> 1 | B48: 40 | C48: 46043 | D48: 9：30 | E48: 小泉 | F48: 横浜本店 | G48: HP | H48: 男性 | K48: 静岡 | L48: 090-3546-3595 | M48: その他 | N48: 報酬額の計算方法についてのご質問でした。 複数社比較されており、詳細なヒアリングはできませんでした。 | O48: 無料相談にお越しください | Y48: =IF(R48="","", IF(AND(R48<TODAY(),W48=""),"未入力","")) | Z48: =COUNTIF($Y$9:Y48,"未入力") -> 1
A49: =Y49&Z49 -> 1 | B49: 41 | C49: 46045 | D49: 15：30 | E49: 久田 | F49: 横浜本店 | G49: HP | H49: おかえ たかひろ様 | K49: 横浜 | L49: 090-6166-3152 | M49: 相続放棄 | N49: 被相続人：お姉様（R8.1.1ご逝去） 相続人：お母様 1/20に警察よりお姉様がご逝去された旨のご連絡を受けたそうです。 相続人であるお母様については、現在認知症を患っておられ、判断能力がない状態であるとのことです。 また、お母様の財産につきましては、社会福祉法人が管理しているとのことです。 「お母様にはお姉様がご逝去された事実をお伝えしたくない」とのご意向がございましたが、相続放棄の手続きを進める上で、当該事実をお伝えしないことは難しい旨をご説明いたしました。 あわせて、お母様につきましては相続放棄手続きを行うため、成年後見人の選任が必要となる可能性がある旨をご説明いたしましたところ、後見人選任に要する費用が、お母様の財産から支払われるのかご懸念を示されておりました。 また、お母様による相続放棄が完了した後、おかえ様ご自身につきましても相続放棄を行いたいとのご意向を示されております。 ☆一度社会福祉法人にお電話されてから再度ご連絡くださるとのことです。 | O49: 無料相談にお越しください | Y49: =IF(R49="","", IF(AND(R49<TODAY(),W49=""),"未入力","")) | Z49: =COUNTIF($Y$9:Y49,"未入力") -> 1
A50: =Y50&Z50 -> 1 | B50: 42 | C50: 46045 | D50: 16：00 | E50: 安井 | F50: 横浜本店 | G50: 過去客 | H50: うえだ ひろお様 | K50: 横浜 | L50: 080-5645-5433 | M50: 遺言書 | N50: 数年前に山田先生にて、叔父様と叔母様の遺言書作成を担当いただいたお客様です。 叔父様のお名前→さいとう たつお様 叔母様のお名前→さいとう ひで様 案件を検索しましたが見つけられませんでした・・・ うえだ様の大叔母様（お祖父様の妹様だそう）の遺言書作成に関するご相談。 既に自筆証書遺言がありますが、それを公正証書で作り直したいとのこと。 大叔母様は現在老人ホームにご入居中ですが、外出はできる為公証役場に行くこともできるそうです。 当日はその自筆証書遺言の内容が分かるものをお持ちいただきます。 080-5645-5433 1/28 うえだ様よりTELあり。 ご本人が自分で相談に行きたいとのご意向に変わったようで、一旦リスケとなりました。（安井） | O50: 無料相談にお越しください | P50: 横浜本店 | Y50: =IF(R50="","", IF(AND(R50<TODAY(),W50=""),"未入力","")) | Z50: =COUNTIF($Y$9:Y50,"未入力") -> 1
A51: =Y51&Z51 -> 1 | B51: 43 | C51: 46046 | D51: 9：20 | E51: 宮田 | F51: 横浜本店 | G51: HP | H51: まつだ みちこ様 | K51: 横浜 | L51: 090-7187-5214 | M51: その他 | N51: 【相談者】まつだみちこ様 【TEL】090-7187-5214 【財産】 預貯金、不動産 【相談内容】 誰も亡くなっていないが相続について知りたい 気になっているのは、土地の金額で、当日は納税通知書等持ってきてくれるとの事。 預貯金に関しては自分で把握できるのでそこまで気になっていない。 均等に分けたいとの事で土地の金額が気になっているので、そこを伝えることくらいになりそうです。 | O51: 無料相談にお越しください | P51: 横浜本店 | R51: 46055 | S51: 月 | T51: 10：00 | U51: 花井 | W51: Ｂ：見込み低 | X51: 相談者：松田道子、松田健司2名にて来所。 自宅、マンション、高知県のアパート2棟経営と相続財産が多く、不動産の比率も高い為、生前対策について相談を受ける。 今後、息子・娘の2名に平等に分割でき、なおかつ相続税が少なくすむような分け方を気にしている。 当初、一方の死亡時に配偶者控除でまとめて、それぞれに平等な分け方で相続するよう遺言を残そうとしていたが、 相続税がトータルで大きくなる可能性、一方の死亡後にもう一方の判断能力が残っていない可能性を指摘し、 検討となる。 | Y51: =IF(R51="","", IF(AND(R51<TODAY(),W51=""),"未入力","")) | Z51: =COUNTIF($Y$9:Y51,"未入力") -> 1
A52: =Y52&Z52 -> 1 | B52: 44 | C52: 46046 | D52: 10：00 | E52: 宮田 | F52: 横浜本店 | G52: HP | H52: 匿名 | L52: 090-5692-3964 | M52: その他 | N52: 叔母の相続についての後見人（司法書士）が行っていたが、連絡もなく2,3カ月経つ 手続きの内容やどういった状況を聞いても教えてくれない。 叔母の兄、叔母、叔母の妹の三兄弟だが兄と妹はすでに亡くなっている。 妹の子がお電話口様 相続人は6名いるとの事 不動産はない お名前を聞きましたが「匿名でごめんなさい」となりました。 もう一度司法書士に話してみて、不安だったらいろいろなとこに相談してみるとの事でした。 | Y52: =IF(R52="","", IF(AND(R52<TODAY(),W52=""),"未入力","")) | Z52: =COUNTIF($Y$9:Y52,"未入力") -> 1
A53: =Y53&Z53 -> 1 | B53: 45 | C53: 46046 | D53: 0.625 | E53: 上田 | F53: 横浜本店 | G53: HP | H53: やました ひろゆき | K53: 東京 | L53: 090-7851-1467 | M53: その他 | N53: 2年前にお母様がお亡くなりになられており、公正証書遺言が残されていた。 遺言執行者としては妹の友人がついていた。 全ての手続きは一旦全て完了したが、目録が送られてきていないことで再度目録作成からやり直しをしようとしている。 受遺者は子どもの三名様 目録がないことによる損害は調べているとのこと 2/6 9:00 受電(小川) 急用のためリスケしたいとのこと、日程に関してはまたお客様からご連絡くださるようです。 | O53: 無料相談にお越しください | P53: 渋谷支店 | Y53: =IF(R53="","", IF(AND(R53<TODAY(),W53=""),"未入力","")) | Z53: =COUNTIF($Y$9:Y53,"未入力") -> 1
A54: =Y54&Z54 -> 1 | B54: 46 | C54: 46048 | D54: 10：00 | E54: 渡部 | F54: 横浜本店 | G54: メール | H54: さかもと かずひろ | L54: 090-9808-3275 | M54: 相続放棄 | N54: 【お問い合わせの内容】 相続放棄について 【お問い合わせの詳細】 坂本 和大と申します。 以前、坂本貴範逝去後の相続放棄案件にて、 蔭山先生・上原先生にお世話になりました。 この度、母・坂本由美子が2026年1月17日に逝去し、母の生前債務および母が関与した父名義借金について、父と協議のうえ相続放棄を行う方針としました。 母名義債務は3件（計約108万円）、父名義債務はUCカード約68万円判明しています。 相続放棄手続、父名義債務の整理・減額交渉、必要書類、費用・スケジュールにつきご相談したく存じます。 土・日が空いておりますが、早々にご相談できればと存じますので、2月5日や2月12日も可能です。 【お名前】 坂本 和大 【フリガナ】 サカモト カズヒロ 【連絡先メールアドレス】 kazu.1202.saka@gmail.com 【連絡先電話番号】 090-9808-3275 【ご住所情報】 郵便番号：223-0052 神奈川県 横浜市港北区綱島東4-9-5 2F | O54: 無料相談にお越しください | P54: 藤沢支店 | Q54: 相続放棄 債務整理 | R54: 46065 | S54: 木 | T54: 10：00 | U54: 森谷 | W54: Ｓ：即受注 | X54: 被相続人の相続放棄と相続人である夫名義で借り入れた債務の整理 | Y54: =IF(R54="","", IF(AND(R54<TODAY(),W54=""),"未入力","")) | Z54: =COUNTIF($Y$9:Y54,"未入力") -> 1 | AB54: ：
A55: =Y55&Z55 -> 1 | B55: 47 | C55: 46050 | D55: 13：30 | E55: 久田 | F55: 横浜本店 | G55: ＨＰ | H55: やすさか ともこ様 | K55: 藤沢 | L55: 0466-34-8125 | M55: 相続税申告 | N55: 被相続人：お父様（R7.11.6ご逝去） 相続人：やすさか様、ご長男様 計2名様 【相続財産】 不動産：ご自宅（藤沢市）2100万円 預貯金：2000万円、現金1200万円 株・有価証券なし 確定申告の還付金を受け取っていなかった。準確定申告が必要かも気になる。 財産の分割方針にも悩まれているご様子でした。 | O55: 無料相談にお越しください | P55: 藤沢支店 | R55: 46052 | S55: 金 | T55: 10：00 | U55: 藤田（早） | W55: Ｓ：即受注 | X55: お父様の相続手続き。 相続税申告サポート受任いたしました。 努めてまいります。 | Y55: =IF(R55="","", IF(AND(R55<TODAY(),W55=""),"未入力","")) | Z55: =COUNTIF($Y$9:Y55,"未入力") -> 1
A56: =Y56&Z56 -> 1 | B56: 48 | C56: 46051 | D56: 10：30 | E56: 久田 | F56: 横浜本店 | G56: ＨＰ | H56: しばた なおみ様 | K56: 藤沢 | L56: 0466-81-3882 | M56: 相続放棄 | N56: 被相続人：しばた様のお兄様 お兄様は離婚されており、お子様が二人いらっしゃいますが、いずれも既に相続放棄をされています。 その結果、お母様のもとへ、お兄様の負債に関する請求が届いたとのことです。 負債があることを知ったのは先週であり、それまでは把握されていなかった状況です。 現在お母様は認知症のため判断能力がなく、自署もできない状態とのことです。 お父様は既にご逝去されているそうです。 | O56: 無料相談にお越しください | P56: 藤沢支店 | R56: 46058 | S56: 木 | T56: 14：00 | U56: 嶋津 | V56: 栗田 | W56: Ｓ：即受注 | X56: 柴田博光様の相続放棄。 母柴田トミ様、妹柴田直美様２名様の手続きのご依頼をいただきました。 | Y56: =IF(R56="","", IF(AND(R56<TODAY(),W56=""),"未入力","")) | Z56: =COUNTIF($Y$9:Y56,"未入力") -> 1
A57: =Y57&Z57 -> 1 | B57: 49 | C57: 46051 | D57: 11：58 | E57: 山﨑 | F57: 横浜本店 | G57: HP | H57: 女性（名前教えてくれず） | K57: 東神奈川 | L57: 090-8851-9765 | M57: 名義変更 | N57: 別荘を買った時の名義変更はいくらでやってくれるの？ | O57: 申請の内容によって異なるので、よろしければ一度無料相談にお越しください。 | Y57: =IF(R57="","", IF(AND(R57<TODAY(),W57=""),"未入力","")) | Z57: =COUNTIF($Y$9:Y57,"未入力") -> 1
A58: =Y58&Z58 -> 1 | B58: 50 | C58: 46051 | D58: 11：50 | E58: 菅家 | F58: 横浜本店 | G58: ＨＰ | H58: 男性 | K58: 福岡 | L58: 090-3323-0561 | M58: その他 | N58: 今後発生するご相続についてのご相談 ご連絡者様のお姉様が8年ほど前に公正証書遺言を作成したと。 お姉様には配偶者や子はおらず、親及び祖父母も他界しているため法定相続人はご連絡者様のみ。 公正証書遺言で全てをご連絡者様に相続させる旨の記載があったが、負債とかも多いため放棄をしたいができるのかとういうご相談。 公正証書遺言があったとしても、相続放棄のお手続きは死亡を知った日から3か月以内であれば可能であることお伝えし、終話しております。 | Y58: =IF(R58="","", IF(AND(R58<TODAY(),W58=""),"未入力","")) | Z58: =COUNTIF($Y$9:Y59,"未入力") -> 1
B59: 51 | C59: 46051 | D59: 4：30 | E59: 宮田 | F59: 横浜本店 | G59: ＨＰ | H59: たかとり ひろし様 | K59: 横浜 | L59: 090-4678-8720 | M59: 相続手続き | N59: 2012.3に祖母（たかとりよしえ様）の相続手続きでお世話になった過去客様です。 担当者不明 【相談者】たかとり ひろし様 【TEL】090-4678-8720 【被相続人】お父様 【相続人】配偶者、ご子息様2名の計3名（ひろし様はご長男様） 【相続財産】 不動産：自宅の土地建物 ＠横浜市鶴見区 金融資産：約2千万円 有価証券：なし その他：なし 【遺言書】なし 【相続税】なし 【相談内容】 以前祖母のお手続きでお世話になったので、またお願いしたいとのこと。 面談の際は手続きの流れを聞いて見積書を見て依頼するかの判断をする。 当日は固定資産税の納税通知書等を持ってきてくださるとの事でした。 面談よろしくお願いいたします。 | O59: 無料相談にお越しください | P59: 横浜本店 | R59: 46060 | S59: 土 | T59: 10：00 | U59: 新井 | W59: Ａ：見込み高 | X59: 新築不動産資金の贈与の途中でなくなってしまった、相続税の課税価格に含めるかも含め、税理士と連携して手続きを進めていく必要有。 上記、課税価格に含めるかどうかで申告が必要になるかも変わる。 一旦家族会議の上、今月中にはご回答いただけるとのこと。 | Y59: =IF(R59="","", IF(AND(R59<TODAY(),W59=""),"未入力","")) | Z59: =COUNTIF($Y$9:Y59,"未入力") -> 1
A60: =Y60&Z60 -> 1 | B60: 52 | C60: 46052 | D60: 11：19 | E60: 宮田 | F60: 横浜本店 | G60: ＨＰ | H60: まつむら ゆきえ様 | K60: 横浜 | L60: 090-7283-8927 | M60: 相続手続き | N60: 【相談者】まつむらゆきえ様 【TEL】090-7283-8927 【被相続人】お父様（亡2024.4？）この間三回忌をやったけど曖昧 【相続人】お母様、お兄様、ゆきえ様 の計3名 【相続財産】 不動産：土地（お父様名義）、建物（お兄様名義）※建物は相続財産じゃないです。 【相談内容】 この間役所に行ったら、三年以内に手続きをしないといけないと言われた これについてわからないので教えてほしい 尚、「90分以内なら無料ですよね？」と念押しで聞かれたので、無料相談で終わる可能性があります。 面談よろしくお願いいたします。 | O60: 無料相談にお越しください | P60: 横浜本店 | R60: 46067 | S60: 土 | T60: 10：00 | U60: 馬場 | W60: Ｂ：見込み低 | X60: お父様の相続のご相談。 登記のご相談でした。 恐らくご依頼になるかと思いますが、お時間かかりそうです。 | Y60: =IF(R60="","", IF(AND(R60<TODAY(),W60=""),"未入力","")) | Z60: =COUNTIF($Y$9:Y60,"未入力") -> 1
A61: =Y61&Z61 -> 1 | B61: 53 | C61: 46052 | D61: 15：30 | E61: 安井 | F61: 横浜本店 | G61: HP | H61: おおたけ様 | K61: 前橋 | L61: 090-2424-9357 | M61: 生前対策 | N61: 当事者：叔母様（埼玉県在住、70代） 財産：不動産（ご自宅） お困りごと：おおたけ様が群馬県在住の為、叔母様の生前対策についてご心配でご連絡下さったとのこと。 叔母様はお子様がおらず、配偶者は既にご逝去されているそうです。 無料相談はおおたけ様のみでも大丈夫ですが、実際に遺言書や契約書等を作成するには叔母様のご意思の確認が不可欠である旨お伝えしたところ、ご一緒にZoom面談される方針で検討いただけることになりました。 叔母様にお話いただいた上で、改めてご連絡いただけます。 | O61: 無料相談にお越しください | P61: その他 | Q61: Zoomでの面談希望 | Y61: =IF(R61="","", IF(AND(R61<TODAY(),W61=""),"未入力","")) | Z61: =COUNTIF($Y$9:Y61,"未入力") -> 1
A62: =Y62&Z62 -> 1 | B62: 54 | C62: 46053 | D62: 11：40 | E62: 久田 | F62: 横浜本店 | G62: HP | H62: すだ めぐみ様 | K62: 横浜 | L62: 090-2174-4861 | M62: 相続手続き | N62: 被相続人：お母様（R7.11.19にご逝去） 相続人：すだ様、妹様2名 計3名様 【相続財産】不動産のみ 建物：祖父の名義のままため、名義変更をしたい。 土地：地主から借りている。（契約書有り） 以下契約内容です。 ・お母様がご逝去されてから3か月以内に土地を地主に返す。 →2月19日に土地を返さなければならない。 ・返した後は、10年間は賃料を払って住むことができる。 登記手続きの流れや、地主に土地を返すまでの流れについて知りたいそうです。 当日は、建物の納税通知書と地主との契約書をお持ちいただけます。 | O62: 無料相談にお越しください | P62: 横浜本社 | R62: 46055 | S62: 月 | T62: 10：00 | U62: 梅澤 | W62: Ｄ：対応不可能 | X62: お母様がご逝去されてから3か月以内に土地を地主に返すという契約になっているが、地主よりこのまま土地を貸してもいいという話がきている。ただ、そのためには、現在建物の所有者がお母様の父名義のままなので、相続登記を要求されている。地主側から指定された司法書士に、須田様側から書類を送付済。1月中旬に司法書士から「書類を受け取りました」という連絡があったが、その後連絡がなく、2月には土地を返さなければならないのかと心配になってオーシャンに相談に来たという。 要するに、どんな状況でも3ヶ月後には必ず土地を返却しなければならないと思い込んでいたらしい。 そのため、こちらからは、その司法書士にこちらから連絡を入れて、今どのような状況なのかを確認するように伝えた。 | Y62: =IF(R62="","", IF(AND(R62<TODAY(),W62=""),"未入力","")) | Z62: =COUNTIF($Y$9:Y62,"未入力") -> 1
A63: =Y63&Z63 -> 1 | B63: 56 | C63: 46045 | D63: 11：00 | E63: 角田 | F63: 横浜本店 | G63: HP | H63: おがわ だん様 | K63: 海外在住（スゥエーデン） | M63: 相続手続き | N63: 去年11月に母親がスウェーデンにて息を引き取りました。 （死亡届は大使館に提出済み） 子供が4人いて、二重国籍・日本国籍・多国籍などの兄弟です。 母親は日本国籍で、 西東京出身、日本に不動産を一つ（実家）を所有しております。 母親の遺言（筆記は無し）は妹に不動産を渡しタイトの事で、兄弟もそれに了承しています。 妹は日本国籍です。 兄弟は皆現在スウェーデン住まい（日本には頻繁に帰国してます）です。 相続の手続きなどをお手伝い出来ないかのお問い合わせです。 | O63: 無料相談にお越しください | P63: その他 | Q63: Zoomでの面談希望 | R63: 46055 | S63: 月 | T63: 16：00 | U63: 角田 | W63: Ｂ：見込み低 | X63: 相続人全員が海外在住。日本の不動産の手続きと預貯金の解約。相続税や海外在住者の相続手続きを説明。249.000円と解約１行25000円でご提案。3月末から４月末に日本に来るのでその際に契約できればとお話し。 まずは他相続人と共有して以来の有無を返答いただけるとのこと。連絡待ち。 | Y63: =IF(R63="","", IF(AND(R63<TODAY(),W63=""),"未入力","")) | Z63: =COUNTIF($Y$9:Y63,"未入力") -> 1
B64: 57
B65: 58
A66: =Y66&Z66 -> 1 | B66: 59 | Y66: =IF(R66="","", IF(AND(R66<TODAY(),W66=""),"未入力","")) | Z66: =COUNTIF($Y$9:Y66,"未入力") -> 1
B67: 60 | Y67: =IF(R67="","", IF(AND(R67<TODAY(),W67=""),"未入力","")) | Z67: =COUNTIF($Y$9:Y67,"未入力") -> 1
A68: =Y68&Z68 -> 1 | B68: 61 | Y68: =IF(R68="","", IF(AND(R68<TODAY(),W68=""),"未入力","")) | Z68: =COUNTIF($Y$9:Y68,"未入力") -> 1
A69: =Y69&Z69 -> 1 | B69: 62 | Y69: =IF(R69="","", IF(AND(R69<TODAY(),W69=""),"未入力","")) | Z69: =COUNTIF($Y$9:Y69,"未入力") -> 1
A70: =Y70&Z70 -> 1 | B70: 63 | Y70: =IF(R70="","", IF(AND(R70<TODAY(),W70=""),"未入力","")) | Z70: =COUNTIF($Y$9:Y70,"未入力") -> 1
A71: =Y71&Z71 -> 1 | B71: 64 | Y71: =IF(R71="","", IF(AND(R71<TODAY(),W71=""),"未入力","")) | Z71: =COUNTIF($Y$9:Y71,"未入力") -> 1
A72: =Y72&Z72 -> 1 | B72: 65 | Y72: =IF(R72="","", IF(AND(R72<TODAY(),W72=""),"未入力","")) | Z72: =COUNTIF($Y$9:Y72,"未入力") -> 1
A73: =Y73&Z73 -> 1 | B73: 66 | Y73: =IF(R73="","", IF(AND(R73<TODAY(),W73=""),"未入力","")) | Z73: =COUNTIF($Y$9:Y73,"未入力") -> 1
A74: =Y74&Z74 -> 1 | B74: 67 | Y74: =IF(R74="","", IF(AND(R74<TODAY(),W74=""),"未入力","")) | Z74: =COUNTIF($Y$9:Y74,"未入力") -> 1
A75: =Y75&Z75 -> 1 | B75: 68 | Y75: =IF(R75="","", IF(AND(R75<TODAY(),W75=""),"未入力","")) | Z75: =COUNTIF($Y$9:Y75,"未入力") -> 1
A76: =Y76&Z76 -> 1 | B76: 69 | Y76: =IF(R76="","", IF(AND(R76<TODAY(),W76=""),"未入力","")) | Z76: =COUNTIF($Y$9:Y76,"未入力") -> 1
A77: =Y77&Z77 -> 1 | B77: 70 | Y77: =IF(R77="","", IF(AND(R77<TODAY(),W77=""),"未入力","")) | Z77: =COUNTIF($Y$9:Y77,"未入力") -> 1
A78: =Y78&Z78 -> 1 | B78: 71 | Y78: =IF(R78="","", IF(AND(R78<TODAY(),W78=""),"未入力","")) | Z78: =COUNTIF($Y$9:Y78,"未入力") -> 1
A79: =Y79&Z79 -> 1 | B79: 72 | Y79: =IF(R79="","", IF(AND(R79<TODAY(),W79=""),"未入力","")) | Z79: =COUNTIF($Y$9:Y79,"未入力") -> 1
... A199: =Y199&Z199 -> 1 | B199: 192 | Y199: =IF(R199="","", IF(AND(R199<TODAY(),W199=""),"未入力","")) | Z199: =COUNTIF($Y$9:Y199,"未入力") -> 1
D206: 総計 | E206: 横浜本店 | F206: 藤沢支店 | G206: 渋谷支店 | H206: お客様先 | I206: パートナー先 | J206: =設定用!F7 -> 藤沢支店
B207: 面談対応件数 | D207: =SUM(E207:I207) -> 32 | E207: =COUNTIFS($P$9:$P$199,E$206,$W$9:$W$199,"<>") -> 18 | F207: =COUNTIFS($P$9:$P$199,F$206,$W$9:$W$199,"<>") -> 11 | G207: =COUNTIFS($P$9:$P$199,G$206,$W$9:$W$199,"<>") -> 3 | H207: =COUNTIFS($P$9:$P$199,H$206,$W$9:$W$199,"<>") -> 0 | I207: =COUNTIFS($P$9:$P$199,I$206,$W$9:$W$199,"<>") -> 0 | J207: =COUNTIFS($P$9:$P$199,J$206,$W$9:$W$199,"<>") -> 11
B208: 即受注件数 | D208: =SUM(E208:I208) -> 12 | E208: =COUNTIFS($P$9:$P$199,E$206,$W$9:$W$199,$O$2) -> 4 | F208: =COUNTIFS($P$9:$P$199,F$206,$W$9:$W$199,$O$2) -> 8 | G208: =COUNTIFS($P$9:$P$199,G$206,$W$9:$W$199,$O$2) -> 0 | H208: =COUNTIFS($P$9:$P$199,H$206,$W$9:$W$199,$O$2) -> 0 | I208: =COUNTIFS($P$9:$P$199,I$206,$W$9:$W$199,$O$2) -> 0 | J208: =COUNTIFS($P$9:$P$199,J$206,$W$9:$W$199,$O$2) -> 8
B209: 戻り受注件数 | D209: =SUM(E209:I209) -> 4 | E209: =COUNTIFS($P$9:$P$199,E$206,$W$9:$W$199,$O$3) -> 4 | F209: =COUNTIFS($P$9:$P$199,F$206,$W$9:$W$199,$O$3) -> 0 | G209: =COUNTIFS($P$9:$P$199,G$206,$W$9:$W$199,$O$3) -> 0 | H209: =COUNTIFS($P$9:$P$199,H$206,$W$9:$W$199,$O$3) -> 0 | I209: =COUNTIFS($P$9:$P$199,I$206,$W$9:$W$199,$O$3) -> 0 | J209: =COUNTIFS($P$9:$P$199,J$206,$W$9:$W$199,$O$3) -> 0
B210: 受注率 | D210: =IFERROR(SUM(D208:D209)/D207,"") -> 0.5 | E210: =IFERROR(SUM(E208:E209)/E207,"") -> 0.44444444 | F210: =IFERROR(SUM(F208:F209)/F207,"") -> 0.72727273 | G210: =IFERROR(SUM(G208:G209)/G207,"") -> 0 | H210: =IFERROR(SUM(H208:H209)/H207,"") | I210: =IFERROR(SUM(I208:I209)/I207,"") | J210: =IFERROR(SUM(J208:J209)/J207,"") -> 0.72727273 | K210: ※面談場所ベース | L210: =IFERROR(SUM(L208:L209)/L207,"") | M210: =IFERROR(SUM(M208:M209)/M207,"")
D213: =設定用!J6 -> 代表 | E213: =設定用!J7 -> 黒田み | F213: =設定用!J8 -> 山田 | G213: =設定用!J9 -> 奥章 | H213: =設定用!J10 -> 山﨑
C214: 面談数 | D214: =COUNTIF($U$9:$U$199,D213) -> 0 | E214: =COUNTIF($U$9:$U$199,E213) -> 0 | F214: =COUNTIF($U$9:$U$199,F213) -> 3 | G214: =COUNTIF($U$9:$U$199,G213) -> 0 | H214: =COUNTIF($U$9:$U$199,H213) -> 0
C215: 受注数 | D215: =SUM(D217,D219) -> 0 | E215: =SUM(E217,E219) -> 0 | F215: =SUM(F217,F219) -> 2 | G215: =SUM(G217,G219) -> 0 | H215: =SUM(H217,H219) -> 0
D216: =IFERROR(D215/D214,"-") -> - | E216: =IFERROR(E215/E214,"-") -> - | F216: =IFERROR(F215/F214,"-") -> 0.66666667 | G216: =IFERROR(G215/G214,"-") -> - | H216: =IFERROR(H215/H214,"-") -> -
C217: Ｓ：即受注 | D217: =COUNTIFS($U$9:$U$199,D$213,$W$9:$W$199,$C217) -> 0 | E217: =COUNTIFS($U$9:$U$199,E$213,$W$9:$W$199,$C217) -> 0 | F217: =COUNTIFS($U$9:$U$199,F$213,$W$9:$W$199,$C217) -> 2 | G217: =COUNTIFS($U$9:$U$199,G$213,$W$9:$W$199,$C217) -> 0 | H217: =COUNTIFS($U$9:$U$199,H$213,$W$9:$W$199,$C217) -> 0
D218: =IFERROR(D217/D214,"-") -> - | E218: =IFERROR(E217/E214,"-") -> - | F218: =IFERROR(F217/F214,"-") -> 0.66666667 | G218: =IFERROR(G217/G214,"-") -> - | H218: =IFERROR(H217/H214,"-") -> -
C219: Ｓ：戻り受注 | D219: =COUNTIFS($U$9:$U$199,D$213,$W$9:$W$199,$C219) -> 0 | E219: =COUNTIFS($U$9:$U$199,E$213,$W$9:$W$199,$C219) -> 0 | F219: =COUNTIFS($U$9:$U$199,F$213,$W$9:$W$199,$C219) -> 0 | G219: =COUNTIFS($U$9:$U$199,G$213,$W$9:$W$199,$C219) -> 0 | H219: =COUNTIFS($U$9:$U$199,H$213,$W$9:$W$199,$C219) -> 0
D220: =IFERROR(D219/D214,"-") -> - | E220: =IFERROR(E219/E214,"-") -> - | F220: =IFERROR(F219/F214,"-") -> 0 | G220: =IFERROR(G219/G214,"-") -> - | H220: =IFERROR(H219/H214,"-") -> -
C221: Ａ：見込み高 | D221: =COUNTIFS($U$9:$U$199,D$213,$W$9:$W$199,$C221) -> 0 | E221: =COUNTIFS($U$9:$U$199,E$213,$W$9:$W$199,$C221) -> 0 | F221: =COUNTIFS($U$9:$U$199,F$213,$W$9:$W$199,$C221) -> 0 | G221: =COUNTIFS($U$9:$U$199,G$213,$W$9:$W$199,$C221) -> 0 | H221: =COUNTIFS($U$9:$U$199,H$213,$W$9:$W$199,$C221) -> 0
D222: =IFERROR(D221/D$214,"-") -> - | E222: =IFERROR(E221/E$214,"-") -> - | F222: =IFERROR(F221/F$214,"-") -> 0 | G222: =IFERROR(G221/G$214,"-") -> - | H222: =IFERROR(H221/H$214,"-") -> -
C223: Ｂ：見込み低 | D223: =COUNTIFS($U$9:$U$199,D$213,$W$9:$W$199,$C223) -> 0 | E223: =COUNTIFS($U$9:$U$199,E$213,$W$9:$W$199,$C223) -> 0 | F223: =COUNTIFS($U$9:$U$199,F$213,$W$9:$W$199,$C223) -> 1 | G223: =COUNTIFS($U$9:$U$199,G$213,$W$9:$W$199,$C223) -> 0 | H223: =COUNTIFS($U$9:$U$199,H$213,$W$9:$W$199,$C223) -> 0
D224: =IFERROR(D223/D$214,"-") -> - | E224: =IFERROR(E223/E$214,"-") -> - | F224: =IFERROR(F223/F$214,"-") -> 0.33333333 | G224: =IFERROR(G223/G$214,"-") -> - | H224: =IFERROR(H223/H$214,"-") -> -
C225: Ｃ：シート渡せず | D225: =COUNTIFS($U$9:$U$199,D$213,$W$9:$W$199,$C225) -> 0 | E225: =COUNTIFS($U$9:$U$199,E$213,$W$9:$W$199,$C225) -> 0 | F225: =COUNTIFS($U$9:$U$199,F$213,$W$9:$W$199,$C225) -> 0 | G225: =COUNTIFS($U$9:$U$199,G$213,$W$9:$W$199,$C225) -> 0 | H225: =COUNTIFS($U$9:$U$199,H$213,$W$9:$W$199,$C225) -> 0
D226: =IFERROR(D225/D$214,"-") -> - | E226: =IFERROR(E225/E$214,"-") -> - | F226: =IFERROR(F225/F$214,"-") -> 0 | G226: =IFERROR(G225/G$214,"-") -> - | H226: =IFERROR(H225/H$214,"-") -> -
C227: Ｄ：対応不可能 | D227: =COUNTIFS($U$9:$U$199,D$213,$W$9:$W$199,$C227) -> 0 | E227: =COUNTIFS($U$9:$U$199,E$213,$W$9:$W$199,$C227) -> 0 | F227: =COUNTIFS($U$9:$U$199,F$213,$W$9:$W$199,$C227) -> 0 | G227: =COUNTIFS($U$9:$U$199,G$213,$W$9:$W$199,$C227) -> 0 | H227: =COUNTIFS($U$9:$U$199,H$213,$W$9:$W$199,$C227) -> 0
D228: =IFERROR(D227/D$214,"-") -> - | E228: =IFERROR(E227/E$214,"-") -> - | F228: =IFERROR(F227/F$214,"-") -> 0 | G228: =IFERROR(G227/G$214,"-") -> - | H228: =IFERROR(H227/H$214,"-") -> -
C229: Ｅ：他社紹介 | D229: =COUNTIFS($U$9:$U$199,D$213,$W$9:$W$199,$C229) -> 0 | E229: =COUNTIFS($U$9:$U$199,E$213,$W$9:$W$199,$C229) -> 0 | F229: =COUNTIFS($U$9:$U$199,F$213,$W$9:$W$199,$C229) -> 0 | G229: =COUNTIFS($U$9:$U$199,G$213,$W$9:$W$199,$C229) -> 0 | H229: =COUNTIFS($U$9:$U$199,H$213,$W$9:$W$199,$C229) -> 0
...

Sheet 2月
B2: ★2026年 2月 | J2: 総計 | L2: ★面談結果未入力 | O2: =設定用!H6 -> Ｓ：即受注
D3: 総計 | E3: =設定用!B6 -> 横浜本店 | F3: =設定用!B7 -> 藤沢支店 | G3: =設定用!B8 -> 渋谷支店 | I3: 面談対応件数 | J3: =D210 -> 26 | K3: 未入力1 | L3: =IFERROR("管理表番号（"&VLOOKUP(K3,$A$10:$U$207,2,FALSE)&"）／面談担当者："&VLOOKUP(K3,$A$10:$U$207,21,FALSE),"") | O3: =設定用!H7 -> Ｓ：戻り受注
B4: 受信件数 | D4: =SUM(E4:I4) -> 52 | E4: =COUNTIF($F$9:$F$207,E3) -> 51 | F4: =COUNTIF($F$9:$F$207,F3) -> 1 | G4: =COUNTIF($F$9:$F$207,G3) -> 0 | I4: 即受注件数 | J4: =D211 -> 7 | K4: 未入力2 | L4: =IFERROR("管理表番号（"&VLOOKUP(K4,$A$10:$U$207,2,FALSE)&"）／面談担当者："&VLOOKUP(K4,$A$10:$U$207,21,FALSE),"")
B5: 面談予約件数 | D5: =SUM(E5:I5) -> 25 | E5: =COUNTIFS($F$9:$F$207,E3,$R$9:$R$207,"<>") -> 24 | F5: =COUNTIFS($F$9:$F$207,F3,$R$9:$R$207,"<>") -> 1 | G5: =COUNTIFS($F$9:$F$207,G3,$R$9:$R$207,"<>") -> 0 | I5: 戻り受注件数 | J5: =D212 -> 0 | K5: 未入力3 | L5: =IFERROR("管理表番号（"&VLOOKUP(K5,$A$10:$U$207,2,FALSE)&"）／面談担当者："&VLOOKUP(K5,$A$10:$U$207,21,FALSE),"")
B6: 面談獲得率 | D6: =IFERROR(D5/D4,"") -> 0.48076923 | E6: =IFERROR(E5/E4,"") -> 0.47058824 | F6: =IFERROR(F5/F4,"") -> 1 | G6: =IFERROR(G5/G4,"") | I6: 受注率 | J6: =D213 -> 0.26923077 | K6: 未入力4 | L6: =IFERROR("管理表番号（"&VLOOKUP(K6,$A$10:$U$207,2,FALSE)&"）／面談担当者："&VLOOKUP(K6,$A$10:$U$207,21,FALSE),"")
B8: ＮＯ | C8: 日付 | D8: 時間 | E8: 担当 | F8: 受信 事務所 | G8: 媒体 | H8: お名前 （ひらがな記入） | K8: お住まい住所 or アナウンス | L8: 電話番号 | M8: 相談の概要 | N8: 問い合わせ内容 | O8: 対応 | P8: 面談場所 | Q8: 面談備考 | R8: 面談日 | S8: 曜日 | T8: 時間 | U8: 面談担当 | V8: 管理担当 | W8: 面談結果 | X8: 対応
A9: =Y9&Z9 -> 0 | B9: 55 | C9: 46054 | D9: 11：50 | E9: 渡部 | F9: 横浜本店 | G9: HP | H9: 男性 | K9: 東京 | L9: 090-2666-1144 | M9: その他 | Y9: =IF(R9="","", IF(AND(R9<TODAY(),W9=""),"未入力","")) | Z9: =COUNTIF($Y$9:Y9,"未入力") -> 0
A10: =Y10&Z10 -> 0 | B10: 2 | C10: 46056 | D10: 11：00 | E10: 宮田 | F10: 横浜本店 | G10: HP | H10: やまぐち様 | K10: 東京 | L10: 090-6174-6847 | M10: 遺言書 | N10: 【相談者】やまぐち様（女性） 【TEL】090-6174-6847 【遺言者】旦那様 【相続人】山口様、お子様3名の計4名 【財産】預金、有価証券 【内容】 旦那様が病院を入退院を繰り返している状況 そのため、公正証書遺言を作りたいとの事。 財産に関しては頑固なため、結婚当時からどこの銀行にいくら入れているの教えてくれずわからない。 ネット銀行、ネット証券でやっているため知ろうにも知れない。 預金と株の概算はわからないが多くはないとの事。 また、二男が行方不明になっているので、相続上どうなるのかも知りたい。 ※横浜と渋谷で日程調整をする。日程は平日が良いとの事。 日程については予定を確認し、再度お電話するとの事でした。 ただ、そこまで食いついてなく、下の名前を言う前に終話になってしまったので本当かは微妙です。 | O10: 無料相談にお越しください | Y10: =IF(R10="","", IF(AND(R10<TODAY(),W10=""),"未入力","")) | Z10: =COUNTIF($Y$9:Y10,"未入力") -> 0
A11: =Y11&Z11 -> 0 | B11: 3 | C11: 46057 | D11: 10：00 | E11: 小川 | F11: クレア | G11: HP | H11: くにみ たいち様 | K11: 千葉 | L11: 090-2748-9373 | M11: 遺言書 | N11: 相談者：くにみ たいち様 TEL：090-2748-9373 遺言者：たいち様のおじ様 相続人：兄弟4名＋既に亡くなられているご兄弟2名のお子様 財産：品川区のマンション(中古価格で約2千万円)、預金3行約1千万円 内容：おじ様が余命一ヶ月を宣告されている。おじ様の代襲相続人になる方と、財産をめぐってトラブルになる可能性が非常に高いので、危急時遺言を遺したい、というご相談。 おじ様は五反田のNTT関東病院にて入院中。 容体としては、現在モルヒネを投与中で、会話・筆談が厳しいレベルだが、認知能力に問題はなく、聞けば反応は返してくれる状態。 また、トラブルに発展しそうな相続人の住所を把握しておらず、今後もできるだけ関わりたくないとのことで、相続発生後の手続きについても気にされておりました。 面談日当日に、取得済みの財産についての資料などをお持ちいただけるようです。 | O11: 無料相談にお越しください | P11: 渋谷支店 | R11: 46059 | S11: 金 | T11: 18：00 | U11: 嶋津 | W11: Ｂ：見込み低 | X11: 相談者のおじは、過去に姉妹の息子（甥）と養子縁組に関するトラブルを起こしており、甥には財産を渡したくないとのご意向。 財産の内容を確認した上で、危急時遺言作成の費用をご案内した。 体調が思わしくなく、遺言書を作成できるかどうかわからないが、本人に確認してみるとのこと。 | Y11: =IF(R11="","", IF(AND(R11<TODAY(),W11=""),"未入力","")) | Z11: =COUNTIF($Y$9:Y11,"未入力") -> 0
A12: =Y12&Z12 -> 0 | B12: 4 | C12: 46057 | D12: 11：30 | E12: 安井 | F12: 横浜本店 | G12: HP | H12: えのもと みちこ様 | K12: 横浜 | L12: 045-319-1171 | M12: 民事信託 | N12: ★信託はじめ、生前対策に関するご相談 相談者：えのもと様、旦那様 推定相続人：お子様2名 財産：ご自宅不動産（夫婦で共有）、預金等の金融資産 お困りごと：今後ご体調の変化により財産の管理がご自身でできなくなることをご不安に思っていらっしゃるとのこと。信託をしたり、不動産の生前贈与等を行うなどし、認知症などになる前に管理できる状態にしておきたいとのことです。 お子様方ともよくこのお話をされているそうですが、信託の知識があまり無いことから誰を受託者にするかといった具体的なお話はされていないご様子でした。 また、旦那様は目が不自由だそうで、当日はえのもと様のみでご来所される予定です。 当日は、ご自宅不動産の納税通知書をお持ちいただけます。 045-319-1171 2/10 えのもと様からお電話があり、旦那様の体調が優れず病院に連れていかれるそうで、キャンセルになりました。再度の日程調整については、状況が落ち着きしだいえのもと様からご連絡いただけるそうです。（久田） | O12: 無料相談にお越しください | P12: 横浜本店 | Y12: =IF(R12="","", IF(AND(R12<TODAY(),W12=""),"未入力","")) | Z12: =COUNTIF($Y$9:Y12,"未入力") -> 0
A13: =Y13&Z13 -> 1 | B13: 57 | C13: 46056 | D13: 18：00 | E13: 久田 | F13: 横浜本店 | G13: HP | H13: えざわ たかゆき様 | K13: 横浜 | L13: 080-6782-4810 | M13: 相続放棄 | N13: 被相続人：お父様（R7年2月頃） 相続人：お母様、ご兄弟、たかゆき様 計3名様 1月29日に横浜信用金庫から催告状が届き、お父様がご逝去された旨をお知りになったそうです。 ご兄弟にも催告状が届いており、相続放棄をご希望されております。 現在お母様は認知症で意思判断能力がない状態です。 成年後見人の申立てが必要な可能性があることはご存知ないご様子でした。 ☆現在日程調整中 面談希望日が決まり次第、えざわ様よりご連絡いただきます。 ご面談場所は「横浜本店」ご希望です。 日程調整＋面談場所案内＋当日の持ち物のご案内をお願いします。 | O13: 無料相談にお越しください | P13: 横浜本店 | Y13: =IF(R13="","", IF(AND(R13<TODAY(),W13=""),"未入力","")) | Z13: =COUNTIF('1月'!$Y$9:Y64,"未入力") -> 1
A14: =Y14&Z14 -> 1 | B14: 58 | C14: 46057 | D14: 17：30 | E14: 久田 | F14: 横浜本店 | G14: HP | H14: たかだ様 | K14: 東京 | L14: 非通知 | N14: 被相続人：お父様（R2.6） 相続人：たかだ様、ご兄弟（疎遠） 【相続財産】 不動産なし 預貯金：何百万円ほど 株式：1000万円いかないほど お父様は生前に成年後見を立てており、 | O14: 無料相談にお越しください | P14: 渋谷支店 | Y14: =IF(R14="","", IF(AND(R14<TODAY(),W14=""),"未入力","")) | Z14: =COUNTIF('1月'!$Y$9:Y65,"未入力") -> 1
A15: =Y15&Z15 -> 0 | B15: 81 | C15: 46058 | D15: 13：00 | E15: 栗田 | F15: 横浜本店 | G15: HP | H15: まつば やすよ様 | K15: 横須賀 | L15: 080-5428-7155 | M15: 相続手続き | N15: HP経由 被相続人：おば 相続人：まつば様の夫の父、アメリカに住んでいるおば、その他おばの兄弟2人 財産内容：預金 相談内容：銀行手続はもちろん、アメリカに住んでいるおばとの連絡のやりとりについて相談したい 住所は分かる | O15: 無料相談にお越しください | P15: 横浜本店 | R15: 46069 | S15: 月 | T15: 13：00 | U15: 新井 | W15: Ａ：見込み高 | X15: 兄弟相続 相続人：甥姪ふくめ6名※うち一名アメリカ在住（住所知らない・生死不明） 相続財産：預金160万ぐらい 相談者や相談者家族は相続人ではない。 正直、手続きを行う費用対価が合わないため、簡易解約や払戻制度の利用を案内いたしました。最悪放置も検討。 相続人の中に同じような配偶者や子供がいない方がいるので、そちらの遺言書作成を提案しております。 遺言書は依頼したいとの話 | Y15: =IF(R15="","", IF(AND(R15<TODAY(),W15=""),"未入力","")) | Z15: =COUNTIF($Y$9:Y15,"未入力") -> 0
A16: =Y16&Z16 -> 0 | B16: 8 | C16: 46058 | D16: 16：59 | E16: 宮田 | F16: 横浜本店 | G16: HP | H16: うしくぼ としゆき様 | K16: 浦和 | L16: 090-6654-8147 | M16: その他 | N16: 【相談者】うしくぼ としゆき様 【TEL】090-6654-8147 【相談内容】 お父様の相続について先に相談しておきたい（まだ生きています） 土地国庫既読制度を希望しておりました。 お父様は畑を持っていて農地（青地）となっている。 既にお母様は他界しており、ご子息様は相談者の一名のみ ※面談は渋谷を希望していました。 面談日については再度相談したいとの事で、としゆき様が落ち着いてからの折り返しとなりました。 折り返しの来た際は渋谷でお願いします。 面談時間は60～90分で完全無料、平日若しくは土曜日で10時～18時までとお伝えしております。 | O16: 無料相談にお越しください | P16: 渋谷支店 | Y16: =IF(R16="","", IF(AND(R16<TODAY(),W16=""),"未入力","")) | Z16: =COUNTIF($Y$9:Y16,"未入力") -> 0
A17: =Y17&Z17 -> 0 | B17: 9 | C17: 46059 | D17: 13：20 | E17: 宮田 | F17: 横浜本店 | G17: HP | H17: いしわた えいいち様 | K17: 横浜 | L17: 090-3223-0874 | M17: 遺言書 | N17: 【相談者】いしわた えいいち様 【TEL】090-3223-0874 【遺言書作成者】お母様 【法定相続人】ご子息乃至お嬢様 計3名（お父様は既に他界） 【相続財産】不動産、金融資産等 【内容】 遺言書を自筆証書で書きたい。 その際の文言についてどう記載したら効力が発生するしないがわからないので教えてほしい 記載内容としては「不動産は○○に相続する。その他相続財産は相続発生時に相続人全員での協議の上で決定する｝ような内容で記載したい。 ※日程調整は横浜で土曜なら確実に来れる（午前午後の指定等なし） 14日（土）16：30の森谷さんが開いていると思い16：30～の約60分の面談をお伝えしました。 また、21日以降の日程も空きがありましたのでお伝えしております。 えいいち様の方で土曜日の日程調整等行っていただき、再度折り返しいただく約束をしました。 受任になる可能性は低そうですが、受電された方は日程調整をお願いします。 | O17: 無料相談にお越しください | P17: 横浜本店 | Y17: =IF(R17="","", IF(AND(R17<TODAY(),W17=""),"未入力","")) | Z17: =COUNTIF($Y$9:Y17,"未入力") -> 0
A18: =Y18&Z18 -> 0 | B18: 10 | C18: 46059 | D18: 15：40 | E18: 山﨑 | F18: 横浜本店 | G18: HP | H18: まきた りゅうすけ様 | K18: 茅ヶ崎？ | L18: 090-1211-3081 | M18: 生前対策 | N18: 自分の子供２人に、自分がもしものことになった時にも高額治療を受けないように伝えていきたい。 | O18: 法的拘束力はないが、茅ヶ崎市役所で配布しているエンディングノートを活用する様にご案内。 | Y18: =IF(R18="","", IF(AND(R18<TODAY(),W18=""),"未入力","")) | Z18: =COUNTIF($Y$9:Y18,"未入力") -> 0
A19: =Y19&Z19 -> 0 | B19: 11 | C19: 46055 | D19: 15：00 | E19: 角田 | F19: 横浜本店 | G19: HP | H19: やたべ ゆうさく様 | K19: 神奈川区 | L19: 090-1115-6287 | M19: 相続手続き | N19: 数年前に嶋津様受注にて面談あり。その際は不動産査定で終了。今回お父様に相続発生し、改めて相談。 | O19: 無料相談にお越しください | P19: 横浜本店 | R19: 46059 | S19: 金 | T19: 10：00 | U19: 角田 | W19: Ｂ：見込み低 | X19: お見積り提示の上、検討とのこと。検討２週間とのこと。 | Y19: =IF(R19="","", IF(AND(R19<TODAY(),W19=""),"未入力","")) | Z19: =COUNTIF($Y$9:Y19,"未入力") -> 0
A20: =Y20&Z20 -> 0 | B20: 12 | C20: 46061 | D20: 11：00 | E20: 田中 | F20: 横浜本店 | G20: HP | H20: おかざき りょう様 | K20: 横浜(藤沢) | L20: 080-8014-6692 | M20: その他 | N20: 【相談者】おかざき りょう様 【TEL】080-8014-6692 【相談内容】相続土地国庫帰属制度について。 りょう様のお母様と叔母様が数年前にご相続された、栃木県の那須の別荘地の土地について処分を検討されている。りょう様が窓口となって確認されている。雑種地だったが、木が生えたため山林扱いになっているとの事です。固定資産税はかかっていない。また、祖父の遠い親戚も別の場所に土地を所有しており、娘さんが相続されたとの事だが、同じように処分を検討されているので話を聞きたいとの事です。3か所について聞きたいとの事です。 ご自宅に権利証があればお持ちくださいとお伝えしました。土地国庫帰属制度の他に方法がないかについても確認されたいとの事です。 | O20: 無料相談にお越しください | P20: 藤沢支店 | R20: 46074 | S20: 土 | T20: 15：00 | U20: 新井 | W20: Ｂ：見込み低 | X20: 相続土地国庫帰属制度や隣地の方への贈与を提案。 一応、OCでは土地国庫帰属制度の見積もりをご提示し、すっきり不動産の見積もりを依頼 | Y20: =IF(R20="","", IF(AND(R20<TODAY(),W20=""),"未入力","")) | Z20: =COUNTIF($Y$9:Y20,"未入力") -> 0
A21: =Y21&Z21 -> 0 | B21: 13 | C21: 46061 | D21: 15：05 | E21: 田中 | F21: 横浜本店 | G21: HP | H21: 男性 | K21: 東京 | L21: 090-5443-3297 | M21: 遺言書 | N21: 【内容】①相続税について、いくらかかるのか教えてほしい。→税理士の業務になるので回答できない。 ②遺言書の作成の依頼費用について。約1億円程財産がある。 →書かれる内容は決まっている。財産額によって変わるが、15万から20万円と回答。 無料相談を案内しましたが、検討されるとのことです。 | O21: 無料相談にお越しください | Y21: =IF(R21="","", IF(AND(R21<TODAY(),W21=""),"未入力","")) | Z21: =COUNTIF($Y$9:Y21,"未入力") -> 0
A22: =Y22&Z22 -> 0 | B22: 14 | C22: 46062 | D22: 0.44444444 | E22: 藤田さ | F22: 藤沢支店 | G22: HP | H22: にしだ かよこ 様 | K22: 藤沢 | L22: 080-5517-6411 | M22: 相続手続き | N22: 相談者の父の相続についてのご相談 父はご存命で三重県にお住まい。 推定相続人は子３人（妻については確認漏れました）。 父が現在入院中で、先が長くなさそうなので、 今のうちに相続についていろいろと準備をしておきたい。 父の近くに住んでいる兄がおそらく大半を引き継ぐと思うが、 不動産が多くあり、兄が管理ができるか不安を感じている。 この後必要となる相続の手続き、相続税申告の要否など、を聞きたい。 当日、固定資産税納税通知書や金融資産資料などお持ちいただける予定。 にしだ かよこ ０８０－５５１７－６４１１ | O22: 無料相談にお越しください | P22: 藤沢支店 | R22: 46066 | S22: 金 | T22: 0.41666667 | U22: 藤田さ | W22: Ｂ：見込み低 | X22: お父様がご存命ですが、来る相続についてご不安がありご面談。 お話を伺った範囲では、相続税申告が必要であることをお伝えし、必要書類や手続きの流れ一式についてご案内。他のご相続人と話し合われてご検討されるとのこと。 | Y22: =IF(R22="","", IF(AND(R22<TODAY(),W22=""),"未入力","")) | Z22: =COUNTIF($Y$9:Y22,"未入力") -> 0
A23: =Y23&Z23 -> 0 | B23: 15 | C23: 46062 | D23: 14：50 | E23: 菅家 | F23: 横浜本店 | G23: HP | H23: 男性 | K23: 東京 | L23: 080-3270-2228 | M23: 複雑な相続 | N23: 被相続人 叔父 相続人 配偶者、兄弟、甥姪 計9名 相談者は故人から見て甥にあたる方。 故人配偶者から相続放棄をしてほしい旨の通知が届いた。相談者とては放棄せず相続をしたいと。 行政書士司法書士では相続手続きをお手伝いすることはできるが、相談者の味方について何かをすることはできないので、弁護士との相談を提案。 別件の相続で現在調停を行っているようで、今お願いしている弁護士に相談してみますとのことでした。 | O23: 弁護士との無料相談にお越しください | Y23: =IF(R23="","", IF(AND(R23<TODAY(),W23=""),"未入力","")) | Z23: =COUNTIF($Y$9:Y23,"未入力") -> 0
A24: =Y24&Z24 -> 0 | B24: 16 | C24: 46063 | D24: 16：20 | E24: 上田 | F24: 横浜本店 | G24: HP | H24: かねこ みつてる様 | K24: 東京 | L24: 080-3156-6554 | M24: 名義変更 | N24: 過去客 R5-Y12060 カネコ テルミ様 亮太郎さんの過去客の兄妹からのご紹介 被相続人：祖母 相続人：相談者、姉が二人、従兄弟も数名いる 相続財産：不動産（私道） 祖母の相続登記の手続きを行っていて、完了したと思っていたら私道がいくつか漏れていた。 私道のみのお手続きです。 当時の手続き資料をお持ちいただけます。 | O24: 無料相談にお越しください | P24: 渋谷支店 | R24: 46071 | S24: 水 | T24: 14：30 | U24: 梅澤 | W24: ― | X24: 私道部分の登記希望。亮太郎さん／真大さんのお客様（過去客ではなく、今月納品した先） 光輝様分私道の相続登記希望、見積提示要求あり、早急に対応要。 面談後に、亮太郎さんに状況をを確認いたしました。 真大さんへ引継ぎをお願いしたいです。 | Y24: =IF(R24="","", IF(AND(R24<TODAY(),W24=""),"未入力","")) | Z24: =COUNTIF($Y$9:Y24,"未入力") -> 0
A25: =Y25&Z25 -> 0 | B25: 17 | C25: 46064 | D25: 13：30 | E25: 栗田 | F25: 横浜本店 | G25: HP | H25: たなか まさき様 | K25: 湘南台 | L25: 090-1669-7818 | M25: 相続放棄 | N25: 被相続人：おじ（R7/10月ご逝去） 相続人：おじの兄弟が数名、たなか様（父は既に他界） 相談内容：藤沢市からおじの兄弟宛にR8年1月16日に連絡があった。詳しい書面はまだ来ていないが、未払の公共料金や税金などがあるらしいので相続放棄を考えている。 基本的にはお願いしたいとのことでした。 | O25: 無料相談にお越しください | P25: 藤沢支店 | R25: 46072 | S25: 木 | T25: 13：30 | U25: 山田 | W25: Ｓ：即受注 | X25: 状況は左の通り。親族間は疎遠な関係が多い。お一人の放棄で受任。 | Y25: =IF(R25="","", IF(AND(R25<TODAY(),W25=""),"未入力","")) | Z25: =COUNTIF($Y$9:Y25,"未入力") -> 0
B26: 18 | C26: 46064 | D26: 16：40 | E26: 上村 | F26: 横浜本店 | G26: HP | H26: ひだか としえ | K26: 横浜市 | L26: 090-1609-3459 | M26: 相続放棄 | N26: 故人：たなか とよ様 ※相談者母 亡くなった日：2026年1月22日 相談者：ひだか としえ様 相続人：相談者とご兄弟2名。※配偶者(＝相談者父)は4年～5年前に死亡。 相談者は横浜市在住。 相続放棄の相談をしたい。 被相続人に負債があるという事情ではなく、 これ以上家族と関わりたくないという事情で放棄を考えている。 (深い事情についてはヒアリングしませんでしたが、ご家族と関わりたくない雰囲気は漂ってました) なお、他の相続人から遺産分割協議書作るから相談者の印鑑証明を送ってほしいといわれているが どうしたらいいのかという質問あり。 →この件につきましては、現時点で送らないでほしいとお伝え。 放棄するorしない方針のメリットデメリット含めて、専門家に相談しましょうとしております。 | O26: 無料相談にお越しください | P26: 横浜本店 | R26: 46069 | S26: 月 | T26: 17：00 | U26: 角田 | W26: Ｂ：見込み低 | X26: 相続放棄のご相談。他姉妹と関わりたくないとのことで、放棄を検討。 メリット、デメリット、注意点をお伝えいたしました。 費用の提示も致しましたが、ご自身で行ってみるとのことでしたので、不受託といたします。
A27: =Y27&Z27 -> 0 | B27: 19 | C27: 46064 | D27: 17：00 | E27: 栗田 | F27: 横浜本店 | G27: HP | H27: 女性 | K27: 横浜 | L27: 070-4457-2359 | M27: その他 | N27: 滋賀県の土地を手放したい 死んだ父と父の兄の共有の土地に関して、管理会社から管理費がかかるといわれて困っている。 なんとか手放す方法があるか相談したい 土地国庫帰属制度や近くの方に贈与するなどの方法があることをお伝え | O27: 無料相談にお越しください | Y27: =IF(R27="","", IF(AND(R27<TODAY(),W27=""),"未入力","")) | Z27: =COUNTIF($Y$9:Y27,"未入力") -> 0
A28: =Y28&Z28 -> 0 | B28: 20 | C28: 46063 | D28: 22：00 | E28: 渡部 | F28: 横浜本店 | G28: メール | H28: かばや まさる | K28: － | L28: 090-2463-7480 | M28: 名義変更 | N28: ※2/12 12:00 留守電 （渡部） 夕方頃再架電予定ですが、折り返しございましたら以下確認の上ご対応お願いいたします。 【お問い合わせの内容】 相続手続きについて 【お問い合わせの詳細】 法定相続人は母、私及び妹の３人ですが、母単独で相続することを予定しております。相続財産につきましては、預金のほか、不動産として ①横浜市金沢区 の実家 ②千葉県長生郡白子町 の土地 があり、①については母への名義変更、②については母への名義変更の後「相続土地国庫帰属制度」を活用したいと考えております。 ○ 相続土地国庫帰属制度の手続を含め、お願いすることは可能でしょうか。（白子町の土地について、土地の状況等が分かる資料や写真の準備を含めてお願いすることは可能でしょうか。） ○ ①及び②に係る費用については、どの位かかるものでしょうか。 【個別のご要望】 【WEB面談の希望】 【お名前】 蒲谷 勝 【フリガナ】 カバヤ マサル 【連絡先メールアドレス】 ca72354@cd5.so-net.ne.jp 【連絡先電話番号】 090-2463-7480 | O28: 無料相談にお越しください | P28: 横浜本店 | R28: 46080 | S28: 金 | T28: 18：00 | U28: 齋藤 | W28: Ｄ：対応不可能 | X28: 土地国庫帰属の現地調査を対応してほしい →厳しいと回答 不動産査定依頼をいただき、場合によっては有償引き取りを提案 | Y28: =IF(R28="","", IF(AND(R28<TODAY(),W28=""),"未入力","")) | Z28: =COUNTIF($Y$9:Y28,"未入力") -> 0
A29: =Y29&Z29 -> 0 | B29: 21 | C29: 46066 | D29: 15：26 | E29: 上田 | F29: 横浜本店 | G29: ＨＰ | H29: やまだ けんいち様 | K29: 東京 | L29: 090-9148-6959 | M29: 遺言書 | N29: 【相談者】やまだ けんいち様 【TEL】090-9148-6959 【遺言者】お母様 【相続人】長男、長女、次女 【財産】不動産のみ 【内容】 お父様からのお言葉で母の面倒見てくれた方に不動産をといわれていて、全てご長男様という内容で作成を検討中。 ただ、不動産しか財産はなく、遺留分が心配。 代償金にするのも長男は貯金がなく、手出しができない。 不動産は残したいというような要望です。 | O29: 無料相談にお越しください | P29: 横浜本店 | R29: 46074 | S29: 土 | T29: 10：00 | U29: 新井 | W29: Ａ：見込み高・後追い要 | X29: 遺留分を請求されても支払ができない。 不動産を担保にお金を借りる方法や養子縁組を行い、遺留分を減らす方法を検討したが、どれも難しく共有持ち分で登記を入れるのが一番有効かという結論になった。 一度、お母様と相談し、施設に伺う予定。 | Y29: =IF(R29="","", IF(AND(R29<TODAY(),W29=""),"未入力","")) | Z29: =COUNTIF($Y$9:Y29,"未入力") -> 0
A30: =Y30&Z30 -> 0 | B30: 22 | C30: 46066 | D30: 9：50 | E30: 久田 | F30: 横浜本店 | G30: ＨＰ | H30: ちばみつよ様 | K30: 東京 | L30: 090-6656-0720 | M30: 遺言書 | N30: 【ご相談者】ちばみつよ様 【遺言者】ちば様のお兄様 【遺言内容（案）】 ・相続財産の2分の1をちば様へ ・残りの2分の1を娘様お二人へ（各2分の1ずつ） ※奥様とは離婚されており、娘様お二人とは現在連絡を取っていないとのことです。 【財産内容】 ・預貯金：約1,000万円 ・不動産：あり 相財産は5000万円以下 【経緯】 当初、公正証書遺言を作成予定でしたが、作成日の前日に緊急入院となりました。（末期がんのため） 公証役場へ確認したところ、現在混み合っており、次回の作成可能日が1か月後との案内を受けたため、危急時遺言のご相談をいただいております。 医師からは「今週末を越えられるかどうか」と説明を受けている状況です。 【お兄様のご状態（※昨日時点）】 ・署名程度であれば何とか可能 → 長文の自筆証書遺言の作成は困難だそうです ・相続人および遺贈先を口頭で伝えることが可能 ・遺言内容の読み聞かせに反応可能 ・本人確認および意思疎通は可能 【その他】 ・公正証書遺言作成時に必要な戸籍等の書類はお持ちいただけます ・医師からの診断書も取得予定 ・個室に入院中であり、病院側の許可も得ているため、病室での作成が可能 ・費用は20～30万円でご案内済み ・本日、前受金の請求書をお渡しすることをお伝え済み | O30: 危急時遺言作成 | P30: その他 | Q30: 赤十字大森病院 | R30: 46066 | S30: 金 | T30: 15：00 | U30: 齋藤 | V30: 上村 | W30: Ｓ：即受注 | X30: 依頼者：千葉 光代(ちば みつよ)様 遺言者：千葉 一利(ちば かずとし)様 ※相談者のお兄様 2/13 15：00～16：30 大森赤十字病院にて、危急時遺言作成で受注、即対応。 危急時遺言の証人として、市川さん、上村が同行。 問い合わせの内容の通り、相談者が上記公正証書遺言の文案に遺言者の印鑑をもらおうと病院に訪問したところ、医師からもう長くないと宣告をされ、遺言作成が間に合わないとなり相談に至った状況。 既に相談者の手元に戸籍、公正証書遺言の文案は揃っていた。 遺言者は緩和ケア病棟の個室にご入院されており、危急時遺言ではあったが、遺言者との意思疎通に大きな問題はなかった。 ※かなりつらそうな状況であったが、齋藤さんとの会話対して体を起こそうとするなどの姿勢がみられ、目の焦点もしっかりとしていた。 公正証書遺言の文案では、財産の1/2を遺言者の妹様である相談者様に遺贈、 残り1/2については遺言者のご息女2名で均等に分け相続(一人につき1/4)というもの。 財産は大田区東馬込のマンション1室、銀行は4行(三井住友銀行、三菱UFJ銀行、りそな銀行、横浜銀行) 法定相続人はご息女2名であるが、配偶者との離婚後、まったくの没交渉だった模様。 遺言内容の確認時に、ご長女の苗字が変わっていることに驚かれるくらい(今、橋本なのか…とつぶやく) なお、叔母にあたる依頼者も全く会ったがないとチラッと仰せ。 齋藤さんの聞き取りの中で、遺言者は本当は財産すべてを相談者にすべて渡したい意向を示したが、 齋藤さんがご息女の遺留分について丁寧に説明したところ、将来的に紛争になることや紛争の可能性があるのなら、少しでもリスクの低い文案通りの内容で良いとの話になり、そのお話を基に遺言書を作成した。 作成後、今後の流れを依頼者に説明。おそらく遺言執行での受注は低いかと思われるが、当日問い合わせで即対応いただいたことに深く感謝される。 齋藤さんの名刺と上村の名刺はお渡ししているため、検認が必要となった場合(お亡くなりになった場合)は別途連絡をいただける。 なお、費用については2/16にお振込予定。※検認が必要となった場合は別途費用かかることはお伝えしている | Y30: =IF(R30="","", IF(AND(R30<TODAY(),W30=""),"未入力","")) | Z30: =COUNTIF($Y$9:Y30,"未入力") -> 0
A31: =Y31&Z31 -> 0 | B31: 23 | C31: 46067 | D31: 10：00 | E31: 久田 | F31: 横浜本店 | G31: ＨＰ | H31: ざはのりこ様 | K31: 横浜 | L31: 090-2466-0709 | M31: 相続放棄 | N31: 被相続人：ざは様の叔父様（R7.2.9にご逝去） 叔父様は結婚しておらず、両親も既にご逝去されている。 叔父様のご兄弟であるざは様のお父様もご逝去されているため、相続権がざは様に渡っている状態。 財産が分からず、相続放棄をしたほうがよいのかもわからないため、今後の手続きについてご相談されたいそうです。 090-2466-0709 | O31: 無料相談にお越しください | P31: 横浜本店 | R31: 46072 | S31: 木 | T31: 17：00 | U31: 山﨑 | W31: Ｓ：即受注 | X31: 相続放棄を受任 | Y31: =IF(R31="","", IF(AND(R31<TODAY(),W31=""),"未入力","")) | Z31: =COUNTIF($Y$9:Y31,"未入力") -> 0
A32: =Y32&Z32 -> 0 | B32: 24 | C32: 46066 | D32: 10：00 | E32: 宮田 | F32: 横浜本店 | G32: ＨＰ | H32: じょ あ あ様 | K32: 横浜 | L32: 080-4059-9659 | M32: 遺言書 | N32: 【相談者】ジョ ア ア様 【TEL】080-4059-9659 【相続財産】自宅（ローンあり）、少しの預金 【相談内容】 遺言書を作りたいから相談したい。 シングルマザーで4才の子どもがいる。 日本の親族はいなくて、中国から日本に来た。 日本語はカタコトですが、わからないことがあるとわからないと言ってくださいます。 たまに質問とは別のことが返ってくることもあります。 大変かと思いますが、よろしくお願いいたします。 | O32: 無料相談にお越しください | P32: 横浜本店 | R32: 46088 | S32: 土 | T32: 10：00 | U32: 角田 | W32: Ｂ：見込み低 | X32: 法務局保管の自筆証書遺言を作成予定。自宅不動産、投資用物件、預貯金あり（銀行４行～５行）。配偶者がなく４歳のお子さん。親族は国内にいない。お子さんの監護権が心配な点。一旦検討するとのこと。 | Y32: =IF(R32="","", IF(AND(R32<TODAY(),W32=""),"未入力","")) | Z32: =COUNTIF($Y$9:Y32,"未入力") -> 0
A33: =Y33&Z33 -> 0 | B33: 25 | C33: 46067 | D33: 16：30 | E33: 久田 | F33: 横浜本店 | G33: ＨＰ | H33: えのもと かずひろ様 | K33: 横浜 | L33: 090-1206-5882 | M33: 相続手続き | N33: 被相続人：えのもと様のお父様（2年程前） 相続人：えのもと様、お母様、兄弟2名 計4名様 不動産：戸建て（横浜）40坪ほど 預貯金：600万円ほど 株・証券：なし ご相続の手続きの流れや必要書類等が知りたいそうです。 090-1206-5882 | O33: 無料相談にお越しください | P33: 横浜本店 | R33: 46072 | S33: 木 | T33: 10：00 | U33: 角田 | W33: Ｂ：見込み低 | X33: 令和５年ご逝去のお父様の相続手続き。相続人は配偶者、お子様３名。お母様が高齢で施設入所も検討しているので、 不動産の売却の視野に協議を検討。他相続人と相談をしてご連絡をいただく予定です。 検討１か月。 | Y33: =IF(R33="","", IF(AND(R33<TODAY(),W33=""),"未入力","")) | Z33: =COUNTIF($Y$9:Y33,"未入力") -> 0
A34: =Y34&Z34 -> 0 | B34: 26 | C34: 46068 | D34: 11：00 | E34: 上田 | F34: 横浜本店 | G34: ＨＰ | H34: 男性 | K34: 横浜 | L34: 090-1115-6287 | M34: その他 | N34: 遺留分請求をしない旨の念書の書き方について 無料相談のご案内をしたところ、今日明日で教えてほしいとのことで時間的に難しく、またわからないことがあればお電話するというとこで終話 | O34: 無料相談にお越しください | Y34: =IF(R34="","", IF(AND(R34<TODAY(),W34=""),"未入力","")) | Z34: =COUNTIF($Y$9:Y34,"未入力") -> 0
A35: =Y35&Z35 -> 0 | B35: 27 | C35: 46069 | D35: 14：00 | E35: 菅家 | F35: 横浜本店 | G35: ＨＰ | H35: かすや のりこ様 | K35: 東京 | L35: 090-2306-2068 | M35: 遺言書 | N35: 自筆証書遺言作成のご相談 遺言者 相談者兄（埼玉在住）79歳 推定相続人 妹2名、姪 兄の面倒は相談者含む妹2名で見ている。姪に手伝ってくれと相談しても手伝ってくれず、相続が発生した際に姪に渡らないように自筆証書遺言を作成しておきたい。 面談については一度姉にも相談してから決めたいとのことで、希望の場合には連絡くださいとお伝え。面談するなら渋谷がいいと。 | O35: 無料相談にお越しください | Y35: =IF(R35="","", IF(AND(R35<TODAY(),W35=""),"未入力","")) | Z35: =COUNTIF($Y$9:Y35,"未入力") -> 0
A36: =Y36&Z36 -> 0 | B36: 28 | C36: 46069 | D36: 14：50 | E36: 渡部 | F36: 横浜本店 | H36: いとう あさこ | K36: メール | L36: 090-4071-8563 | N36: 2/16 留守電 （渡部） 折り返しございましたら対応お願いいたします。 2/17、2/18留守電 信託 家族信託サイト経由 【メールアドレス】 mhasa.rryygg@gmail.com 【郵便番号】 168-0081 【ご住所】 杉並区宮前4-24-7 【電話番号】 090-4071-8563 【FAX】 【お問い合わせ内容】 障害のある娘のために、将来的に家族信託を活用して生活資金の確保および実際の使用を確実にしておきたいと考えています。どのような方法が有効か教えていただきたいと思います。 【個人情報の取り扱いについて】 個人情報の取扱いについて「同意する」 | O36: 無料相談にお越しください | Y36: =IF(R36="","", IF(AND(R36<TODAY(),W36=""),"未入力","")) | Z36: =COUNTIF($Y$9:Y36,"未入力") -> 0
A37: =Y37&Z37 -> 0 | B37: 29 | C37: 46069 | D37: 15：15 | E37: 安井 | F37: 横浜本店 | G37: HP | H37: やまざき きよか様 | K37: 横浜 | L37: 090-8646-2379 | M37: 相続手続き | N37: 被相続人：お父様（R6.12.28ご逝去） 相続人：やまざき様1名のみ 相続財産：自宅不動産（土地、建物）、預金、株式 お困りごと：相続手続きについて聞きたい、お手伝いを頂きたいとのこと。 当日は、納税通知書があればお持ちいただけます。 090-8646-2379 | O37: 無料相談にお越しください | P37: 横浜本店 | R37: 46071 | S37: 水 | T37: 17：00 | U37: 花井 | W37: Ｓ：即受注 | X37: 相続人は依頼者一人であるが、相続財産総額が約4000万弱（ただし預金については聴取による部分が大きく、ブレがあるものと考える）で、相続税申告が必要。加えて13万円/月のローンの負担を実質的には被相続人が行っていたという意味ではその金額についても贈与の持ち戻しが必要になる為、早期に税理士を紹介する。 金融機関口座についても複数に分かれており、保振・生保協会への開示請求も行う。 もろもろ込みで遺産承継にて契約。 | Y37: =IF(R37="","", IF(AND(R37<TODAY(),W37=""),"未入力","")) | Z37: =COUNTIF($Y$9:Y37,"未入力") -> 0
A38: =Y38&Z38 -> 0 | B38: 30 | C38: 46069 | D38: 15：00 | E38: 久田 | F38: 横浜本店 | G38: HP | H38: いけうち けんいちろう様 | K38: 横浜 | L38: 0467-43-2888 | M38: 相続手続き | N38: 被相続人：いけうち様のお父様（10年程前） 相続人；いけうち様、兄弟3名 計4名様 不動産：3筆 お母様は3年程前にご逝去されております。 不動産の名義変更手続きを進めたいそうです。 自筆の遺言書があり、不動産をそれぞれ①いけうち様のご子息様2名 ②お兄様 ③お母様にご相続又は遺贈されることが記載されているそうです。 当日は自筆の遺言書をお持ちいただけます。 0467-43-2888 | O38: 無料相談にお越しください | P38: 藤沢支店 | R38: 46074 | S38: 土 | T38: 10：00 | U38: 森谷 | W38: Ｓ：即受注 | X38: 遺言検認と相続登記 自筆証書遺言は封筒を開封してしまった。 登記申請件数は最低でも５件 相続人の一人に知的障がい者いる（意思疎通、内容理解はできるので分割協議は可能らしい） | Y38: =IF(R38="","", IF(AND(R38<TODAY(),W38=""),"未入力","")) | Z38: =COUNTIF($Y$9:Y38,"未入力") -> 0
A39: =Y39&Z39 -> 0 | B39: 31 | C39: 46070 | D39: 9：32 | E39: 宮田 | F39: 横浜本店 | G39: HP | H39: さとう まりこ様 | K39: 横浜 | L39: 090-4370-5758 | M39: その他 | N39: 【相談者】さとうまりこ様 【TEL】090-4370-5758 【被相続人】お祖母様（R7.10.1） 【相続人】4名（内1名譲渡契約書済み） 【相続財産】 不動産、預貯金、有価証券 約4～5千万 【相談内容】 既に協議が成立していて相続税について知りたいとの事 一般的なところの話になるかと思います 面談については再度折り返しいただき日程調整になると思います。 平日土曜どちらでも大丈夫で、藤沢希望です。 | O39: 無料相談にお越しください | P39: 藤沢支店 | Y39: =IF(R39="","", IF(AND(R39<TODAY(),W39=""),"未入力","")) | Z39: =COUNTIF($Y$9:Y39,"未入力") -> 0
A40: =Y40&Z40 -> 0 | B40: 32 | C40: 46070 | D40: 14：20 | E40: 久田 | F40: 横浜本店 | G40: HP | H40: すずき しゅういち様 | K40: 東京 | L40: 080-1123-1038 | M40: 遺言書 | N40: 遺言者：すずき様のお父様 推定相続人：すずき様、お母様、兄弟3名 計4名様 【財産内容】 不動産：マンション1室 預貯金：約3,000万円 株式：約3,000万円 公正証書遺言での作成をご希望されております。 遺言の内容としては、すずき様お一人に全財産を相続させたいとのご意向です。 なお、お父様はあまり外出ができないご状態のため、意思確認等はZoom面談をご希望されております。 また、遺言書の作成日については、公証人の出張対応を希望されています。 対応を急がれる傾向があり、ご希望どおりに進まないと感情的になられる場面も見受けられました。 メールアドレス：shu16470@gmail.com 電話番号：080-1123-1038 Zoom ミーティングに参加する https://us06web.zoom.us/j/82523178613?pwd=t9ebKUSHu45sGzpshelrjiaMqRPdmZ.1 ミーティング ID: 825 2317 8613 パスコード: 145094 ☆クレアの方へ ご提示いただいたメールアドレス宛にZoomのご案内を送付いたしましたが、送信エラーとなり、送付することができませんでした。 そのため、恐れ入りますが、明日の朝一ですずき様へ再度メールアドレスのご確認のため、ご連絡いただきますようお願いいたします。（小川さんにお伝え済み） →対応済 2/18 渡部 再度フリーにTELあり。メール不明との事で上記shuのアドレスに案内を送信しております。(口頭でアドレスの再確認をとってます) 2/25上村 | O40: 無料相談にお越しください | P40: その他 | Q40: Zoom | R40: 46078 | S40: 火 | T40: 10：00 | U40: 馬場 | W40: Ａ：見込み高・後追い要 | X40: お父様の公正証書遺言作成のご相談。 2/25に見積書を送ってご返答待ち。 | Y40: =IF(R40="","", IF(AND(R40<TODAY(),W40=""),"未入力","")) | Z40: =COUNTIF($Y$9:Y40,"未入力") -> 0
A41: =Y41&Z41 -> 0 | B41: 33 | C41: 46070 | D41: 15：15 | E41: 宮田 | F41: 横浜本店 | G41: HP | H41: 男性 | K41: 横浜 | L41: 090-4125-6887 | M41: その他 | N41: 遺産分割協議書とは何かと言われ、お話をしたら「おっけわかった」と切られてしまいました。 | Y41: =IF(R41="","", IF(AND(R41<TODAY(),W41=""),"未入力","")) | Z41: =COUNTIF($Y$9:Y41,"未入力") -> 0
A42: =Y42&Z42 -> 0 | B42: 34 | C42: 46070 | D42: 16：00 | E42: 菅家 | F42: 横浜本店 | G42: HP | H42: 男性 | K42: 横浜 | L42: 090-3682-0045 | M42: その他 | N42: 貸付金の利息についてのご相談 もともと相談者が経営していた会社を息子に受け継ぎ、現在貸付金が3000万円ほどある。息子と少しもめているとのことですが、こちらは公証役場ではないとお伝えしたところ、じゃあ大丈夫です。と終話しております。 | Y42: =IF(R42="","", IF(AND(R42<TODAY(),W42=""),"未入力","")) | Z42: =COUNTIF($Y$9:Y42,"未入力") -> 0
A43: =Y43&Z43 -> 0 | B43: 35 | C43: 46071 | D43: 12：30 | E43: 菅家 | F43: 横浜本店 | G43: HP | H43: ほくやま せいこ様 ※おくやまかもしれません | K43: 横浜 | L43: 080-3449-9665 | M43: その他 | N43: 土地国庫帰属制度の相談 北海道に原野を持っており、扱いに困っているとのこと。 土地のみで家屋は立っておらず更地。土地国庫が使用できるのか、それともご売却を検討するのか含めて無料相談をご案内しました。 相談にくる人数等を確認して、改めてご連絡いただくこととなりました。 | O43: 無料相談にお越しください | Y43: =IF(R43="","", IF(AND(R43<TODAY(),W43=""),"未入力","")) | Z43: =COUNTIF($Y$9:Y43,"未入力") -> 0
A44: =Y44&Z44 -> 0 | B44: 36 | C44: 46071 | D44: 15：50 | E44: 上村 | F44: 横浜本店 | G44: HP | H44: たかはし | K44: 埼玉 浦和 | L44: 070-5376-1366 | M44: 生前対策 | N44: 浦和在住の方。身元保証について相談したいと伺うものの一般社団法人身元保証協会(東京丸の内にある)と間違えてご連絡をいただく形。 一般社団法人身元保証相談士協会であることをお伝えのうえ、身元保証は弊事務所で十分な対応が可能であって、一度ご相談にお越しいただきたいとご提案も 場所で難色を示される。(横浜なのねというトーン) 身元保証の団体は多いのねとご納得され、もし合わなければ連絡いただけるとおっしゃり終話。 | Y44: =IF(R44="","", IF(AND(R44<TODAY(),W44=""),"未入力","")) | Z44: =COUNTIF($Y$9:Y44,"未入力") -> 0
A45: =Y45&Z45 -> 0 | B45: 37 | C45: 46071 | D45: 17：10 | E45: 上村 | F45: 横浜本店 | G45: HP | H45: さくらい やすこ | K45: 武蔵野市 | L45: 080-5509-9188 | M45: 生前対策 | N45: 武蔵野市在住。女性。 TEL 080-5509-9188 生前対策の相談。 籍は入れてないが、資産家の男性(74歳)と交際しており、 近い将来、相談者も交際相手と籍を入れることを考えているといった状況。 自身の子は既に交際相手と養子縁組している。 相談経緯としては、交際相手が高齢、持病(糖尿病)、最近になり足も衰え10分程度しか 歩行できない状況となっており、万が一のことがあった場合、養子縁組した自身の連れ子や (仮に入籍した場合)自身の影響があるのではないかと思ったというところから。 交際相手は4人兄弟。(兄1名、弟2人という構成) ------資産は下記の通り------- 【不動産】 ①マンション1棟 ※兄と半分で共有。持分反映させて2億円ほど。 ②アパート1棟 ※交際相手100％名義。1億円ほど。 ※①、②とも東京都練馬区に所在。具体的な地名は伺えずも、 両物件とも練馬駅から徒歩7分程度の場所にあると仰せ。 【金融資産】 ・投資信託 ・預貯金あり ★不動産と金融資産併せて、4億5千万円ほどの資産有との事★ ------------------------------------- ・相談者の子(=相談者交際相手と養子縁組した子)は法人代表者であるとの事だが コロナ禍後からは法人として動いていないと仰せ。※法人自体は残している模様。 ・交際相手に万が一のことがあった場合を想定して、事前に不動産など、 子の法人に移した方が税金が少なくなったりするのか。 また仮に自身が交際相手と入籍したら税金負担少なくなるのか、 税金に限らず経済的にメリットになることはあるのかということを知りたいと仰せ。 ※若干人物感で懸念される部分があったので、配偶者控除については触れませんでした。 ・なお、相談者は、以前交際していた(入籍してない)人の年金を受け取っているとの事。 自身が死亡したときに何か税金関係の負担があるのか知りたいと予約取った後に仰せ。 ※全体的に怪しい雰囲気でしたが、最後に上記コメントがある、若干の片言で話す・・など 有り体に言えば胡散臭い人物ではあります。 ・渋谷を希望されてましたが、直近の相談枠埋まっているとお伝えし、横浜で予約を取ってます。 時間も15時が厳しそうなため、イレギュラーですが14時で取ってます。 (13時からだと前予定の移動時間に支障をきたす可能性ありのため) | O45: 無料相談にお越しください | P45: 横浜本店 | R45: 46073 | S45: 金 | T45: 14：00 | U45: 渡邉 | W45: Ａ：見込み高・後追い要 | X45: 主に専門性の高い税金のご相談。お客様のご希望もあり税理士の引き合わせを予定 | Y45: =IF(R45="","", IF(AND(R45<TODAY(),W45=""),"未入力","")) | Z45: =COUNTIF($Y$9:Y45,"未入力") -> 0
A46: =Y46&Z46 -> 0 | B46: 38 | C46: 46071 | D46: 18：16 | E46: 宮田 | F46: 横浜本店 | G46: HP | H46: さいた こうさく様 | K46: 横浜 | L46: 080-6596-6239 | M46: 遺言書 | N46: 【相談者】さいたこうさく様 【TEL】080-6596-6239 【遺言者】お父様 【家族構成】5人家族（内子ども3名）（こうさく様と妹様2名） 【相続財産】マンションと少しの預貯金 【相談内容】 遺言書の作成をしたい ただ、もめそうな気がするから公的なもので作成したい（公正証書遺言） よろしくお願いいたします。 | O46: 無料相談にお越しください | P46: 横浜本店 | R46: 46073 | S46: 金 | T46: 10：00 | U46: 梅澤 | W46: Ａ：見込み高・後追い要 | X46: 公正証書遺言作成希望。 相談者は独身、父母と同居。妹が2人いる。いずれも結婚して家を出ている。 父が、祖父の相続の時に妹と揉めた経験があるので、自分の時には揉めさせたくないとの思いがあるという。 財産は不動産と預金。料金表提示済。料金にご納得いただけたら、次回面談には父親本人が参加する予定。 | Y46: =IF(R46="","", IF(AND(R46<TODAY(),W46=""),"未入力","")) | Z46: =COUNTIF($Y$9:Y46,"未入力") -> 0
A47: =Y47&Z47 -> 0 | B47: 39 | C47: 46072 | D47: 11：25 | E47: 上村 | F47: 横浜本店 | G47: HP | H47: いで てるかず | K47: 東京 | L47: 090-7276-7313 | M47: 相続手続き | N47: 【相談者】いで てるかず様 【TEL】090-7276-7313 【被相続人】父 R5年2月死亡 【相続人】姉・相談者(長男)・妹 の3人 ※母は先に死亡※ 【相続財産】 ・不動産：①農地 ②貸地(薬局) ③貸地(運送会社の駐車場) ④被相続人自宅(土地建物) ①～④は全て静岡県沼津市に所在している。広さ、評価額は不明。 ④の固定資産税が84万～85万程度との事※単純に1.4％の税率だとして6071万？ ④には現在、仕事をしていない妹が居住している。 なお、②のみ相続人3名の共有で相続登記をしているが その他は被相続人名義のまま ・金融資産：預貯金3000万円程度 銀行は凍結済も解約まで至ってない。 (その他) ・相続税は借金までして払っていると仰せ(妹だけかもしれませんが) 【相談内容】 ・他の相続人と話し合いがうまくいってない、そのため死亡から3年経過しても、分割協議がまとまらず困っている。 ・弁護士に相談も…と考えたが、まずは当事者間で協議をちゃんとしたいので、OCに相談に至ったという事情。 ・まず、不動産の分割で平行線。被相続人自宅に働いていない妹が住んでおり、出ていく行かないの話でもめそう また、姉からは相談者に対して農地を引き継いで(＆農家やれ※仕事変えろ)欲しいといわれていて困っている。 (上村からは3年経過してもまとまらないのは大変ですし、相続登記義務化もあるから動かないといけないですよねとお伝え) ・金融機関の解約も当然話が進んでいない ※おそらく相続税負担が大変な状況かとお見受けされる これもしっかりと協議したい。 【対応】 姉と一緒に相談したいとの事で、横浜or藤沢での面談を3月末ごろに希望。 姉と日程調整したうえで連絡を再度頂けると仰せ(差し支えなければ、上村宛に再度連絡くださいとお伝えしてます)。 予約は横浜の方が取りやすいかもとも事前にお伝えしてます。 ★2/27受電★ 3/12(木)10：00～ 渋谷支店でアポイント取りました | O47: 無料相談にお越しください | P47: 渋谷支店 | Y47: =IF(R47="","", IF(AND(R47<TODAY(),W47=""),"未入力","")) | Z47: =COUNTIF($Y$9:Y47,"未入力") -> 0
A48: =Y48&Z48 -> 0 | B48: 40 | K48: 横浜 | L48: 090-2251-0728 | M48: その他 | N48: 相談者の母の行方が分からず、母名義の不動産を処分したいのに困っていると。 オーシャンでお手伝いできることはない旨お伝えし終話しております。 | Y48: =IF(R48="","", IF(AND(R48<TODAY(),W48=""),"未入力","")) | Z48: =COUNTIF($Y$9:Y48,"未入力") -> 0
A49: =Y49&Z49 -> 0 | B49: 40 | C49: 46073 | D49: 9：45 | E49: 宮田 | F49: 横浜本店 | G49: HP | H49: きたむら あきこ様 | K49: 川崎 | L49: 0801248-1406 | M49: 相続手続き | N49: 【相談者】きたむらあきこ様 【TEL】080-1248-1406 【被相続人】お父様（R7.11) 【相続人】お母様、ご子息様、お嬢様（あきこ様）計3名 【相続財産】 不動産：自宅の土地建物 ＠藤沢 3,380万円 預貯金：2,900万円 その他：還付金 868千円 生命保険：800万円 受取人：お母様 【相談内容】 藤沢の平安で式を挙げた。 その後兄の知り合い？の事務所に色々と相続手続きについて聞いてみて見積をもらったところ878千円（遺産承継？）と聞いて「高すぎる！！！」となっているとの事。 これが妥当かどうか確認の為、相見積もりとして弊社を選んでくださいました。 その事務所によると、相続財産は計7,300万円と仰っており、生命保険も加算された金額になっていると思われる。 また、ご子息様は現在60歳で障害者手帳3級を持っているため相続税はかからないと説明されたとの事でした。 相続手続きは任せるご意向でしたので、安ければお願いする可能性が高いかもしれません。 よろしくお願いいたします。 | O49: 無料相談にお越しください | P49: 藤沢支店 | R49: 46080 | S49: 金 | T49: 10：00 | U49: 藤田 | W49: Ａ：見込み高 | X49: ベストファーム行・税にて既にご相談・ご契約された方のご相談。 遺産承継のご契約をされていたようなので、全体の内容を確認しつつ、 弊所での遺産承継費用・一般相続手続き費用（解約込）をご案内。 先方のご提示よりも良い内容・金額をご案内できたかと思います。 ご家族でご検討されるとのこと。 | Y49: =IF(R49="","", IF(AND(R49<TODAY(),W49=""),"未入力","")) | Z49: =COUNTIF($Y$9:Y49,"未入力") -> 0
A50: =Y50&Z50 -> 0 | B50: 41 | C50: 46073 | D50: 18：00 | E50: 栗田 | F50: 横浜本店 | G50: HP | H50: こみや ひろつぐ様 | K50: 藤沢 | L50: 090-3536-9684 | M50: 生前対策 | N50: 相続はまだ開始していないそうですが、これからの対策も含め相談したいとのこと 父 ガン 母 認知症（重度） 推定相続人：こみや様、姉、兄、弟 ※姉と兄が結託してこみや様と仲が悪くなっている 財産内容：不動産 マンション一棟 預金 相談内容：土地は元々母60％、父20％、兄20％だったが、こみや様に内緒で母の名義を兄へ変更してしまった。建物自体は父名義。通帳も兄と姉が持っているので分からない。 登記簿を取得したとのことですので当日見て欲しいとのことです。 | O50: 無料相談にお越しください | P50: 横浜本店 | R50: 46080 | S50: 金 | T50: 10：00 | U50: 馬場 | W50: Ｂ：見込み低 | X50: 母→息子への贈与の無効訴えを行うかもしれなく、弁護士をご紹介する事になりました。 | Y50: =IF(R50="","", IF(AND(R50<TODAY(),W50=""),"未入力","")) | Z50: =COUNTIF($Y$9:Y50,"未入力") -> 0
A51: =Y51&Z51 -> 0 | B51: 42 | C51: 46074 | D51: 10：00 | E51: 菅家 | F51: 横浜本店 | G51: HP | H51: 女性 | K51: 横浜 | L51: 090-2458-1850 | M51: 名義変更 | N51: 相続登記についてのお問い合わせ 現在相続手続きを司法書士に依頼をしている。忙しく司法書士に連絡ができておらずHPをみて電話をしたと。 遺産分割協議書について質問をされたので、一般的なことをお答えし、詳細は依頼している司法書士にお話ししてくださいとお伝えし終話しております。 | Y51: =IF(R51="","", IF(AND(R51<TODAY(),W51=""),"未入力","")) | Z51: =COUNTIF($Y$9:Y51,"未入力") -> 0
A52: =Y52&Z52 -> 0 | B52: 43 | C52: 46074 | D52: 11：00 | E52: 栗田 | F52: 横浜本店 | G52: HP | H52: あんざい よしの様 | K52: 横浜 | L52: 090-8088-2044 | M52: その他 | N52: 親族から住んでいる家の立ち退きを口頭で伝えられたから相談したい 相談者と姉が住んでいる家（所有者はおそらく祖母）から立ち退いてほしいと、祖母の娘（おば）から口頭で伝えられた 祖母は要介護認定を受けていて、特養に入居している。おそらく施設の費用の捻出のために、不動産を売却したいのではないか ただ、正式な書面や代理人からの連絡が来たわけではない。 弁護士との引き合わせをご提案しましたが、具体的なリアクションがあってから相談いただくことになりました。 具体的なリアクション（正式な書面や代理人からの受任通知など）があれば再度連絡をいただくかもしれません。 | O52: パートナー弁護士をご紹介します | Y52: =IF(R52="","", IF(AND(R52<TODAY(),W52=""),"未入力","")) | Z52: =COUNTIF($Y$9:Y52,"未入力") -> 0
A53: =Y53&Z53 -> 0 | B53: 44 | C53: 46076 | D53: 0.45833333 | E53: 菅家 | F53: 横浜本店 | G53: HP | H53: 男性 | K53: 横浜 | L53: 080-6562-7333 | M53: その他 | N53: 生前贈与で取得した不動産の確定申告等の税務についてのご相談 オーシャンで提携している税理士のご紹介になる旨説明。 面談の候補日程を確認してから再度連絡しますとのこと。 | O53: 税理士をご紹介します | Y53: =IF(R53="","", IF(AND(R53<TODAY(),W53=""),"未入力","")) | Z53: =COUNTIF($Y$9:Y53,"未入力") -> 0
A54: =Y54&Z54 -> 0 | B54: 45 | C54: 46077 | D54: 14：00 | E54: 安井 | F54: 横浜本店 | G54: HP | H54: まつもと たつや様 | K54: 横浜 | L54: 090-7329-9593 | M54: 相続手続き | N54: 被相続人：お父様（お電話いただいた日から計算して先週にご逝去） 相続人：お母様、まつもと様含めお子様2名の計3名様 相続財産：預貯金及び証券のみ お困りごと：相続手続きについて、必要な戸籍の収集等不明点が多いのでご相談されたいとのこと。預金については未だご連絡しておらず、証券会社には25日にご連絡して書類の取り寄せをしようとしていらっしゃるそうです。 090-7329-9593 3/3 まつもと様からお電話あり 自分でなんとかできそうな状況になったということでキャンセルになりました。（安井） | O54: 無料相談にお越しください | P54: 藤沢支店 | Y54: =IF(R54="","", IF(AND(R54<TODAY(),W54=""),"未入力","")) | Z54: =COUNTIF($Y$9:Y54,"未入力") -> 0
A55: =Y55&Z55 -> 0 | B55: 46 | C55: 46077 | D55: 14：47 | E55: 宮田 | F55: 横浜本店 | G55: HP | H55: きし しんじ様 | K55: 横浜 | L55: 090-9672-0908 | M55: 遺言書 | N55: 【相談者】きししんじ様 【TEL】090-9672-0908 【相談内容】 遺言書の作成を行いたい 銀行に聞いたところ、銀行では数十万とかだから少し高いと感じてしまったとの事でした。 また、公正証書遺言の手数料について気になってたので、「相続財産の金額によって変動します」とお伝えしたところ、「2～3億円」とおっしゃっておりました。 尚、詳細についてヒアリングしようとしましたが、逃げられそうだったので無料相談の日程調整に切り替えました。恐れ入りますが、詳細については当日にヒアリングをお願いします。 | O55: 無料相談にお越しください | P55: 横浜本店 | R55: 46086 | S55: 木 | T55: 10：00 | U55: 渡邉 | W55: Ａ：見込み高 | X55: 遺言書作成のご相談。すでに銀行でお話を聞いておりお詳しい状態であった。公正証書遺言の検討もあったが、書き換えも予定にあることから弊所で文案を作成して自身で転記する方法が最も濃厚な選択肢。費用感を気にされていて奥様にご相談するとのこと。 | Y55: =IF(R55="","", IF(AND(R55<TODAY(),W55=""),"未入力","")) | Z55: =COUNTIF($Y$9:Y55,"未入力") -> 0
A56: =Y56&Z56 -> 0 | B56: 47 | C56: 46077 | D56: 15：00 | E56: 安井 | F56: 横浜本店 | G56: HP | H56: 男性 | K56: 東京 | L56: 090-9685-8885 | M56: 名義変更 | N56: 被相続人：お父様（今月にご逝去） 相続人：お母様、相談者含むお子様4名の計5名様 相続財産：ご自宅の土地、建物の持分 お困りごと：平日に休みが無い為専門家に手続きを依頼しようか検討している 資料が無いと無料相談できないのか？とのお問い合わせでしたので、無くても対応はできるが具体的な数字のお伝えができない部分があるかもしれないと回答。固定資産税の納税通知書は捨ててしまったそうで、今年度の分が届いてから改めて相談したいということで終話しました。 | O56: 無料相談にお越しください | P56: 横浜本店 | Y56: =IF(R56="","", IF(AND(R56<TODAY(),W56=""),"未入力","")) | Z56: =COUNTIF($Y$9:Y56,"未入力") -> 0
A57: =Y57&Z57 -> 0 | B57: 48 | C57: 46077 | D57: 16：50 | E57: 小泉 | F57: 横浜本店 | G57: HP | H57: くぬぎ たつや様 | K57: 東京 | L57: 070-4564-9552 | M57: 遺言書 | N57: ※たつや様かたつき様か曖昧です、すみません。→功刀達也(くぬぎたつや)様 相談者電話番号：070-4564-9552 相談者：くぬぎ たつや様 遺言者の長男 【相談内容】 お母様の遺言書作成のご相談 当日は来ることが出来ず、ご長男様のみ来所されます。 | O57: 無料相談にお越しください | P57: 渋谷支店 | R57: 46083 | S57: 月 | T57: 14：00 | U57: 梅澤 | W57: Ｂ：見込み低 | X57: 父の相続の時に姉と揉めて調停になったので、母に遺言を書いてほしいとの希望あり。 母の資産は目黒の自宅マンション(持分約2分の1)と預貯金約150万円。 契約者は母となることを説明。公正証書遺言の料金を提示しています。 年齢は91歳でも買い物にも出かけているので、公証役場へ出向くのは可能。 | Y57: =IF(R57="","", IF(AND(R57<TODAY(),W57=""),"未入力","")) | Z57: =COUNTIF($Y$9:Y57,"未入力") -> 0
A58: =Y58&Z58 -> 0 | B58: 49 | C58: 46078 | D58: 9：45 | E58: 宮田 | F58: 横浜本店 | G58: HP | H58: きむら なおみ様 | K58: 横浜 | L58: 090-1595-7888 | M58: 遺言書 | N58: 【相談者】きむらなおみ様 【TEL】090-1595-7888 【遺言者】きむらなおみ様（お母様） 【相続財産】 自宅マンション（娘二人と3名で共有名義）、預貯金 【相談内容】 公的な遺言書を作成したい。 また、マンションにはお母様名義で借入金があり、娘名義に変えると贈与税がかかってしまう。 そのため、遺言書で税金対策などをしたいから教えてほしいとの事。 不動産は売買価格で4,800万円から5,800万円とのこと。 よろしくお願いいたします。 | O58: 無料相談にお越しください | P58: 横浜本店 | R58: 46086 | S58: 木 | T58: 10：00 | U58: 齋藤 | W58: Ｓ：即受注 | X58: 遺言 | Y58: =IF(R58="","", IF(AND(R58<TODAY(),W58=""),"未入力","")) | Z58: =COUNTIF($Y$9:Y58,"未入力") -> 0
A59: =Y59&Z59 -> 0 | B59: 50 | C59: 46078 | D59: 16：40 | E59: 上村 | F59: 横浜本店 | G59: HP | H59: なかじま やすこ | K59: 東京都世田谷区 | L59: 090-8748-4708 | M59: 名義変更 | N59: 【相談者】なかじま やすこ様 【TEL】09-8748-4708 【相談内容】 生前対策。夫名義の自宅マンションを自分名義にする話が過去からあった。 婚姻後20年たったら何かしらの控除があるときいたので 税制的なメリット、どのタイミングで名義変更した方がいいのか 依頼となったら費用感、期間を相談したい。 ・マンション概要：世田谷区に所在 最寄り駅は尾山台。平米数は60㎡弱 家族で居住している ※尾山台ならそれなりの高級住宅街です・・ 面談は横浜でも渋谷でも可でしたが、 渋谷は移転準備中で・・を申し伝えたところ横浜がいいとなりました) お姉さまと一緒に相談したい、3/9～の週希望。 お姉さまと日程確認して連絡いただける | O59: "相談者からの連絡待ち (日程調整)" | P59: 横浜本店 | Y59: =IF(R59="","", IF(AND(R59<TODAY(),W59=""),"未入力","")) | Z59: =COUNTIF($Y$9:Y59,"未入力") -> 0
A60: =Y60&Z60 -> 0 | B60: 51 | C60: 46079 | D60: 18：00 | E60: 上田 | F60: 横浜本店 | G60: HP | H60: かい のぶゆき様 | K60: 横浜 | L60: 090-7737-3226 | M60: 遺言書 | N60: 遺言者：母 推定相続人：長男の子2名、次男、三男（CL)、長女 相続財産：不動産、預金 長女は生活保護を受けていて、母から今まで2000万円ほど援助をしてもらっている。 次男は母を騙し？土地を安く買った。(法人名義で購入）また、300万円くらい残高があった母名義の口座の通帳を引き出し、不動産所得税として使った。(実際の所得税は150万くらい） 不動産はCL？に残すかなという予定、預金はまだ未定。 遺留分のことも考えてどうするかも相談したい。 日程調整してまたご連絡いただけます。 | O60: 無料相談にお越しください | P60: 横浜本店 | Y60: =IF(R60="","", IF(AND(R60<TODAY(),W60=""),"未入力","")) | Z60: =COUNTIF($Y$9:Y60,"未入力") -> 0
A61: =Y61&Z61 -> 0 | B61: 52 | C61: 46081 | D61: 11：58 | E61: 上村 | F61: 横浜本店 | G61: HP | H61: やまだ こずえ様 | K61: 東京都稲城市 | L61: 090-6174-6847 | M61: 遺言書 | N61: 相談者：山田 こずえ様 遺言者：山田 進様 (すすむ) 相談者の夫 住所：東京都稲城市 相談者TEL 090-6174-6847 遺言書の作成の相談。 (困りごと) ①夫の体調が芳しくない状況(現在退院しているが、緩和ケアに入る様子) ②ご子息が3名いらっしゃるが、真ん中の子(次男)がまったく連絡が取れなくて困っている。 大きな財産があるわけではないが、万が一の時のためにしっかりと遺言書を残したい。 他事務所に相談したところ、遺言書は早くても4月以降になってしまう＆危急時遺言は難しいと言われてしまった。 (お伝えしたこと) ①遺言書については公正証書遺言にする形、公証役場の混雑次第に左右される要素が大きいので、4月以降になることは十分にあり得る。 ②危急時遺言の対応は可能である。 公正証書遺言を作成準備中の方の容態が急変して、危急時遺言をされた方もいらっしゃるので (R8-Y02A055の事例を念頭に) まず一度相談にお越しくださいとお伝えし、横浜本店での面談アポイントを取りました。 ※渋谷でなくてOkとの事※ (その他伺った事情) ・次男様は自身の離婚後、相談者夫婦と連絡が取れなくなった様子 (携帯電話番号も変えられた) ・財産状況は預貯金、株、こども保険の3種 不動産は無し ※相談者夫婦はご子息名義の家に居住(居候と仰せでした) ・ご相談は夫とお二人でお見えになられます。 ・少し相談日が先になったのは、夫の通院の都合と、ご夫婦で旅行に行きたい(最後の旅行というニュアンス)という事情からです。 ・お車でお越しになられるとの事で、提携駐車場の用意がないことはお伝え済みです。 | O61: 無料相談にお越しください | P61: 横浜本店 | R61: 46091 | S61: 火 | T61: 14：00 | U61: 花井 | W61: Ａ：見込み高・後追い要 | X61: 息子（二男）が行方知れずとなってしまっており、万が一の際に相続手続が進まなくなることを懸念して遺言作成の相談に来所。 同日ご本人（進様）についても同席。当初は危急時遺言の作成についての相談であったが、本人は間違いなく遺言能力もあり、自筆証書遺言を作成できる状態であったことから、公正証書遺言の作成とそれまでのつなぎとして自筆証書遺言の作成をご提案。 一度検討のうえ、返答となる。 | Y61: =IF(R61="","", IF(AND(R61<TODAY(),W61=""),"未入力","")) | Z61: =COUNTIF($Y$9:Y61,"未入力") -> 0
A62: =Y62&Z62 -> 0 | B62: 53 | C62: 46079 | E62: 久田 | F62: 横浜本店 | G62: HP | H62: わたなべ かの様 | M62: 相続放棄 | N62: 被相続人：わたなべ様の旦那様の叔母様 相続人：関係が複雑なため、鹿児島市より届いた相関図をお持ちいただけるとのこと。 生前、叔母様は鹿児島市から被ばく者保険金を受け取っていた。ご逝去された後も保険金が支払いがされ続けていたため、そのお金を回収する協力願いの書類がわたなべ様の旦那様宛に届いたそうです。書類が届いてからは1ヶ月ほど経っているとのこと。 相続放棄するべきなのかも含めてご相談されたいそうです。 当日は、鹿児島市から届いた通知書をお持ちいただけます。 旦那様とお二人でご来所予定です。 | O62: 無料相談にお越しください | P62: 横浜本店 | R62: 46081 | S62: 土 | T62: 17：00 | U62: 山﨑 | W62: Ｓ：即受注 | X62: 相続放棄で受任 | Y62: =IF(R62="","", IF(AND(R62<TODAY(),W62=""),"未入力","")) | Z62: =COUNTIF($Y$9:Y62,"未入力") -> 0
A63: =Y63&Z63 -> 0 | B63: 54 | M63: 相続放棄 | Y63: =IF(R63="","", IF(AND(R63<TODAY(),W63=""),"未入力","")) | Z63: =COUNTIF($Y$9:Y63,"未入力") -> 0
A64: =Y64&Z64 -> 0 | B64: 55 | Y64: =IF(R64="","", IF(AND(R64<TODAY(),W64=""),"未入力","")) | Z64: =COUNTIF($Y$9:Y64,"未入力") -> 0
A65: =Y65&Z65 -> 0 | B65: 56 | Y65: =IF(R65="","", IF(AND(R65<TODAY(),W65=""),"未入力","")) | Z65: =COUNTIF($Y$9:Y65,"未入力") -> 0
A66: =Y66&Z66 -> 0 | B66: 57 | Y66: =IF(R66="","", IF(AND(R66<TODAY(),W66=""),"未入力","")) | Z66: =COUNTIF($Y$9:Y66,"未入力") -> 0
A67: =Y67&Z67 -> 0 | B67: 58 | Y67: =IF(R67="","", IF(AND(R67<TODAY(),W67=""),"未入力","")) | Z67: =COUNTIF($Y$9:Y67,"未入力") -> 0
A68: =Y68&Z68 -> 0 | B68: 59 | Y68: =IF(R68="","", IF(AND(R68<TODAY(),W68=""),"未入力","")) | Z68: =COUNTIF($Y$9:Y68,"未入力") -> 0
A69: =Y69&Z69 -> 0 | B69: 60 | Y69: =IF(R69="","", IF(AND(R69<TODAY(),W69=""),"未入力","")) | Z69: =COUNTIF($Y$9:Y69,"未入力") -> 0
A70: =Y70&Z70 -> 0 | B70: 61 | Y70: =IF(R70="","", IF(AND(R70<TODAY(),W70=""),"未入力","")) | Z70: =COUNTIF($Y$9:Y70,"未入力") -> 0
A71: =Y71&Z71 -> 0 | B71: 62 | Y71: =IF(R71="","", IF(AND(R71<TODAY(),W71=""),"未入力","")) | Z71: =COUNTIF($Y$9:Y71,"未入力") -> 0
A72: =Y72&Z72 -> 0 | B72: 63 | Y72: =IF(R72="","", IF(AND(R72<TODAY(),W72=""),"未入力","")) | Z72: =COUNTIF($Y$9:Y72,"未入力") -> 0
A73: =Y73&Z73 -> 0 | B73: 64 | Y73: =IF(R73="","", IF(AND(R73<TODAY(),W73=""),"未入力","")) | Z73: =COUNTIF($Y$9:Y73,"未入力") -> 0
A74: =Y74&Z74 -> 0 | B74: 65 | Y74: =IF(R74="","", IF(AND(R74<TODAY(),W74=""),"未入力","")) | Z74: =COUNTIF($Y$9:Y74,"未入力") -> 0
A75: =Y75&Z75 -> 0 | B75: 66 | Y75: =IF(R75="","", IF(AND(R75<TODAY(),W75=""),"未入力","")) | Z75: =COUNTIF($Y$9:Y75,"未入力") -> 0
... A207: =Y207&Z207 -> 0 | B207: 200 | Y207: =IF(R207="","", IF(AND(R207<TODAY(),W207=""),"未入力","")) | Z207: =COUNTIF($Y$9:Y207,"未入力") -> 0
D209: 総計 | E209: 横浜本店 | F209: 藤沢支店 | G209: 渋谷支店 | H209: お客様先 | I209: パートナー先 | J209: =設定用!F11 -> その他
B210: 面談対応件数 | D210: =SUM(E210:J210) -> 26 | E210: =COUNTIFS($P$9:$P$207,E$209,$W$9:$W$207,"<>") -> 16 | F210: =COUNTIFS($P$9:$P$207,F$209,$W$9:$W$207,"<>") -> 5 | G210: =COUNTIFS($P$9:$P$207,G$209,$W$9:$W$207,"<>") -> 3 | H210: =COUNTIFS($P$9:$P$207,H$209,$W$9:$W$207,"<>") -> 0 | I210: =COUNTIFS($P$9:$P$207,I$209,$W$9:$W$207,"<>") -> 0 | J210: =COUNTIFS($P$9:$P$207,J$209,$W$9:$W$207,"<>") -> 2
B211: 即受注件数 | D211: =SUM(E211:J211) -> 7 | E211: =COUNTIFS($P$9:$P$207,E$209,$W$9:$W$207,$O$2) -> 4 | F211: =COUNTIFS($P$9:$P$207,F$209,$W$9:$W$207,$O$2) -> 2 | G211: =COUNTIFS($P$9:$P$207,G$209,$W$9:$W$207,$O$2) -> 0 | H211: =COUNTIFS($P$9:$P$207,H$209,$W$9:$W$207,$O$2) -> 0 | I211: =COUNTIFS($P$9:$P$207,I$209,$W$9:$W$207,$O$2) -> 0 | J211: =COUNTIFS($P$9:$P$207,J$209,$W$9:$W$207,$O$2) -> 1
B212: 戻り受注件数 | D212: =SUM(E212:J212) -> 0 | E212: =COUNTIFS($P$9:$P$207,E$209,$W$9:$W$207,$O$3) -> 0 | F212: =COUNTIFS($P$9:$P$207,F$209,$W$9:$W$207,$O$3) -> 0 | G212: =COUNTIFS($P$9:$P$207,G$209,$W$9:$W$207,$O$3) -> 0 | H212: =COUNTIFS($P$9:$P$207,H$209,$W$9:$W$207,$O$3) -> 0 | I212: =COUNTIFS($P$9:$P$207,I$209,$W$9:$W$207,$O$3) -> 0 | J212: =COUNTIFS($P$9:$P$207,J$209,$W$9:$W$207,$O$3) -> 0
B213: 受注率 | D213: =IFERROR(SUM(D211:D212)/D210,"") -> 0.26923077 | E213: =IFERROR(SUM(E211:E212)/E210,"") -> 0.25 | F213: =IFERROR(SUM(F211:F212)/F210,"") -> 0.4 | G213: =IFERROR(SUM(G211:G212)/G210,"") -> 0 | H213: =IFERROR(SUM(H211:H212)/H210,"") | I213: =IFERROR(SUM(I211:I212)/I210,"") | J213: =IFERROR(SUM(J211:J212)/J210,"") -> 0.5 | K213: ※面談場所ベース | L213: =IFERROR(SUM(L211:L212)/L210,"") | M213: =IFERROR(SUM(M211:M212)/M210,"")
D216: =設定用!J6 -> 代表 | E216: =設定用!J7 -> 黒田み | F216: =設定用!J8 -> 山田 | G216: =設定用!J9 -> 奥章 | H216: =設定用!J10 -> 山﨑
C217: 面談数 | D217: =COUNTIF($U$9:$U$207,D216) -> 0 | E217: =COUNTIF($U$9:$U$207,E216) -> 0 | F217: =COUNTIF($U$9:$U$207,F216) -> 1 | G217: =COUNTIF($U$9:$U$207,G216) -> 0 | H217: =COUNTIF($U$9:$U$207,H216) -> 2
C218: 受注数 | D218: =SUM(D220,D222) -> 0 | E218: =SUM(E220,E222) -> 0 | F218: =SUM(F220,F222) -> 1 | G218: =SUM(G220,G222) -> 0 | H218: =SUM(H220,H222) -> 2
D219: =IFERROR(D218/D217,"-") -> - | E219: =IFERROR(E218/E217,"-") -> - | F219: =IFERROR(F218/F217,"-") -> 1 | G219: =IFERROR(G218/G217,"-") -> - | H219: =IFERROR(H218/H217,"-") -> 1
C220: Ｓ：即受注 | D220: =COUNTIFS($U$9:$U$207,D$216,$W$9:$W$207,$C220) -> 0 | E220: =COUNTIFS($U$9:$U$207,E$216,$W$9:$W$207,$C220) -> 0 | F220: =COUNTIFS($U$9:$U$207,F$216,$W$9:$W$207,$C220) -> 1 | G220: =COUNTIFS($U$9:$U$207,G$216,$W$9:$W$207,$C220) -> 0 | H220: =COUNTIFS($U$9:$U$207,H$216,$W$9:$W$207,$C220) -> 2
D221: =IFERROR(D220/D217,"-") -> - | E221: =IFERROR(E220/E217,"-") -> - | F221: =IFERROR(F220/F217,"-") -> 1 | G221: =IFERROR(G220/G217,"-") -> - | H221: =IFERROR(H220/H217,"-") -> 1
C222: Ｓ：戻り受注 | D222: =COUNTIFS($U$9:$U$207,D$216,$W$9:$W$207,$C222) -> 0 | E222: =COUNTIFS($U$9:$U$207,E$216,$W$9:$W$207,$C222) -> 0 | F222: =COUNTIFS($U$9:$U$207,F$216,$W$9:$W$207,$C222) -> 0 | G222: =COUNTIFS($U$9:$U$207,G$216,$W$9:$W$207,$C222) -> 0 | H222: =COUNTIFS($U$9:$U$207,H$216,$W$9:$W$207,$C222) -> 0
D223: =IFERROR(D222/D217,"-") -> - | E223: =IFERROR(E222/E217,"-") -> - | F223: =IFERROR(F222/F217,"-") -> 0 | G223: =IFERROR(G222/G217,"-") -> - | H223: =IFERROR(H222/H217,"-") -> 0
C224: Ａ：見込み高 | D224: =COUNTIFS($U$9:$U$207,D$216,$W$9:$W$207,$C224) -> 0 | E224: =COUNTIFS($U$9:$U$207,E$216,$W$9:$W$207,$C224) -> 0 | F224: =COUNTIFS($U$9:$U$207,F$216,$W$9:$W$207,$C224) -> 0 | G224: =COUNTIFS($U$9:$U$207,G$216,$W$9:$W$207,$C224) -> 0 | H224: =COUNTIFS($U$9:$U$207,H$216,$W$9:$W$207,$C224) -> 0
D225: =IFERROR(D224/D$217,"-") -> - | E225: =IFERROR(E224/E$217,"-") -> - | F225: =IFERROR(F224/F$217,"-") -> 0 | G225: =IFERROR(G224/G$217,"-") -> - | H225: =IFERROR(H224/H$217,"-") -> 0
C226: Ｂ：見込み低 | D226: =COUNTIFS($U$9:$U$207,D$216,$W$9:$W$207,$C226) -> 0 | E226: =COUNTIFS($U$9:$U$207,E$216,$W$9:$W$207,$C226) -> 0 | F226: =COUNTIFS($U$9:$U$207,F$216,$W$9:$W$207,$C226) -> 0 | G226: =COUNTIFS($U$9:$U$207,G$216,$W$9:$W$207,$C226) -> 0 | H226: =COUNTIFS($U$9:$U$207,H$216,$W$9:$W$207,$C226) -> 0
D227: =IFERROR(D226/D$217,"-") -> - | E227: =IFERROR(E226/E$217,"-") -> - | F227: =IFERROR(F226/F$217,"-") -> 0 | G227: =IFERROR(G226/G$217,"-") -> - | H227: =IFERROR(H226/H$217,"-") -> 0
C228: Ｃ：シート渡せず | D228: =COUNTIFS($U$9:$U$207,D$216,$W$9:$W$207,$C228) -> 0 | E228: =COUNTIFS($U$9:$U$207,E$216,$W$9:$W$207,$C228) -> 0 | F228: =COUNTIFS($U$9:$U$207,F$216,$W$9:$W$207,$C228) -> 0 | G228: =COUNTIFS($U$9:$U$207,G$216,$W$9:$W$207,$C228) -> 0 | H228: =COUNTIFS($U$9:$U$207,H$216,$W$9:$W$207,$C228) -> 0
D229: =IFERROR(D228/D$217,"-") -> - | E229: =IFERROR(E228/E$217,"-") -> - | F229: =IFERROR(F228/F$217,"-") -> 0 | G229: =IFERROR(G228/G$217,"-") -> - | H229: =IFERROR(H228/H$217,"-") -> 0
C230: Ｄ：対応不可能 | D230: =COUNTIFS($U$9:$U$207,D$216,$W$9:$W$207,$C230) -> 0 | E230: =COUNTIFS($U$9:$U$207,E$216,$W$9:$W$207,$C230) -> 0 | F230: =COUNTIFS($U$9:$U$207,F$216,$W$9:$W$207,$C230) -> 0 | G230: =COUNTIFS($U$9:$U$207,G$216,$W$9:$W$207,$C230) -> 0 | H230: =COUNTIFS($U$9:$U$207,H$216,$W$9:$W$207,$C230) -> 0
D231: =IFERROR(D230/D$217,"-") -> - | E231: =IFERROR(E230/E$217,"-") -> - | F231: =IFERROR(F230/F$217,"-") -> 0 | G231: =IFERROR(G230/G$217,"-") -> - | H231: =IFERROR(H230/H$217,"-") -> 0
C232: Ｅ：他社紹介 | D232: =COUNTIFS($U$9:$U$207,D$216,$W$9:$W$207,$C232) -> 0 | E232: =COUNTIFS($U$9:$U$207,E$216,$W$9:$W$207,$C232) -> 0 | F232: =COUNTIFS($U$9:$U$207,F$216,$W$9:$W$207,$C232) -> 0 | G232: =COUNTIFS($U$9:$U$207,G$216,$W$9:$W$207,$C232) -> 0 | H232: =COUNTIFS($U$9:$U$207,H$216,$W$9:$W$207,$C232) -> 0
D233: =IFERROR(D232/D$217,"-") -> - | E233: =IFERROR(E232/E$217,"-") -> - | F233: =IFERROR(F232/F$217,"-") -> 0 | G233: =IFERROR(G232/G$217,"-") -> - | H233: =IFERROR(H232/H$217,"-") -> 0
D236: =設定用!J11 -> 鵜飼 | E236: =設定用!J12 -> 筆野 | F236: =設定用!J13 -> 岡田 | G236: =設定用!J14 -> 杉原 | H236: =設定用!J15 -> 時川 | I236: 嶋津 | J236: 馬場 | K236: 和田 | L236: 蔭山 | M236: 五十嵐 | N236: 伊藤 | O236: 新井
C237: 面談数 | D237: =COUNTIF($U$9:$U$207,D236) -> 0 | E237: =COUNTIF($U$9:$U$207,E236) -> 0 | F237: =COUNTIF($U$9:$U$207,F236) -> 0 | G237: =COUNTIF($U$9:$U$207,G236) -> 0 | H237: =COUNTIF($U$9:$U$207,H236) -> 0 | I237: =COUNTIF($U$9:$U$207,I236) -> 1 | J237: =COUNTIF($U$9:$U$207,J236) -> 2 | K237: =COUNTIF($U$9:$U$207,K236) -> 0 | L237: =COUNTIF($U$9:$U$207,L236) -> 0 | M237: =COUNTIF($U$9:$U$205,M236) -> 0 | N237: =COUNTIF($U$9:$U$205,N236) -> 0 | O237: =COUNTIF($U$9:$U$205,O236) -> 3
C238: 受注数 | D238: =SUM(D240,D242) -> 0 | E238: =SUM(E240,E242) -> 0 | F238: =SUM(F240,F242) -> 0 | G238: =SUM(G240,G242) -> 0 | H238: =SUM(H240,H242) -> 0 | I238: =SUM(I240,I242) -> 0 | J238: =SUM(J240,J242) -> 0 | K238: =SUM(K240,K242) -> 0 | ... O238: =SUM(O240,O242) -> 0
...

Sheet 3月
B2: ★2026年 3月 | J2: 総計 | L2: ★面談結果未入力 | O2: =設定用!H6 -> Ｓ：即受注
A3: 「」 | D3: 総計 | E3: =設定用!B6 -> 横浜本店 | F3: =設定用!B7 -> 藤沢支店 | G3: =設定用!B8 -> 渋谷支店 | I3: 面談対応件数 | J3: =D207 -> 39 | K3: 未入力1 | L3: =IFERROR("管理表番号（"&VLOOKUP(K3,$A$10:$U$203,2,FALSE)&"）／面談担当者："&VLOOKUP(K3,$A$10:$U$203,21,FALSE),"") -> 管理表番号（67）／面談担当者：山田 | O3: =設定用!H7 -> Ｓ：戻り受注
B4: 受信件数 | D4: =SUM(E4:I4) -> 68 | E4: =COUNTIF($F$9:$F$203,E3) -> 67 | F4: =COUNTIF($F$9:$F$203,F3) -> 1 | G4: =COUNTIF($F$9:$F$203,G3) -> 0 | I4: 即受注件数 | J4: =D208 -> 11 | K4: 未入力2 | L4: =IFERROR("管理表番号（"&VLOOKUP(K4,$A$10:$U$203,2,FALSE)&"）／面談担当者："&VLOOKUP(K4,$A$10:$U$203,21,FALSE),"")
B5: 面談予約件数 | D5: =SUM(E5:I5) -> 44 | E5: =COUNTIFS($F$9:$F$203,E3,$R$9:$R$203,"<>") -> 43 | F5: =COUNTIFS($F$9:$F$203,F3,$R$9:$R$203,"<>") -> 1 | G5: =COUNTIFS($F$9:$F$203,G3,$R$9:$R$203,"<>") -> 0 | I5: 戻り受注件数 | J5: =D209 -> 2 | K5: 未入力3 | L5: =IFERROR("管理表番号（"&VLOOKUP(K5,$A$10:$U$203,2,FALSE)&"）／面談担当者："&VLOOKUP(K5,$A$10:$U$203,21,FALSE),"")
B6: 面談獲得率 | D6: =IFERROR(D5/D4,"") -> 0.64705882 | E6: =IFERROR(E5/E4,"") -> 0.64179104 | F6: =IFERROR(F5/F4,"") -> 1 | G6: =IFERROR(G5/G4,"") | I6: 受注率 | J6: =D210 -> 0.33333333 | K6: 未入力4 | L6: =IFERROR("管理表番号（"&VLOOKUP(K6,$A$10:$U$203,2,FALSE)&"）／面談担当者："&VLOOKUP(K6,$A$10:$U$203,21,FALSE),"")
B8: ＮＯ | C8: 日付 | D8: 時間 | E8: 担当 | F8: 受信 事務所 | G8: 媒体 | H8: お名前 （ひらがな記入） | K8: お住まい住所 or アナウンス | L8: 電話番号 | M8: 相談の概要 | N8: 問い合わせ内容 | O8: 対応 | P8: 面談場所 | Q8: 面談備考 | R8: 面談日 | S8: 曜日 | T8: 時間 | U8: 面談担当 | V8: 管理担当 | W8: 面談結果 | X8: 対応
A9: =Y9&Z9 -> 0 | B9: 1 | C9: 46082 | D9: 14：30 | E9: 安井 | F9: 横浜本店 | G9: HP | H9: こばやし えいこ様 | K9: 横浜 | L9: 045-902-2687 | M9: 遺言書 | N9: ★遺言書作成に関するご相談 遺言者：こばやし様 相続人：お姉様 お困りごと：お姉様との関係は良好だが、その子供である甥との関係がよくなく、万が一にもそこに相続権が渡るのが嫌で遺言を書いておきたいとのこと。 公正証書ではなく自筆で検討されているようで、それでも相談に乗っていただけるのか？と聞かれた為、文案の作成という形でお手伝いが可能である旨及びそこで費用が発生する旨お伝えしております。 045-902-2687 | O9: 無料相談にお越しください | P9: 横浜本店 | R9: 46108 | S9: 金 | T9: 13：00 | U9: 渡邉 | W9: Ｓ：即受注 | X9: 事前のヒアリング通りでお姉様の子供（甥）に結果的にも財産が渡らないように遺言を作成したいとのこと。 | Y9: =IF(R9="","", IF(AND(R9<TODAY(),W9=""),"未入力","")) | Z9: =COUNTIF($Y$9:Y9,"未入力") -> 0
A10: =Y10&Z10 -> 0 | B10: 2 | C10: 46082 | D10: 15：20 | E10: 安井 | F10: 横浜本店 | G10: HP | H10: きょう こくりょう様 | K10: 横浜 | L10: 080-9642-5440 | M10: 相続手続き | N10: きょう様は相談者である「ちん ほうりー」様のご友人であり、当事者ではありません。 きょう様は日本に帰化されていますが、ちん様は帰化されておらず、また日本が不自由だそうで、きょう様が代理としてご相談のお電話をくださりました。 当日はちん様ときょう様がお二人で来所され、きょう様が通訳してくださいます。 被相続人：旦那様（日本国籍、令和8年2月2日にご逝去） 相続人：ちん様、娘様（日本国籍、14歳） 相続財産：ご自宅とマンション4部屋、預金200万円、株式100万円 お困りごと：旦那様の相続手続きを別の司法書士に依頼したそうですが、日本語が不自由なちん様が、あまり内容を理解されないままに契約をしてしまったとのこと。その後、手続費用がトータルで100万円掛かると言われ、そんなにするものなのか？と不安を抱かれたようで、ちん様がきょう様に他に頼めるところが無いか探して欲しいとお願いされたことで、セカンドオピニオン的にお電話くださったようです。 あまりあからさまにその司法書士に仕事を奪ったと思われるのはよくないと思われるので、あくまでも参考程度でお見積りを出しますとお伝えしております。 当日は納税通知書をお持ちいただける予定です。 080-9642-5440 | O10: 無料相談にお越しください | P10: 横浜本店 | R10: 46085 | S10: 水 | T10: 10：00 | U10: 嶋津 | W10: Ａ：見込み高・後追い要 | X10: 相続手続一式、特別代理人選任申立手続費用として、報酬482,900円と経費約20万円程度かかる旨ご説明しました。 一旦ご検討いただき、お客様からご連絡をいただけることになりました。 | Y10: =IF(R10="","", IF(AND(R10<TODAY(),W10=""),"未入力","")) | Z10: =COUNTIF($Y$9:Y10,"未入力") -> 0
